Workbook

Sheet README_SOTP
B2: Vinci SA — Sum-of-the-parts valuation model (valuation date 30 Jun 2026 · price as of 16 Sep 2026)
B4: Investment logic
B5: Vinci is a portfolio of assets with very different economics: French motorway concessions that revert to the State at no cost (Escota 2032, Cofiroute 2034, ASF 2036), long-dated or freehold airports, and going-concern energy and construction businesses.
B6: A single perpetual DCF cannot capture finite contract lives, so each business is valued separately with the method that fits its legal and economic nature, then aggregated.
B7: Architecture
B8: Finite concessions (Autoroutes, OMA, other airports, other concessions): cash flows to contract end, TV = 0 — the same approach Vinci uses in its own impairment tests (FS 2025, Note E).
B9: Going concerns (freehold Gatwick + Edinburgh, VINCI Energies, Cobra IS, VINCI Construction): explicit forecast + Gordon TV with normalised capex. VINCI Immobilier at book capital employed.
B10: Each block has its own discount rate. Bridge at 30 Jun 2026: net debt, equity-method investments, net-of-tax pensions, third-party shares of Gatwick/Edinburgh/OMA on implied equity value, other minorities at book. Lease repayments sit inside FCF, so lease liabilities are not deducted.
B11: Sheets: Inputs → Autoroutes / Airports / Other_Concessions / Energy_Construction → SOTP (valuation, per-share build, checks, sensitivity). Historicals holds the FY2023–25 statements.
B12: Sources: VINCI FY2025 consolidated financial statements (Notes C.1.2, E, F.12, I.23.5, 29); 2025 Universal Registration Document (portfolio table, revenue by network); Half-year financial report 2026.
B13: Known limitations
B14: 1) No network-level accounts for ASF/Escota/Cofiroute: segment margins, capex and D&A applied pro rata to revenue. 2) Airport margins are segment averages. 3) "Other airports" and "Other concessions" use one weighted end date each.
... B16: 6) Discount rates are judgement inputs (yellow) — see SOTP sensitivity. 7) Cobra IS renewables EBITDA from current build-out not modelled explicitly.

Sheet SOTP
B2: Vinci SA — Sum-of-the-parts valuation (EUR m)
B3: =CONCATENATE("Valuation date ",TEXT(Inputs!$C$5,"dd-mmm-yyyy")," · balance sheet at 30 Jun 2026 · lease repayments inside FCF") -> Valuation date 30-Jun-2026 · balance sheet at 30 Jun 2026 · lease repayments inside FCF
B5: Block | C5: Method | D5: Life / TV | E5: WACC | F5: EV (100%) | G5: % of EV | H5: EV/EBITDA 26E
B6: ASF | C6: Finite-life DCF, TV = 0 | D6: Ends 2036 | E6: =Autoroutes!$C$12 -> 0.065 | F6: =Autoroutes!$C$38 -> 16324.916 | G6: =F6/$F$18 -> 0.16871021 | H6: =Autoroutes!$C$40 -> 5.8891906
B7: Escota | C7: Finite-life DCF, TV = 0 | D7: Ends 2032 | E7: =Autoroutes!$C$54 -> 0.065 | F7: =Autoroutes!$C$80 -> 2669.7173 | G7: =F7/$F$18 -> 0.027590252 | H7: =Autoroutes!$C$82 -> 3.9375724
B8: Cofiroute | C8: Finite-life DCF, TV = 0 | D8: Ends 2034 | E8: =Autoroutes!$C$96 -> 0.065 | F8: =Autoroutes!$C$122 -> 5885.7573 | G8: =F8/$F$18 -> 0.060826489 | H8: =Autoroutes!$C$124 -> 4.9538966
B9: Arcour, Arcos & A86 Duplex | C9: Finite-life DCF, TV = 0 | D9: Ends 2070 (A86: 2086) | E9: =Autoroutes!$C$138 -> 0.065 | F9: =Autoroutes!$C$164 -> 1567.1769 | G9: =F9/$F$18 -> 0.016196024 | H9: =Autoroutes!$C$166 -> 13.970359
B10: Gatwick + Edinburgh (freehold, 50.01%) | C10: DCF to 2035 + Gordon TV (freehold) | D10: Freehold | E10: =Airports!$C$12 -> 0.075 | F10: =Airports!$C$38 -> 14949.534 | G10: =F10/$F$18 -> 0.15449628 | H10: =Airports!$C$40 -> 13.279555
B11: OMA Mexico (to 2048, 29.99%) | C11: Finite-life DCF, TV = 0 | D11: Ends 2048 | E11: =Airports!$C$54 -> 0.095 | F11: =Airports!$C$80 -> 3105.9041 | G11: =F11/$F$18 -> 0.032098035 | H11: =Airports!$C$82 -> 7.583845
B12: Other fully consolidated airports (ANA, Aerodom, Lyon, Belgrade, Brazil…) | C12: Finite-life DCF, TV = 0 | D12: Weighted end ~2058 | E12: =Airports!$C$96 -> 0.08 | F12: =Airports!$C$122 -> 14811.109 | G12: =F12/$F$18 -> 0.15306573 | H12: =Airports!$C$124 -> 9.4479866
B13: Other concessions (VINCI Highways etc.) | C13: Finite-life DCF, TV = 0 | D13: Weighted end ~2050 | E13: =Other_Concessions!$C$12 -> 0.08 | F13: =Other_Concessions!$C$38 -> 4138.1812 | G13: =F13/$F$18 -> 0.042766125 | H13: =Other_Concessions!$C$40 -> 11.422989
B14: VINCI Energies | C14: 5-yr DCF + Gordon TV | D14: Going concern | E14: =Energy_Construction!$C$12 -> 0.075 | F14: =Energy_Construction!$C$38 -> 19042.164 | G14: =F14/$F$18 -> 0.19679166 | H14: =Energy_Construction!$C$40 -> 8.859419
B15: Cobra IS | C15: 5-yr DCF + Gordon TV | D15: Going concern | E15: =Energy_Construction!$C$54 -> 0.09 | F15: =Energy_Construction!$C$80 -> 3821.9922 | G15: =F15/$F$18 -> 0.039498463 | H15: =Energy_Construction!$C$82 -> 4.5873869
B16: VINCI Construction | C16: 5-yr DCF + Gordon TV | D16: Going concern | E16: =Energy_Construction!$C$96 -> 0.08 | F16: =Energy_Construction!$C$122 -> 9338.6104 | G16: =F16/$F$18 -> 0.096510075 | H16: =Energy_Construction!$C$124 -> 4.4205229
B17: VINCI Immobilier | C17: Book capital employed (1.0x) | D17: n.a. | F17: =Inputs!$C$27 -> 1108 | G17: =F17/$F$18 -> 0.01145065
B18: Enterprise value of consolidated businesses | F18: =SUM(F6:F17) -> 96763.062 | G18: =SUM(G6:G17) -> 1 | H18: =F18/(Autoroutes!$D$22+Autoroutes!$D$64+Autoroutes!$D$106+Autoroutes!$D$148+Airports!$D$22+Airports!$D$64+Airports!$D$106+Other_Concessions!$D$22+Energy_Construction!$D$22+Energy_Construction!$D$64+Energy_Construction!$D$106) -> 7.2696232
B20: Plus: equity-method investments (book) | F20: =Inputs!$C$17 -> 2051
B21: Less: net financial debt (30 Jun 2026) | F21: =-Inputs!$C$12 -> -22450
B22: Less: employee-benefit provisions, net of tax | F22: =-Inputs!$C$18*(1-Inputs!$C$11) -> -867.398
B23: Less: third-party share of Gatwick + Edinburgh (implied equity) | F23: =-Inputs!$C$25*MAX(0,F10-Inputs!$C$23) -> -2087.8491
B24: Less: third-party share of OMA (implied equity) | F24: =-Inputs!$C$26*MAX(0,F11-Inputs!$C$24) -> -1242.6104
B25: Less: other non-controlling interests (book) | F25: =-(Inputs!$C$19-Inputs!$C$20-Inputs!$C$21-Inputs!$C$22) -> -670
B26: EQUITY VALUE attributable to Vinci shareholders | F26: =F18+SUM(F20:F25) -> 71496.204
B27: Diluted shares (m) = issued × (1 − treasury %) + performance shares | F27: =Inputs!$C$7*(1-Inputs!$C$8)+Inputs!$C$9 -> 561.91309
B28: IMPLIED VALUE PER SHARE (EUR) | F28: =F26/F27 -> 127.23712
B29: Current share price (EUR) — see Inputs | F29: =Inputs!$C$6 -> 112.3
B30: Implied upside / (downside) | F30: =F28/F29-1 -> 0.13301089
B33: Value per share by block (EUR, before bridge items)
B34: ASF | F34: =F6/$F$27 -> 29.052387
B35: Escota | F35: =F7/$F$27 -> 4.7511214
B36: Cofiroute | F36: =F8/$F$27 -> 10.474498
B37: Arcour, Arcos & A86 Duplex | F37: =F9/$F$27 -> 2.7890023
B38: Gatwick + Edinburgh (freehold, 50.01%) | F38: =F10/$F$27 -> 26.604708
B39: OMA Mexico (to 2048, 29.99%) | F39: =F11/$F$27 -> 5.5273746
B40: Other fully consolidated airports (ANA, Aerodom, Lyon, Belgrade, Brazil…) | F40: =F12/$F$27 -> 26.358362
B41: Other concessions (VINCI Highways etc.) | F41: =F13/$F$27 -> 7.3644507
B42: VINCI Energies | F42: =F14/$F$27 -> 33.888095
B43: Cobra IS | F43: =F15/$F$27 -> 6.8017498
B44: VINCI Construction | F44: =F16/$F$27 -> 16.619315
B45: VINCI Immobilier + bridge items per share | F45: =(F17+SUM(F20:F25))/$F$27 -> -42.99394
B46: Total (ties to implied value per share) | F46: =SUM(F34:F45) -> 127.23712
B48: MODEL INTEGRITY CHECKS (a failed check shows REVISAR)
B49: Segment net debt ties to group net debt | F49: =Inputs!$C$30 -> OK
B50: Every block: WACC > g, no cash flow after concession end | F50: =IF(AND(Autoroutes!$C$43="OK",Autoroutes!$C$85="OK",Autoroutes!$C$127="OK",Autoroutes!$C$169="OK",Airports!$C$43="OK",Airports!$C$85="OK",Airports!$C$127="OK",Other_Concessions!$C$43="OK",Energy_Construction!$C$43="OK",Energy_Construction!$C$85="OK",Energy_Construction!$C$127="OK"),"OK","REVISAR") -> OK
B51: Per-share build ties to implied value | F51: =IF(ABS(F46-F28)<0.01,"OK","REVISAR") -> OK
B52: Implied value within ±40% of market price (else needs explicit thesis) | F52: =IF(ABS(F30)<=0.4,"OK","REVISAR") -> OK
B53: Group EV / FY2026E EBITDA between 6x and 14x | F53: =IF(AND(H18>=6,H18<=14),"OK","REVISAR") -> OK
B54: No finite concession carries a terminal value | F54: =IF(Autoroutes!$C$13*Autoroutes!$C$41+Autoroutes!$C$55*Autoroutes!$C$83+Autoroutes!$C$97*Autoroutes!$C$125+Autoroutes!$C$139*Autoroutes!$C$167+Airports!$C$13*Airports!$C$41+Airports!$C$55*Airports!$C$83+Airports!$C$97*Airports!$C$125+Other_Concessions!$C$13*Other_Concessions!$C$41+Energy_Construction!$C$13*Energy_Construction!$C$41+Energy_Construction!$C$55*Energy_Construction!$C$83+Energy_Construction!$C$97*Energy_Construction!$C$125=0,"OK","REVISAR") -> OK
B57: SENSITIVITY — implied value per share (EUR): parallel WACC shift (rows) × terminal-growth shift for going concerns (columns)
C58: -0.005 | D58: 0 | E58: 0.005
B59: -0.01 | C59: =((SUMPRODUCT(Autoroutes!$D$29:$AV$29/(1+Autoroutes!$C$12+$B59)^Autoroutes!$D$30:$AV$30)+IF(Autoroutes!$C$13=0,Autoroutes!$C$41*(1+Autoroutes!$C$16+C$58)/(Autoroutes!$C$12+$B59-Autoroutes!$C$16-C$58)/(1+Autoroutes!$C$12+$B59)^Autoroutes!$C$42,0))+(SUMPRODUCT(Autoroutes!$D$71:$AV$71/(1+Autoroutes!$C$54+$B59)^Autoroutes!$D$72:$AV$72)+IF(Autoroutes!$C$55=0,Autoroutes!$C$83*(1+Autoroutes!$C$58+C$58)/(Autoroutes!$C$54+$B59-Autoroutes!$C$58-C$58)/(1+Autoroutes!$C$54+$B59)^Autoroutes!$C$84,0))+(SUMPRODUCT(Autoroutes!$D$113:$AV$113/(1+Autoroutes!$C$96+$B59)^Autoroutes!$D$114:$AV$114)+IF(Autoroutes!$C$97=0,Autoroutes!$C$125*(1+Autoroutes!$C$100+C$58)/(Autoroutes!$C$96+$B59-Autoroutes!$C$100-C$58)/(1+Autoroutes!$C$96+$B59)^Autoroutes!$C$126,0))+(SUMPRODUCT(Autoroutes!$D$155:$AV$155/(1+Autoroutes!$C$138+$B59)^Autoroutes!$D$156:$AV$156)+IF(Autoroutes!$C$139=0,Autoroutes!$C$167*(1+Autoroutes!$C$142+C$58)/(Autoroutes!$C$138+$B59-Autoroutes!$C$142-C$58)/(1+Autoroutes!$C$138+$B59)^Autoroutes!$C$168,0))+(SUMPRODUCT(Airports!$D$29:$AV$29/(1+Airports!$C$12+$B59)^Airports!$D$30:$AV$30)+IF(Airports!$C$13=0,Airports!$C$41*(1+Airports!$C$16+C$58)/(Airports!$C$12+$B59-Airports!$C$16-C$58)/(1+Airports!$C$12+$B59)^Airports!$C$42,0))+(SUMPRODUCT(Airports!$D$71:$AV$71/(1+Airports!$C$54+$B59)^Airports!$D$72:$AV$72)+IF(Airports!$C$55=0,Airports!$C$83*(1+Airports!$C$58+C$58)/(Airports!$C$54+$B59-Airports!$C$58-C$58)/(1+Airports!$C$54+$B59)^Airports!$C$84,0))+(SUMPRODUCT(Airports!$D$113:$AV$113/(1+Airports!$C$96+$B59)^Airports!$D$114:$AV$114)+IF(Airports!$C$97=0,Airports!$C$125*(1+Airports!$C$100+C$58)/(Airports!$C$96+$B59-Airports!$C$100-C$58)/(1+Airports!$C$96+$B59)^Airports!$C$126,0))+(SUMPRODUCT(Other_Concessions!$D$29:$AV$29/(1+Other_Concessions!$C$12+$B59)^Other_Concessions!$D$30:$AV$30)+IF(Other_Concessions!$C$13=0,Other_Concessions!$C$41*(1+Other_Concessions!$C$16+C$58)/(Other_Concessions!$C$12+$B59-Other_Concessions!$C$16-C$58)/(1+Other_Concessions!$C$12+$B59)^Other_Concessions!$C$42,0))+(SUMPRODUCT(Energy_Construction!$D$29:$AV$29/(1+Energy_Construction!$C$12+$B59)^Energy_Construction!$D$30:$AV$30)+IF(Energy_Construction!$C$13=0,Energy_Construction!$C$41*(1+Energy_Construction!$C$16+C$58)/(Energy_Construction!$C$12+$B59-Energy_Construction!$C$16-C$58)/(1+Energy_Construction!$C$12+$B59)^Energy_Construction!$C$42,0))+(SUMPRODUCT(Energy_Construction!$D$71:$AV$71/(1+Energy_Construction!$C$54+$B59)^Energy_Construction!$D$72:$AV$72)+IF(Energy_Construction!$C$55=0,Energy_Construction!$C$83*(1+Energy_Construction!$C$58+C$58)/(Energy_Construction!$C$54+$B59-Energy_Construction!$C$58-C$58)/(1+Energy_Construction!$C$54+$B59)^Energy_Construction!$C$84,0))+(SUMPRODUCT(Energy_Construction!$D$113:$AV$113/(1+Energy_Construction!$C$96+$B59)^Energy_Construction!$D$114:$AV$114)+IF(Energy_Construction!$C$97=0,Energy_Construction!$C$125*(1+Energy_Construction!$C$100+C$58)/(Energy_Construction!$C$96+$B59-Energy_Construction!$C$100-C$58)/(1+Energy_Construction!$C$96+$B59)^Energy_Construction!$C$126,0))+(F17+F20+F21+F22+F25)-Inputs!$C$25*MAX(0,(SUMPRODUCT(Airports!$D$29:$AV$29/(1+Airports!$C$12+$B59)^Airports!$D$30:$AV$30)+IF(Airports!$C$13=0,Airports!$C$41*(1+Airports!$C$16+C$58)/(Airports!$C$12+$B59-Airports!$C$16-C$58)/(1+Airports!$C$12+$B59)^Airports!$C$42,0))-Inputs!$C$23)-Inputs!$C$26*MAX(0,(SUMPRODUCT(Airports!$D$71:$AV$71/(1+Airports!$C$54+$B59)^Airports!$D$72:$AV$72)+IF(Airports!$C$55=0,Airports!$C$83*(1+Airports!$C$58+C$58)/(Airports!$C$54+$B59-Airports!$C$58-C$58)/(1+Airports!$C$54+$B59)^Airports!$C$84,0))-Inputs!$C$24))/$F$27 -> 142.04095 | D59: =((SUMPRODUCT(Autoroutes!$D$29:$AV$29/(1+Autoroutes!$C$12+$B59)^Autoroutes!$D$30:$AV$30)+IF(Autoroutes!$C$13=0,Autoroutes!$C$41*(1+Autoroutes!$C$16+D$58)/(Autoroutes!$C$12+$B59-Autoroutes!$C$16-D$58)/(1+Autoroutes!$C$12+$B59)^Autoroutes!$C$42,0))+(SUMPRODUCT(Autoroutes!$D$71:$AV$71/(1+Autoroutes!$C$54+$B59)^Autoroutes!$D$72:$AV$72)+IF(Autoroutes!$C$55=0,Autoroutes!$C$83*(1+Autoroutes!$C$58+D$58)/(Autoroutes!$C$54+$B59-Autoroutes!$C$58-D$58)/(1+Autoroutes!$C$54+$B59)^Autoroutes!$C$84,0))+(SUMPRODUCT(Autoroutes!$D$113:$AV$113/(1+Autoroutes!$C$96+$B59)^Autoroutes!$D$114:$AV$114)+IF(Autoroutes!$C$97=0,Autoroutes!$C$125*(1+Autoroutes!$C$100+D$58)/(Autoroutes!$C$96+$B59-Autoroutes!$C$100-D$58)/(1+Autoroutes!$C$96+$B59)^Autoroutes!$C$126,0))+(SUMPRODUCT(Autoroutes!$D$155:$AV$155/(1+Autoroutes!$C$138+$B59)^Autoroutes!$D$156:$AV$156)+IF(Autoroutes!$C$139=0,Autoroutes!$C$167*(1+Autoroutes!$C$142+D$58)/(Autoroutes!$C$138+$B59-Autoroutes!$C$142-D$58)/(1+Autoroutes!$C$138+$B59)^Autoroutes!$C$168,0))+(SUMPRODUCT(Airports!$D$29:$AV$29/(1+Airports!$C$12+$B59)^Airports!$D$30:$AV$30)+IF(Airports!$C$13=0,Airports!$C$41*(1+Airports!$C$16+D$58)/(Airports!$C$12+$B59-Airports!$C$16-D$58)/(1+Airports!$C$12+$B59)^Airports!$C$42,0))+(SUMPRODUCT(Airports!$D$71:$AV$71/(1+Airports!$C$54+$B59)^Airports!$D$72:$AV$72)+IF(Airports!$C$55=0,Airports!$C$83*(1+Airports!$C$58+D$58)/(Airports!$C$54+$B59-Airports!$C$58-D$58)/(1+Airports!$C$54+$B59)^Airports!$C$84,0))+(SUMPRODUCT(Airports!$D$113:$AV$113/(1+Airports!$C$96+$B59)^Airports!$D$114:$AV$114)+IF(Airports!$C$97=0,Airports!$C$125*(1+Airports!$C$100+D$58)/(Airports!$C$96+$B59-Airports!$C$100-D$58)/(1+Airports!$C$96+$B59)^Airports!$C$126,0))+(SUMPRODUCT(Other_Concessions!$D$29:$AV$29/(1+Other_Concessions!$C$12+$B59)^Other_Concessions!$D$30:$AV$30)+IF(Other_Concessions!$C$13=0,Other_Concessions!$C$41*(1+Other_Concessions!$C$16+D$58)/(Other_Concessions!$C$12+$B59-Other_Concessions!$C$16-D$58)/(1+Other_Concessions!$C$12+$B59)^Other_Concessions!$C$42,0))+(SUMPRODUCT(Energy_Construction!$D$29:$AV$29/(1+Energy_Construction!$C$12+$B59)^Energy_Construction!$D$30:$AV$30)+IF(Energy_Construction!$C$13=0,Energy_Construction!$C$41*(1+Energy_Construction!$C$16+D$58)/(Energy_Construction!$C$12+$B59-Energy_Construction!$C$16-D$58)/(1+Energy_Construction!$C$12+$B59)^Energy_Construction!$C$42,0))+(SUMPRODUCT(Energy_Construction!$D$71:$AV$71/(1+Energy_Construction!$C$54+$B59)^Energy_Construction!$D$72:$AV$72)+IF(Energy_Construction!$C$55=0,Energy_Construction!$C$83*(1+Energy_Construction!$C$58+D$58)/(Energy_Construction!$C$54+$B59-Energy_Construction!$C$58-D$58)/(1+Energy_Construction!$C$54+$B59)^Energy_Construction!$C$84,0))+(SUMPRODUCT(Energy_Construction!$D$113:$AV$113/(1+Energy_Construction!$C$96+$B59)^Energy_Construction!$D$114:$AV$114)+IF(Energy_Construction!$C$97=0,Energy_Construction!$C$125*(1+Energy_Construction!$C$100+D$58)/(Energy_Construction!$C$96+$B59-Energy_Construction!$C$100-D$58)/(1+Energy_Construction!$C$96+$B59)^Energy_Construction!$C$126,0))+(F17+F20+F21+F22+F25)-Inputs!$C$25*MAX(0,(SUMPRODUCT(Airports!$D$29:$AV$29/(1+Airports!$C$12+$B59)^Airports!$D$30:$AV$30)+IF(Airports!$C$13=0,Airports!$C$41*(1+Airports!$C$16+D$58)/(Airports!$C$12+$B59-Airports!$C$16-D$58)/(1+Airports!$C$12+$B59)^Airports!$C$42,0))-Inputs!$C$23)-Inputs!$C$26*MAX(0,(SUMPRODUCT(Airports!$D$71:$AV$71/(1+Airports!$C$54+$B59)^Airports!$D$72:$AV$72)+IF(Airports!$C$55=0,Airports!$C$83*(1+Airports!$C$58+D$58)/(Airports!$C$54+$B59-Airports!$C$58-D$58)/(1+Airports!$C$54+$B59)^Airports!$C$84,0))-Inputs!$C$24))/$F$27 -> 149.01429 | E59: =((SUMPRODUCT(Autoroutes!$D$29:$AV$29/(1+Autoroutes!$C$12+$B59)^Autoroutes!$D$30:$AV$30)+IF(Autoroutes!$C$13=0,Autoroutes!$C$41*(1+Autoroutes!$C$16+E$58)/(Autoroutes!$C$12+$B59-Autoroutes!$C$16-E$58)/(1+Autoroutes!$C$12+$B59)^Autoroutes!$C$42,0))+(SUMPRODUCT(Autoroutes!$D$71:$AV$71/(1+Autoroutes!$C$54+$B59)^Autoroutes!$D$72:$AV$72)+IF(Autoroutes!$C$55=0,Autoroutes!$C$83*(1+Autoroutes!$C$58+E$58)/(Autoroutes!$C$54+$B59-Autoroutes!$C$58-E$58)/(1+Autoroutes!$C$54+$B59)^Autoroutes!$C$84,0))+(SUMPRODUCT(Autoroutes!$D$113:$AV$113/(1+Autoroutes!$C$96+$B59)^Autoroutes!$D$114:$AV$114)+IF(Autoroutes!$C$97=0,Autoroutes!$C$125*(1+Autoroutes!$C$100+E$58)/(Autoroutes!$C$96+$B59-Autoroutes!$C$100-E$58)/(1+Autoroutes!$C$96+$B59)^Autoroutes!$C$126,0))+(SUMPRODUCT(Autoroutes!$D$155:$AV$155/(1+Autoroutes!$C$138+$B59)^Autoroutes!$D$156:$AV$156)+IF(Autoroutes!$C$139=0,Autoroutes!$C$167*(1+Autoroutes!$C$142+E$58)/(Autoroutes!$C$138+$B59-Autoroutes!$C$142-E$58)/(1+Autoroutes!$C$138+$B59)^Autoroutes!$C$168,0))+(SUMPRODUCT(Airports!$D$29:$AV$29/(1+Airports!$C$12+$B59)^Airports!$D$30:$AV$30)+IF(Airports!$C$13=0,Airports!$C$41*(1+Airports!$C$16+E$58)/(Airports!$C$12+$B59-Airports!$C$16-E$58)/(1+Airports!$C$12+$B59)^Airports!$C$42,0))+(SUMPRODUCT(Airports!$D$71:$AV$71/(1+Airports!$C$54+$B59)^Airports!$D$72:$AV$72)+IF(Airports!$C$55=0,Airports!$C$83*(1+Airports!$C$58+E$58)/(Airports!$C$54+$B59-Airports!$C$58-E$58)/(1+Airports!$C$54+$B59)^Airports!$C$84,0))+(SUMPRODUCT(Airports!$D$113:$AV$113/(1+Airports!$C$96+$B59)^Airports!$D$114:$AV$114)+IF(Airports!$C$97=0,Airports!$C$125*(1+Airports!$C$100+E$58)/(Airports!$C$96+$B59-Airports!$C$100-E$58)/(1+Airports!$C$96+$B59)^Airports!$C$126,0))+(SUMPRODUCT(Other_Concessions!$D$29:$AV$29/(1+Other_Concessions!$C$12+$B59)^Other_Concessions!$D$30:$AV$30)+IF(Other_Concessions!$C$13=0,Other_Concessions!$C$41*(1+Other_Concessions!$C$16+E$58)/(Other_Concessions!$C$12+$B59-Other_Concessions!$C$16-E$58)/(1+Other_Concessions!$C$12+$B59)^Other_Concessions!$C$42,0))+(SUMPRODUCT(Energy_Construction!$D$29:$AV$29/(1+Energy_Construction!$C$12+$B59)^Energy_Construction!$D$30:$AV$30)+IF(Energy_Construction!$C$13=0,Energy_Construction!$C$41*(1+Energy_Construction!$C$16+E$58)/(Energy_Construction!$C$12+$B59-Energy_Construction!$C$16-E$58)/(1+Energy_Construction!$C$12+$B59)^Energy_Construction!$C$42,0))+(SUMPRODUCT(Energy_Construction!$D$71:$AV$71/(1+Energy_Construction!$C$54+$B59)^Energy_Construction!$D$72:$AV$72)+IF(Energy_Construction!$C$55=0,Energy_Construction!$C$83*(1+Energy_Construction!$C$58+E$58)/(Energy_Construction!$C$54+$B59-Energy_Construction!$C$58-E$58)/(1+Energy_Construction!$C$54+$B59)^Energy_Construction!$C$84,0))+(SUMPRODUCT(Energy_Construction!$D$113:$AV$113/(1+Energy_Construction!$C$96+$B59)^Energy_Construction!$D$114:$AV$114)+IF(Energy_Construction!$C$97=0,Energy_Construction!$C$125*(1+Energy_Construction!$C$100+E$58)/(Energy_Construction!$C$96+$B59-Energy_Construction!$C$100-E$58)/(1+Energy_Construction!$C$96+$B59)^Energy_Construction!$C$126,0))+(F17+F20+F21+F22+F25)-Inputs!$C$25*MAX(0,(SUMPRODUCT(Airports!$D$29:$AV$29/(1+Airports!$C$12+$B59)^Airports!$D$30:$AV$30)+IF(Airports!$C$13=0,Airports!$C$41*(1+Airports!$C$16+E$58)/(Airports!$C$12+$B59-Airports!$C$16-E$58)/(1+Airports!$C$12+$B59)^Airports!$C$42,0))-Inputs!$C$23)-Inputs!$C$26*MAX(0,(SUMPRODUCT(Airports!$D$71:$AV$71/(1+Airports!$C$54+$B59)^Airports!$D$72:$AV$72)+IF(Airports!$C$55=0,Airports!$C$83*(1+Airports!$C$58+E$58)/(Airports!$C$54+$B59-Airports!$C$58-E$58)/(1+Airports!$C$54+$B59)^Airports!$C$84,0))-Inputs!$C$24))/$F$27 -> 157.60149
B60: -0.005 | C60: =((SUMPRODUCT(Autoroutes!$D$29:$AV$29/(1+Autoroutes!$C$12+$B60)^Autoroutes!$D$30:$AV$30)+IF(Autoroutes!$C$13=0,Autoroutes!$C$41*(1+Autoroutes!$C$16+C$58)/(Autoroutes!$C$12+$B60-Autoroutes!$C$16-C$58)/(1+Autoroutes!$C$12+$B60)^Autoroutes!$C$42,0))+(SUMPRODUCT(Autoroutes!$D$71:$AV$71/(1+Autoroutes!$C$54+$B60)^Autoroutes!$D$72:$AV$72)+IF(Autoroutes!$C$55=0,Autoroutes!$C$83*(1+Autoroutes!$C$58+C$58)/(Autoroutes!$C$54+$B60-Autoroutes!$C$58-C$58)/(1+Autoroutes!$C$54+$B60)^Autoroutes!$C$84,0))+(SUMPRODUCT(Autoroutes!$D$113:$AV$113/(1+Autoroutes!$C$96+$B60)^Autoroutes!$D$114:$AV$114)+IF(Autoroutes!$C$97=0,Autoroutes!$C$125*(1+Autoroutes!$C$100+C$58)/(Autoroutes!$C$96+$B60-Autoroutes!$C$100-C$58)/(1+Autoroutes!$C$96+$B60)^Autoroutes!$C$126,0))+(SUMPRODUCT(Autoroutes!$D$155:$AV$155/(1+Autoroutes!$C$138+$B60)^Autoroutes!$D$156:$AV$156)+IF(Autoroutes!$C$139=0,Autoroutes!$C$167*(1+Autoroutes!$C$142+C$58)/(Autoroutes!$C$138+$B60-Autoroutes!$C$142-C$58)/(1+Autoroutes!$C$138+$B60)^Autoroutes!$C$168,0))+(SUMPRODUCT(Airports!$D$29:$AV$29/(1+Airports!$C$12+$B60)^Airports!$D$30:$AV$30)+IF(Airports!$C$13=0,Airports!$C$41*(1+Airports!$C$16+C$58)/(Airports!$C$12+$B60-Airports!$C$16-C$58)/(1+Airports!$C$12+$B60)^Airports!$C$42,0))+(SUMPRODUCT(Airports!$D$71:$AV$71/(1+Airports!$C$54+$B60)^Airports!$D$72:$AV$72)+IF(Airports!$C$55=0,Airports!$C$83*(1+Airports!$C$58+C$58)/(Airports!$C$54+$B60-Airports!$C$58-C$58)/(1+Airports!$C$54+$B60)^Airports!$C$84,0))+(SUMPRODUCT(Airports!$D$113:$AV$113/(1+Airports!$C$96+$B60)^Airports!$D$114:$AV$114)+IF(Airports!$C$97=0,Airports!$C$125*(1+Airports!$C$100+C$58)/(Airports!$C$96+$B60-Airports!$C$100-C$58)/(1+Airports!$C$96+$B60)^Airports!$C$126,0))+(SUMPRODUCT(Other_Concessions!$D$29:$AV$29/(1+Other_Concessions!$C$12+$B60)^Other_Concessions!$D$30:$AV$30)+IF(Other_Concessions!$C$13=0,Other_Concessions!$C$41*(1+Other_Concessions!$C$16+C$58)/(Other_Concessions!$C$12+$B60-Other_Concessions!$C$16-C$58)/(1+Other_Concessions!$C$12+$B60)^Other_Concessions!$C$42,0))+(SUMPRODUCT(Energy_Construction!$D$29:$AV$29/(1+Energy_Construction!$C$12+$B60)^Energy_Construction!$D$30:$AV$30)+IF(Energy_Construction!$C$13=0,Energy_Construction!$C$41*(1+Energy_Construction!$C$16+C$58)/(Energy_Construction!$C$12+$B60-Energy_Construction!$C$16-C$58)/(1+Energy_Construction!$C$12+$B60)^Energy_Construction!$C$42,0))+(SUMPRODUCT(Energy_Construction!$D$71:$AV$71/(1+Energy_Construction!$C$54+$B60)^Energy_Construction!$D$72:$AV$72)+IF(Energy_Construction!$C$55=0,Energy_Construction!$C$83*(1+Energy_Construction!$C$58+C$58)/(Energy_Construction!$C$54+$B60-Energy_Construction!$C$58-C$58)/(1+Energy_Construction!$C$54+$B60)^Energy_Construction!$C$84,0))+(SUMPRODUCT(Energy_Construction!$D$113:$AV$113/(1+Energy_Construction!$C$96+$B60)^Energy_Construction!$D$114:$AV$114)+IF(Energy_Construction!$C$97=0,Energy_Construction!$C$125*(1+Energy_Construction!$C$100+C$58)/(Energy_Construction!$C$96+$B60-Energy_Construction!$C$100-C$58)/(1+Energy_Construction!$C$96+$B60)^Energy_Construction!$C$126,0))+(F17+F20+F21+F22+F25)-Inputs!$C$25*MAX(0,(SUMPRODUCT(Airports!$D$29:$AV$29/(1+Airports!$C$12+$B60)^Airports!$D$30:$AV$30)+IF(Airports!$C$13=0,Airports!$C$41*(1+Airports!$C$16+C$58)/(Airports!$C$12+$B60-Airports!$C$16-C$58)/(1+Airports!$C$12+$B60)^Airports!$C$42,0))-Inputs!$C$23)-Inputs!$C$26*MAX(0,(SUMPRODUCT(Airports!$D$71:$AV$71/(1+Airports!$C$54+$B60)^Airports!$D$72:$AV$72)+IF(Airports!$C$55=0,Airports!$C$83*(1+Airports!$C$58+C$58)/(Airports!$C$54+$B60-Airports!$C$58-C$58)/(1+Airports!$C$54+$B60)^Airports!$C$84,0))-Inputs!$C$24))/$F$27 -> 131.60949 | D60: =((SUMPRODUCT(Autoroutes!$D$29:$AV$29/(1+Autoroutes!$C$12+$B60)^Autoroutes!$D$30:$AV$30)+IF(Autoroutes!$C$13=0,Autoroutes!$C$41*(1+Autoroutes!$C$16+D$58)/(Autoroutes!$C$12+$B60-Autoroutes!$C$16-D$58)/(1+Autoroutes!$C$12+$B60)^Autoroutes!$C$42,0))+(SUMPRODUCT(Autoroutes!$D$71:$AV$71/(1+Autoroutes!$C$54+$B60)^Autoroutes!$D$72:$AV$72)+IF(Autoroutes!$C$55=0,Autoroutes!$C$83*(1+Autoroutes!$C$58+D$58)/(Autoroutes!$C$54+$B60-Autoroutes!$C$58-D$58)/(1+Autoroutes!$C$54+$B60)^Autoroutes!$C$84,0))+(SUMPRODUCT(Autoroutes!$D$113:$AV$113/(1+Autoroutes!$C$96+$B60)^Autoroutes!$D$114:$AV$114)+IF(Autoroutes!$C$97=0,Autoroutes!$C$125*(1+Autoroutes!$C$100+D$58)/(Autoroutes!$C$96+$B60-Autoroutes!$C$100-D$58)/(1+Autoroutes!$C$96+$B60)^Autoroutes!$C$126,0))+(SUMPRODUCT(Autoroutes!$D$155:$AV$155/(1+Autoroutes!$C$138+$B60)^Autoroutes!$D$156:$AV$156)+IF(Autoroutes!$C$139=0,Autoroutes!$C$167*(1+Autoroutes!$C$142+D$58)/(Autoroutes!$C$138+$B60-Autoroutes!$C$142-D$58)/(1+Autoroutes!$C$138+$B60)^Autoroutes!$C$168,0))+(SUMPRODUCT(Airports!$D$29:$AV$29/(1+Airports!$C$12+$B60)^Airports!$D$30:$AV$30)+IF(Airports!$C$13=0,Airports!$C$41*(1+Airports!$C$16+D$58)/(Airports!$C$12+$B60-Airports!$C$16-D$58)/(1+Airports!$C$12+$B60)^Airports!$C$42,0))+(SUMPRODUCT(Airports!$D$71:$AV$71/(1+Airports!$C$54+$B60)^Airports!$D$72:$AV$72)+IF(Airports!$C$55=0,Airports!$C$83*(1+Airports!$C$58+D$58)/(Airports!$C$54+$B60-Airports!$C$58-D$58)/(1+Airports!$C$54+$B60)^Airports!$C$84,0))+(SUMPRODUCT(Airports!$D$113:$AV$113/(1+Airports!$C$96+$B60)^Airports!$D$114:$AV$114)+IF(Airports!$C$97=0,Airports!$C$125*(1+Airports!$C$100+D$58)/(Airports!$C$96+$B60-Airports!$C$100-D$58)/(1+Airports!$C$96+$B60)^Airports!$C$126,0))+(SUMPRODUCT(Other_Concessions!$D$29:$AV$29/(1+Other_Concessions!$C$12+$B60)^Other_Concessions!$D$30:$AV$30)+IF(Other_Concessions!$C$13=0,Other_Concessions!$C$41*(1+Other_Concessions!$C$16+D$58)/(Other_Concessions!$C$12+$B60-Other_Concessions!$C$16-D$58)/(1+Other_Concessions!$C$12+$B60)^Other_Concessions!$C$42,0))+(SUMPRODUCT(Energy_Construction!$D$29:$AV$29/(1+Energy_Construction!$C$12+$B60)^Energy_Construction!$D$30:$AV$30)+IF(Energy_Construction!$C$13=0,Energy_Construction!$C$41*(1+Energy_Construction!$C$16+D$58)/(Energy_Construction!$C$12+$B60-Energy_Construction!$C$16-D$58)/(1+Energy_Construction!$C$12+$B60)^Energy_Construction!$C$42,0))+(SUMPRODUCT(Energy_Construction!$D$71:$AV$71/(1+Energy_Construction!$C$54+$B60)^Energy_Construction!$D$72:$AV$72)+IF(Energy_Construction!$C$55=0,Energy_Construction!$C$83*(1+Energy_Construction!$C$58+D$58)/(Energy_Construction!$C$54+$B60-Energy_Construction!$C$58-D$58)/(1+Energy_Construction!$C$54+$B60)^Energy_Construction!$C$84,0))+(SUMPRODUCT(Energy_Construction!$D$113:$AV$113/(1+Energy_Construction!$C$96+$B60)^Energy_Construction!$D$114:$AV$114)+IF(Energy_Construction!$C$97=0,Energy_Construction!$C$125*(1+Energy_Construction!$C$100+D$58)/(Energy_Construction!$C$96+$B60-Energy_Construction!$C$100-D$58)/(1+Energy_Construction!$C$96+$B60)^Energy_Construction!$C$126,0))+(F17+F20+F21+F22+F25)-Inputs!$C$25*MAX(0,(SUMPRODUCT(Airports!$D$29:$AV$29/(1+Airports!$C$12+$B60)^Airports!$D$30:$AV$30)+IF(Airports!$C$13=0,Airports!$C$41*(1+Airports!$C$16+D$58)/(Airports!$C$12+$B60-Airports!$C$16-D$58)/(1+Airports!$C$12+$B60)^Airports!$C$42,0))-Inputs!$C$23)-Inputs!$C$26*MAX(0,(SUMPRODUCT(Airports!$D$71:$AV$71/(1+Airports!$C$54+$B60)^Airports!$D$72:$AV$72)+IF(Airports!$C$55=0,Airports!$C$83*(1+Airports!$C$58+D$58)/(Airports!$C$54+$B60-Airports!$C$58-D$58)/(1+Airports!$C$54+$B60)^Airports!$C$84,0))-Inputs!$C$24))/$F$27 -> 137.28478 | E60: =((SUMPRODUCT(Autoroutes!$D$29:$AV$29/(1+Autoroutes!$C$12+$B60)^Autoroutes!$D$30:$AV$30)+IF(Autoroutes!$C$13=0,Autoroutes!$C$41*(1+Autoroutes!$C$16+E$58)/(Autoroutes!$C$12+$B60-Autoroutes!$C$16-E$58)/(1+Autoroutes!$C$12+$B60)^Autoroutes!$C$42,0))+(SUMPRODUCT(Autoroutes!$D$71:$AV$71/(1+Autoroutes!$C$54+$B60)^Autoroutes!$D$72:$AV$72)+IF(Autoroutes!$C$55=0,Autoroutes!$C$83*(1+Autoroutes!$C$58+E$58)/(Autoroutes!$C$54+$B60-Autoroutes!$C$58-E$58)/(1+Autoroutes!$C$54+$B60)^Autoroutes!$C$84,0))+(SUMPRODUCT(Autoroutes!$D$113:$AV$113/(1+Autoroutes!$C$96+$B60)^Autoroutes!$D$114:$AV$114)+IF(Autoroutes!$C$97=0,Autoroutes!$C$125*(1+Autoroutes!$C$100+E$58)/(Autoroutes!$C$96+$B60-Autoroutes!$C$100-E$58)/(1+Autoroutes!$C$96+$B60)^Autoroutes!$C$126,0))+(SUMPRODUCT(Autoroutes!$D$155:$AV$155/(1+Autoroutes!$C$138+$B60)^Autoroutes!$D$156:$AV$156)+IF(Autoroutes!$C$139=0,Autoroutes!$C$167*(1+Autoroutes!$C$142+E$58)/(Autoroutes!$C$138+$B60-Autoroutes!$C$142-E$58)/(1+Autoroutes!$C$138+$B60)^Autoroutes!$C$168,0))+(SUMPRODUCT(Airports!$D$29:$AV$29/(1+Airports!$C$12+$B60)^Airports!$D$30:$AV$30)+IF(Airports!$C$13=0,Airports!$C$41*(1+Airports!$C$16+E$58)/(Airports!$C$12+$B60-Airports!$C$16-E$58)/(1+Airports!$C$12+$B60)^Airports!$C$42,0))+(SUMPRODUCT(Airports!$D$71:$AV$71/(1+Airports!$C$54+$B60)^Airports!$D$72:$AV$72)+IF(Airports!$C$55=0,Airports!$C$83*(1+Airports!$C$58+E$58)/(Airports!$C$54+$B60-Airports!$C$58-E$58)/(1+Airports!$C$54+$B60)^Airports!$C$84,0))+(SUMPRODUCT(Airports!$D$113:$AV$113/(1+Airports!$C$96+$B60)^Airports!$D$114:$AV$114)+IF(Airports!$C$97=0,Airports!$C$125*(1+Airports!$C$100+E$58)/(Airports!$C$96+$B60-Airports!$C$100-E$58)/(1+Airports!$C$96+$B60)^Airports!$C$126,0))+(SUMPRODUCT(Other_Concessions!$D$29:$AV$29/(1+Other_Concessions!$C$12+$B60)^Other_Concessions!$D$30:$AV$30)+IF(Other_Concessions!$C$13=0,Other_Concessions!$C$41*(1+Other_Concessions!$C$16+E$58)/(Other_Concessions!$C$12+$B60-Other_Concessions!$C$16-E$58)/(1+Other_Concessions!$C$12+$B60)^Other_Concessions!$C$42,0))+(SUMPRODUCT(Energy_Construction!$D$29:$AV$29/(1+Energy_Construction!$C$12+$B60)^Energy_Construction!$D$30:$AV$30)+IF(Energy_Construction!$C$13=0,Energy_Construction!$C$41*(1+Energy_Construction!$C$16+E$58)/(Energy_Construction!$C$12+$B60-Energy_Construction!$C$16-E$58)/(1+Energy_Construction!$C$12+$B60)^Energy_Construction!$C$42,0))+(SUMPRODUCT(Energy_Construction!$D$71:$AV$71/(1+Energy_Construction!$C$54+$B60)^Energy_Construction!$D$72:$AV$72)+IF(Energy_Construction!$C$55=0,Energy_Construction!$C$83*(1+Energy_Construction!$C$58+E$58)/(Energy_Construction!$C$54+$B60-Energy_Construction!$C$58-E$58)/(1+Energy_Construction!$C$54+$B60)^Energy_Construction!$C$84,0))+(SUMPRODUCT(Energy_Construction!$D$113:$AV$113/(1+Energy_Construction!$C$96+$B60)^Energy_Construction!$D$114:$AV$114)+IF(Energy_Construction!$C$97=0,Energy_Construction!$C$125*(1+Energy_Construction!$C$100+E$58)/(Energy_Construction!$C$96+$B60-Energy_Construction!$C$100-E$58)/(1+Energy_Construction!$C$96+$B60)^Energy_Construction!$C$126,0))+(F17+F20+F21+F22+F25)-Inputs!$C$25*MAX(0,(SUMPRODUCT(Airports!$D$29:$AV$29/(1+Airports!$C$12+$B60)^Airports!$D$30:$AV$30)+IF(Airports!$C$13=0,Airports!$C$41*(1+Airports!$C$16+E$58)/(Airports!$C$12+$B60-Airports!$C$16-E$58)/(1+Airports!$C$12+$B60)^Airports!$C$42,0))-Inputs!$C$23)-Inputs!$C$26*MAX(0,(SUMPRODUCT(Airports!$D$71:$AV$71/(1+Airports!$C$54+$B60)^Airports!$D$72:$AV$72)+IF(Airports!$C$55=0,Airports!$C$83*(1+Airports!$C$58+E$58)/(Airports!$C$54+$B60-Airports!$C$58-E$58)/(1+Airports!$C$54+$B60)^Airports!$C$84,0))-Inputs!$C$24))/$F$27 -> 144.13302
B61: 0 | C61: =((SUMPRODUCT(Autoroutes!$D$29:$AV$29/(1+Autoroutes!$C$12+$B61)^Autoroutes!$D$30:$AV$30)+IF(Autoroutes!$C$13=0,Autoroutes!$C$41*(1+Autoroutes!$C$16+C$58)/(Autoroutes!$C$12+$B61-Autoroutes!$C$16-C$58)/(1+Autoroutes!$C$12+$B61)^Autoroutes!$C$42,0))+(SUMPRODUCT(Autoroutes!$D$71:$AV$71/(1+Autoroutes!$C$54+$B61)^Autoroutes!$D$72:$AV$72)+IF(Autoroutes!$C$55=0,Autoroutes!$C$83*(1+Autoroutes!$C$58+C$58)/(Autoroutes!$C$54+$B61-Autoroutes!$C$58-C$58)/(1+Autoroutes!$C$54+$B61)^Autoroutes!$C$84,0))+(SUMPRODUCT(Autoroutes!$D$113:$AV$113/(1+Autoroutes!$C$96+$B61)^Autoroutes!$D$114:$AV$114)+IF(Autoroutes!$C$97=0,Autoroutes!$C$125*(1+Autoroutes!$C$100+C$58)/(Autoroutes!$C$96+$B61-Autoroutes!$C$100-C$58)/(1+Autoroutes!$C$96+$B61)^Autoroutes!$C$126,0))+(SUMPRODUCT(Autoroutes!$D$155:$AV$155/(1+Autoroutes!$C$138+$B61)^Autoroutes!$D$156:$AV$156)+IF(Autoroutes!$C$139=0,Autoroutes!$C$167*(1+Autoroutes!$C$142+C$58)/(Autoroutes!$C$138+$B61-Autoroutes!$C$142-C$58)/(1+Autoroutes!$C$138+$B61)^Autoroutes!$C$168,0))+(SUMPRODUCT(Airports!$D$29:$AV$29/(1+Airports!$C$12+$B61)^Airports!$D$30:$AV$30)+IF(Airports!$C$13=0,Airports!$C$41*(1+Airports!$C$16+C$58)/(Airports!$C$12+$B61-Airports!$C$16-C$58)/(1+Airports!$C$12+$B61)^Airports!$C$42,0))+(SUMPRODUCT(Airports!$D$71:$AV$71/(1+Airports!$C$54+$B61)^Airports!$D$72:$AV$72)+IF(Airports!$C$55=0,Airports!$C$83*(1+Airports!$C$58+C$58)/(Airports!$C$54+$B61-Airports!$C$58-C$58)/(1+Airports!$C$54+$B61)^Airports!$C$84,0))+(SUMPRODUCT(Airports!$D$113:$AV$113/(1+Airports!$C$96+$B61)^Airports!$D$114:$AV$114)+IF(Airports!$C$97=0,Airports!$C$125*(1+Airports!$C$100+C$58)/(Airports!$C$96+$B61-Airports!$C$100-C$58)/(1+Airports!$C$96+$B61)^Airports!$C$126,0))+(SUMPRODUCT(Other_Concessions!$D$29:$AV$29/(1+Other_Concessions!$C$12+$B61)^Other_Concessions!$D$30:$AV$30)+IF(Other_Concessions!$C$13=0,Other_Concessions!$C$41*(1+Other_Concessions!$C$16+C$58)/(Other_Concessions!$C$12+$B61-Other_Concessions!$C$16-C$58)/(1+Other_Concessions!$C$12+$B61)^Other_Concessions!$C$42,0))+(SUMPRODUCT(Energy_Construction!$D$29:$AV$29/(1+Energy_Construction!$C$12+$B61)^Energy_Construction!$D$30:$AV$30)+IF(Energy_Construction!$C$13=0,Energy_Construction!$C$41*(1+Energy_Construction!$C$16+C$58)/(Energy_Construction!$C$12+$B61-Energy_Construction!$C$16-C$58)/(1+Energy_Construction!$C$12+$B61)^Energy_Construction!$C$42,0))+(SUMPRODUCT(Energy_Construction!$D$71:$AV$71/(1+Energy_Construction!$C$54+$B61)^Energy_Construction!$D$72:$AV$72)+IF(Energy_Construction!$C$55=0,Energy_Construction!$C$83*(1+Energy_Construction!$C$58+C$58)/(Energy_Construction!$C$54+$B61-Energy_Construction!$C$58-C$58)/(1+Energy_Construction!$C$54+$B61)^Energy_Construction!$C$84,0))+(SUMPRODUCT(Energy_Construction!$D$113:$AV$113/(1+Energy_Construction!$C$96+$B61)^Energy_Construction!$D$114:$AV$114)+IF(Energy_Construction!$C$97=0,Energy_Construction!$C$125*(1+Energy_Construction!$C$100+C$58)/(Energy_Construction!$C$96+$B61-Energy_Construction!$C$100-C$58)/(1+Energy_Construction!$C$96+$B61)^Energy_Construction!$C$126,0))+(F17+F20+F21+F22+F25)-Inputs!$C$25*MAX(0,(SUMPRODUCT(Airports!$D$29:$AV$29/(1+Airports!$C$12+$B61)^Airports!$D$30:$AV$30)+IF(Airports!$C$13=0,Airports!$C$41*(1+Airports!$C$16+C$58)/(Airports!$C$12+$B61-Airports!$C$16-C$58)/(1+Airports!$C$12+$B61)^Airports!$C$42,0))-Inputs!$C$23)-Inputs!$C$26*MAX(0,(SUMPRODUCT(Airports!$D$71:$AV$71/(1+Airports!$C$54+$B61)^Airports!$D$72:$AV$72)+IF(Airports!$C$55=0,Airports!$C$83*(1+Airports!$C$58+C$58)/(Airports!$C$54+$B61-Airports!$C$58-C$58)/(1+Airports!$C$54+$B61)^Airports!$C$84,0))-Inputs!$C$24))/$F$27 -> 122.53983 | D61: =((SUMPRODUCT(Autoroutes!$D$29:$AV$29/(1+Autoroutes!$C$12+$B61)^Autoroutes!$D$30:$AV$30)+IF(Autoroutes!$C$13=0,Autoroutes!$C$41*(1+Autoroutes!$C$16+D$58)/(Autoroutes!$C$12+$B61-Autoroutes!$C$16-D$58)/(1+Autoroutes!$C$12+$B61)^Autoroutes!$C$42,0))+(SUMPRODUCT(Autoroutes!$D$71:$AV$71/(1+Autoroutes!$C$54+$B61)^Autoroutes!$D$72:$AV$72)+IF(Autoroutes!$C$55=0,Autoroutes!$C$83*(1+Autoroutes!$C$58+D$58)/(Autoroutes!$C$54+$B61-Autoroutes!$C$58-D$58)/(1+Autoroutes!$C$54+$B61)^Autoroutes!$C$84,0))+(SUMPRODUCT(Autoroutes!$D$113:$AV$113/(1+Autoroutes!$C$96+$B61)^Autoroutes!$D$114:$AV$114)+IF(Autoroutes!$C$97=0,Autoroutes!$C$125*(1+Autoroutes!$C$100+D$58)/(Autoroutes!$C$96+$B61-Autoroutes!$C$100-D$58)/(1+Autoroutes!$C$96+$B61)^Autoroutes!$C$126,0))+(SUMPRODUCT(Autoroutes!$D$155:$AV$155/(1+Autoroutes!$C$138+$B61)^Autoroutes!$D$156:$AV$156)+IF(Autoroutes!$C$139=0,Autoroutes!$C$167*(1+Autoroutes!$C$142+D$58)/(Autoroutes!$C$138+$B61-Autoroutes!$C$142-D$58)/(1+Autoroutes!$C$138+$B61)^Autoroutes!$C$168,0))+(SUMPRODUCT(Airports!$D$29:$AV$29/(1+Airports!$C$12+$B61)^Airports!$D$30:$AV$30)+IF(Airports!$C$13=0,Airports!$C$41*(1+Airports!$C$16+D$58)/(Airports!$C$12+$B61-Airports!$C$16-D$58)/(1+Airports!$C$12+$B61)^Airports!$C$42,0))+(SUMPRODUCT(Airports!$D$71:$AV$71/(1+Airports!$C$54+$B61)^Airports!$D$72:$AV$72)+IF(Airports!$C$55=0,Airports!$C$83*(1+Airports!$C$58+D$58)/(Airports!$C$54+$B61-Airports!$C$58-D$58)/(1+Airports!$C$54+$B61)^Airports!$C$84,0))+(SUMPRODUCT(Airports!$D$113:$AV$113/(1+Airports!$C$96+$B61)^Airports!$D$114:$AV$114)+IF(Airports!$C$97=0,Airports!$C$125*(1+Airports!$C$100+D$58)/(Airports!$C$96+$B61-Airports!$C$100-D$58)/(1+Airports!$C$96+$B61)^Airports!$C$126,0))+(SUMPRODUCT(Other_Concessions!$D$29:$AV$29/(1+Other_Concessions!$C$12+$B61)^Other_Concessions!$D$30:$AV$30)+IF(Other_Concessions!$C$13=0,Other_Concessions!$C$41*(1+Other_Concessions!$C$16+D$58)/(Other_Concessions!$C$12+$B61-Other_Concessions!$C$16-D$58)/(1+Other_Concessions!$C$12+$B61)^Other_Concessions!$C$42,0))+(SUMPRODUCT(Energy_Construction!$D$29:$AV$29/(1+Energy_Construction!$C$12+$B61)^Energy_Construction!$D$30:$AV$30)+IF(Energy_Construction!$C$13=0,Energy_Construction!$C$41*(1+Energy_Construction!$C$16+D$58)/(Energy_Construction!$C$12+$B61-Energy_Construction!$C$16-D$58)/(1+Energy_Construction!$C$12+$B61)^Energy_Construction!$C$42,0))+(SUMPRODUCT(Energy_Construction!$D$71:$AV$71/(1+Energy_Construction!$C$54+$B61)^Energy_Construction!$D$72:$AV$72)+IF(Energy_Construction!$C$55=0,Energy_Construction!$C$83*(1+Energy_Construction!$C$58+D$58)/(Energy_Construction!$C$54+$B61-Energy_Construction!$C$58-D$58)/(1+Energy_Construction!$C$54+$B61)^Energy_Construction!$C$84,0))+(SUMPRODUCT(Energy_Construction!$D$113:$AV$113/(1+Energy_Construction!$C$96+$B61)^Energy_Construction!$D$114:$AV$114)+IF(Energy_Construction!$C$97=0,Energy_Construction!$C$125*(1+Energy_Construction!$C$100+D$58)/(Energy_Construction!$C$96+$B61-Energy_Construction!$C$100-D$58)/(1+Energy_Construction!$C$96+$B61)^Energy_Construction!$C$126,0))+(F17+F20+F21+F22+F25)-Inputs!$C$25*MAX(0,(SUMPRODUCT(Airports!$D$29:$AV$29/(1+Airports!$C$12+$B61)^Airports!$D$30:$AV$30)+IF(Airports!$C$13=0,Airports!$C$41*(1+Airports!$C$16+D$58)/(Airports!$C$12+$B61-Airports!$C$16-D$58)/(1+Airports!$C$12+$B61)^Airports!$C$42,0))-Inputs!$C$23)-Inputs!$C$26*MAX(0,(SUMPRODUCT(Airports!$D$71:$AV$71/(1+Airports!$C$54+$B61)^Airports!$D$72:$AV$72)+IF(Airports!$C$55=0,Airports!$C$83*(1+Airports!$C$58+D$58)/(Airports!$C$54+$B61-Airports!$C$58-D$58)/(1+Airports!$C$54+$B61)^Airports!$C$84,0))-Inputs!$C$24))/$F$27 -> 127.23712 | E61: =((SUMPRODUCT(Autoroutes!$D$29:$AV$29/(1+Autoroutes!$C$12+$B61)^Autoroutes!$D$30:$AV$30)+IF(Autoroutes!$C$13=0,Autoroutes!$C$41*(1+Autoroutes!$C$16+E$58)/(Autoroutes!$C$12+$B61-Autoroutes!$C$16-E$58)/(1+Autoroutes!$C$12+$B61)^Autoroutes!$C$42,0))+(SUMPRODUCT(Autoroutes!$D$71:$AV$71/(1+Autoroutes!$C$54+$B61)^Autoroutes!$D$72:$AV$72)+IF(Autoroutes!$C$55=0,Autoroutes!$C$83*(1+Autoroutes!$C$58+E$58)/(Autoroutes!$C$54+$B61-Autoroutes!$C$58-E$58)/(1+Autoroutes!$C$54+$B61)^Autoroutes!$C$84,0))+(SUMPRODUCT(Autoroutes!$D$113:$AV$113/(1+Autoroutes!$C$96+$B61)^Autoroutes!$D$114:$AV$114)+IF(Autoroutes!$C$97=0,Autoroutes!$C$125*(1+Autoroutes!$C$100+E$58)/(Autoroutes!$C$96+$B61-Autoroutes!$C$100-E$58)/(1+Autoroutes!$C$96+$B61)^Autoroutes!$C$126,0))+(SUMPRODUCT(Autoroutes!$D$155:$AV$155/(1+Autoroutes!$C$138+$B61)^Autoroutes!$D$156:$AV$156)+IF(Autoroutes!$C$139=0,Autoroutes!$C$167*(1+Autoroutes!$C$142+E$58)/(Autoroutes!$C$138+$B61-Autoroutes!$C$142-E$58)/(1+Autoroutes!$C$138+$B61)^Autoroutes!$C$168,0))+(SUMPRODUCT(Airports!$D$29:$AV$29/(1+Airports!$C$12+$B61)^Airports!$D$30:$AV$30)+IF(Airports!$C$13=0,Airports!$C$41*(1+Airports!$C$16+E$58)/(Airports!$C$12+$B61-Airports!$C$16-E$58)/(1+Airports!$C$12+$B61)^Airports!$C$42,0))+(SUMPRODUCT(Airports!$D$71:$AV$71/(1+Airports!$C$54+$B61)^Airports!$D$72:$AV$72)+IF(Airports!$C$55=0,Airports!$C$83*(1+Airports!$C$58+E$58)/(Airports!$C$54+$B61-Airports!$C$58-E$58)/(1+Airports!$C$54+$B61)^Airports!$C$84,0))+(SUMPRODUCT(Airports!$D$113:$AV$113/(1+Airports!$C$96+$B61)^Airports!$D$114:$AV$114)+IF(Airports!$C$97=0,Airports!$C$125*(1+Airports!$C$100+E$58)/(Airports!$C$96+$B61-Airports!$C$100-E$58)/(1+Airports!$C$96+$B61)^Airports!$C$126,0))+(SUMPRODUCT(Other_Concessions!$D$29:$AV$29/(1+Other_Concessions!$C$12+$B61)^Other_Concessions!$D$30:$AV$30)+IF(Other_Concessions!$C$13=0,Other_Concessions!$C$41*(1+Other_Concessions!$C$16+E$58)/(Other_Concessions!$C$12+$B61-Other_Concessions!$C$16-E$58)/(1+Other_Concessions!$C$12+$B61)^Other_Concessions!$C$42,0))+(SUMPRODUCT(Energy_Construction!$D$29:$AV$29/(1+Energy_Construction!$C$12+$B61)^Energy_Construction!$D$30:$AV$30)+IF(Energy_Construction!$C$13=0,Energy_Construction!$C$41*(1+Energy_Construction!$C$16+E$58)/(Energy_Construction!$C$12+$B61-Energy_Construction!$C$16-E$58)/(1+Energy_Construction!$C$12+$B61)^Energy_Construction!$C$42,0))+(SUMPRODUCT(Energy_Construction!$D$71:$AV$71/(1+Energy_Construction!$C$54+$B61)^Energy_Construction!$D$72:$AV$72)+IF(Energy_Construction!$C$55=0,Energy_Construction!$C$83*(1+Energy_Construction!$C$58+E$58)/(Energy_Construction!$C$54+$B61-Energy_Construction!$C$58-E$58)/(1+Energy_Construction!$C$54+$B61)^Energy_Construction!$C$84,0))+(SUMPRODUCT(Energy_Construction!$D$113:$AV$113/(1+Energy_Construction!$C$96+$B61)^Energy_Construction!$D$114:$AV$114)+IF(Energy_Construction!$C$97=0,Energy_Construction!$C$125*(1+Energy_Construction!$C$100+E$58)/(Energy_Construction!$C$96+$B61-Energy_Construction!$C$100-E$58)/(1+Energy_Construction!$C$96+$B61)^Energy_Construction!$C$126,0))+(F17+F20+F21+F22+F25)-Inputs!$C$25*MAX(0,(SUMPRODUCT(Airports!$D$29:$AV$29/(1+Airports!$C$12+$B61)^Airports!$D$30:$AV$30)+IF(Airports!$C$13=0,Airports!$C$41*(1+Airports!$C$16+E$58)/(Airports!$C$12+$B61-Airports!$C$16-E$58)/(1+Airports!$C$12+$B61)^Airports!$C$42,0))-Inputs!$C$23)-Inputs!$C$26*MAX(0,(SUMPRODUCT(Airports!$D$71:$AV$71/(1+Airports!$C$54+$B61)^Airports!$D$72:$AV$72)+IF(Airports!$C$55=0,Airports!$C$83*(1+Airports!$C$58+E$58)/(Airports!$C$54+$B61-Airports!$C$58-E$58)/(1+Airports!$C$54+$B61)^Airports!$C$84,0))-Inputs!$C$24))/$F$27 -> 132.81179 | F61: =IF(ABS(D61-F28)<0.01,"OK","REVISAR") -> OK
B62: 0.005 | C62: =((SUMPRODUCT(Autoroutes!$D$29:$AV$29/(1+Autoroutes!$C$12+$B62)^Autoroutes!$D$30:$AV$30)+IF(Autoroutes!$C$13=0,Autoroutes!$C$41*(1+Autoroutes!$C$16+C$58)/(Autoroutes!$C$12+$B62-Autoroutes!$C$16-C$58)/(1+Autoroutes!$C$12+$B62)^Autoroutes!$C$42,0))+(SUMPRODUCT(Autoroutes!$D$71:$AV$71/(1+Autoroutes!$C$54+$B62)^Autoroutes!$D$72:$AV$72)+IF(Autoroutes!$C$55=0,Autoroutes!$C$83*(1+Autoroutes!$C$58+C$58)/(Autoroutes!$C$54+$B62-Autoroutes!$C$58-C$58)/(1+Autoroutes!$C$54+$B62)^Autoroutes!$C$84,0))+(SUMPRODUCT(Autoroutes!$D$113:$AV$113/(1+Autoroutes!$C$96+$B62)^Autoroutes!$D$114:$AV$114)+IF(Autoroutes!$C$97=0,Autoroutes!$C$125*(1+Autoroutes!$C$100+C$58)/(Autoroutes!$C$96+$B62-Autoroutes!$C$100-C$58)/(1+Autoroutes!$C$96+$B62)^Autoroutes!$C$126,0))+(SUMPRODUCT(Autoroutes!$D$155:$AV$155/(1+Autoroutes!$C$138+$B62)^Autoroutes!$D$156:$AV$156)+IF(Autoroutes!$C$139=0,Autoroutes!$C$167*(1+Autoroutes!$C$142+C$58)/(Autoroutes!$C$138+$B62-Autoroutes!$C$142-C$58)/(1+Autoroutes!$C$138+$B62)^Autoroutes!$C$168,0))+(SUMPRODUCT(Airports!$D$29:$AV$29/(1+Airports!$C$12+$B62)^Airports!$D$30:$AV$30)+IF(Airports!$C$13=0,Airports!$C$41*(1+Airports!$C$16+C$58)/(Airports!$C$12+$B62-Airports!$C$16-C$58)/(1+Airports!$C$12+$B62)^Airports!$C$42,0))+(SUMPRODUCT(Airports!$D$71:$AV$71/(1+Airports!$C$54+$B62)^Airports!$D$72:$AV$72)+IF(Airports!$C$55=0,Airports!$C$83*(1+Airports!$C$58+C$58)/(Airports!$C$54+$B62-Airports!$C$58-C$58)/(1+Airports!$C$54+$B62)^Airports!$C$84,0))+(SUMPRODUCT(Airports!$D$113:$AV$113/(1+Airports!$C$96+$B62)^Airports!$D$114:$AV$114)+IF(Airports!$C$97=0,Airports!$C$125*(1+Airports!$C$100+C$58)/(Airports!$C$96+$B62-Airports!$C$100-C$58)/(1+Airports!$C$96+$B62)^Airports!$C$126,0))+(SUMPRODUCT(Other_Concessions!$D$29:$AV$29/(1+Other_Concessions!$C$12+$B62)^Other_Concessions!$D$30:$AV$30)+IF(Other_Concessions!$C$13=0,Other_Concessions!$C$41*(1+Other_Concessions!$C$16+C$58)/(Other_Concessions!$C$12+$B62-Other_Concessions!$C$16-C$58)/(1+Other_Concessions!$C$12+$B62)^Other_Concessions!$C$42,0))+(SUMPRODUCT(Energy_Construction!$D$29:$AV$29/(1+Energy_Construction!$C$12+$B62)^Energy_Construction!$D$30:$AV$30)+IF(Energy_Construction!$C$13=0,Energy_Construction!$C$41*(1+Energy_Construction!$C$16+C$58)/(Energy_Construction!$C$12+$B62-Energy_Construction!$C$16-C$58)/(1+Energy_Construction!$C$12+$B62)^Energy_Construction!$C$42,0))+(SUMPRODUCT(Energy_Construction!$D$71:$AV$71/(1+Energy_Construction!$C$54+$B62)^Energy_Construction!$D$72:$AV$72)+IF(Energy_Construction!$C$55=0,Energy_Construction!$C$83*(1+Energy_Construction!$C$58+C$58)/(Energy_Construction!$C$54+$B62-Energy_Construction!$C$58-C$58)/(1+Energy_Construction!$C$54+$B62)^Energy_Construction!$C$84,0))+(SUMPRODUCT(Energy_Construction!$D$113:$AV$113/(1+Energy_Construction!$C$96+$B62)^Energy_Construction!$D$114:$AV$114)+IF(Energy_Construction!$C$97=0,Energy_Construction!$C$125*(1+Energy_Construction!$C$100+C$58)/(Energy_Construction!$C$96+$B62-Energy_Construction!$C$100-C$58)/(1+Energy_Construction!$C$96+$B62)^Energy_Construction!$C$126,0))+(F17+F20+F21+F22+F25)-Inputs!$C$25*MAX(0,(SUMPRODUCT(Airports!$D$29:$AV$29/(1+Airports!$C$12+$B62)^Airports!$D$30:$AV$30)+IF(Airports!$C$13=0,Airports!$C$41*(1+Airports!$C$16+C$58)/(Airports!$C$12+$B62-Airports!$C$16-C$58)/(1+Airports!$C$12+$B62)^Airports!$C$42,0))-Inputs!$C$23)-Inputs!$C$26*MAX(0,(SUMPRODUCT(Airports!$D$71:$AV$71/(1+Airports!$C$54+$B62)^Airports!$D$72:$AV$72)+IF(Airports!$C$55=0,Airports!$C$83*(1+Airports!$C$58+C$58)/(Airports!$C$54+$B62-Airports!$C$58-C$58)/(1+Airports!$C$54+$B62)^Airports!$C$84,0))-Inputs!$C$24))/$F$27 -> 114.56171 | D62: =((SUMPRODUCT(Autoroutes!$D$29:$AV$29/(1+Autoroutes!$C$12+$B62)^Autoroutes!$D$30:$AV$30)+IF(Autoroutes!$C$13=0,Autoroutes!$C$41*(1+Autoroutes!$C$16+D$58)/(Autoroutes!$C$12+$B62-Autoroutes!$C$16-D$58)/(1+Autoroutes!$C$12+$B62)^Autoroutes!$C$42,0))+(SUMPRODUCT(Autoroutes!$D$71:$AV$71/(1+Autoroutes!$C$54+$B62)^Autoroutes!$D$72:$AV$72)+IF(Autoroutes!$C$55=0,Autoroutes!$C$83*(1+Autoroutes!$C$58+D$58)/(Autoroutes!$C$54+$B62-Autoroutes!$C$58-D$58)/(1+Autoroutes!$C$54+$B62)^Autoroutes!$C$84,0))+(SUMPRODUCT(Autoroutes!$D$113:$AV$113/(1+Autoroutes!$C$96+$B62)^Autoroutes!$D$114:$AV$114)+IF(Autoroutes!$C$97=0,Autoroutes!$C$125*(1+Autoroutes!$C$100+D$58)/(Autoroutes!$C$96+$B62-Autoroutes!$C$100-D$58)/(1+Autoroutes!$C$96+$B62)^Autoroutes!$C$126,0))+(SUMPRODUCT(Autoroutes!$D$155:$AV$155/(1+Autoroutes!$C$138+$B62)^Autoroutes!$D$156:$AV$156)+IF(Autoroutes!$C$139=0,Autoroutes!$C$167*(1+Autoroutes!$C$142+D$58)/(Autoroutes!$C$138+$B62-Autoroutes!$C$142-D$58)/(1+Autoroutes!$C$138+$B62)^Autoroutes!$C$168,0))+(SUMPRODUCT(Airports!$D$29:$AV$29/(1+Airports!$C$12+$B62)^Airports!$D$30:$AV$30)+IF(Airports!$C$13=0,Airports!$C$41*(1+Airports!$C$16+D$58)/(Airports!$C$12+$B62-Airports!$C$16-D$58)/(1+Airports!$C$12+$B62)^Airports!$C$42,0))+(SUMPRODUCT(Airports!$D$71:$AV$71/(1+Airports!$C$54+$B62)^Airports!$D$72:$AV$72)+IF(Airports!$C$55=0,Airports!$C$83*(1+Airports!$C$58+D$58)/(Airports!$C$54+$B62-Airports!$C$58-D$58)/(1+Airports!$C$54+$B62)^Airports!$C$84,0))+(SUMPRODUCT(Airports!$D$113:$AV$113/(1+Airports!$C$96+$B62)^Airports!$D$114:$AV$114)+IF(Airports!$C$97=0,Airports!$C$125*(1+Airports!$C$100+D$58)/(Airports!$C$96+$B62-Airports!$C$100-D$58)/(1+Airports!$C$96+$B62)^Airports!$C$126,0))+(SUMPRODUCT(Other_Concessions!$D$29:$AV$29/(1+Other_Concessions!$C$12+$B62)^Other_Concessions!$D$30:$AV$30)+IF(Other_Concessions!$C$13=0,Other_Concessions!$C$41*(1+Other_Concessions!$C$16+D$58)/(Other_Concessions!$C$12+$B62-Other_Concessions!$C$16-D$58)/(1+Other_Concessions!$C$12+$B62)^Other_Concessions!$C$42,0))+(SUMPRODUCT(Energy_Construction!$D$29:$AV$29/(1+Energy_Construction!$C$12+$B62)^Energy_Construction!$D$30:$AV$30)+IF(Energy_Construction!$C$13=0,Energy_Construction!$C$41*(1+Energy_Construction!$C$16+D$58)/(Energy_Construction!$C$12+$B62-Energy_Construction!$C$16-D$58)/(1+Energy_Construction!$C$12+$B62)^Energy_Construction!$C$42,0))+(SUMPRODUCT(Energy_Construction!$D$71:$AV$71/(1+Energy_Construction!$C$54+$B62)^Energy_Construction!$D$72:$AV$72)+IF(Energy_Construction!$C$55=0,Energy_Construction!$C$83*(1+Energy_Construction!$C$58+D$58)/(Energy_Construction!$C$54+$B62-Energy_Construction!$C$58-D$58)/(1+Energy_Construction!$C$54+$B62)^Energy_Construction!$C$84,0))+(SUMPRODUCT(Energy_Construction!$D$113:$AV$113/(1+Energy_Construction!$C$96+$B62)^Energy_Construction!$D$114:$AV$114)+IF(Energy_Construction!$C$97=0,Energy_Construction!$C$125*(1+Energy_Construction!$C$100+D$58)/(Energy_Construction!$C$96+$B62-Energy_Construction!$C$100-D$58)/(1+Energy_Construction!$C$96+$B62)^Energy_Construction!$C$126,0))+(F17+F20+F21+F22+F25)-Inputs!$C$25*MAX(0,(SUMPRODUCT(Airports!$D$29:$AV$29/(1+Airports!$C$12+$B62)^Airports!$D$30:$AV$30)+IF(Airports!$C$13=0,Airports!$C$41*(1+Airports!$C$16+D$58)/(Airports!$C$12+$B62-Airports!$C$16-D$58)/(1+Airports!$C$12+$B62)^Airports!$C$42,0))-Inputs!$C$23)-Inputs!$C$26*MAX(0,(SUMPRODUCT(Airports!$D$71:$AV$71/(1+Airports!$C$54+$B62)^Airports!$D$72:$AV$72)+IF(Airports!$C$55=0,Airports!$C$83*(1+Airports!$C$58+D$58)/(Airports!$C$54+$B62-Airports!$C$58-D$58)/(1+Airports!$C$54+$B62)^Airports!$C$84,0))-Inputs!$C$24))/$F$27 -> 118.50464 | E62: =((SUMPRODUCT(Autoroutes!$D$29:$AV$29/(1+Autoroutes!$C$12+$B62)^Autoroutes!$D$30:$AV$30)+IF(Autoroutes!$C$13=0,Autoroutes!$C$41*(1+Autoroutes!$C$16+E$58)/(Autoroutes!$C$12+$B62-Autoroutes!$C$16-E$58)/(1+Autoroutes!$C$12+$B62)^Autoroutes!$C$42,0))+(SUMPRODUCT(Autoroutes!$D$71:$AV$71/(1+Autoroutes!$C$54+$B62)^Autoroutes!$D$72:$AV$72)+IF(Autoroutes!$C$55=0,Autoroutes!$C$83*(1+Autoroutes!$C$58+E$58)/(Autoroutes!$C$54+$B62-Autoroutes!$C$58-E$58)/(1+Autoroutes!$C$54+$B62)^Autoroutes!$C$84,0))+(SUMPRODUCT(Autoroutes!$D$113:$AV$113/(1+Autoroutes!$C$96+$B62)^Autoroutes!$D$114:$AV$114)+IF(Autoroutes!$C$97=0,Autoroutes!$C$125*(1+Autoroutes!$C$100+E$58)/(Autoroutes!$C$96+$B62-Autoroutes!$C$100-E$58)/(1+Autoroutes!$C$96+$B62)^Autoroutes!$C$126,0))+(SUMPRODUCT(Autoroutes!$D$155:$AV$155/(1+Autoroutes!$C$138+$B62)^Autoroutes!$D$156:$AV$156)+IF(Autoroutes!$C$139=0,Autoroutes!$C$167*(1+Autoroutes!$C$142+E$58)/(Autoroutes!$C$138+$B62-Autoroutes!$C$142-E$58)/(1+Autoroutes!$C$138+$B62)^Autoroutes!$C$168,0))+(SUMPRODUCT(Airports!$D$29:$AV$29/(1+Airports!$C$12+$B62)^Airports!$D$30:$AV$30)+IF(Airports!$C$13=0,Airports!$C$41*(1+Airports!$C$16+E$58)/(Airports!$C$12+$B62-Airports!$C$16-E$58)/(1+Airports!$C$12+$B62)^Airports!$C$42,0))+(SUMPRODUCT(Airports!$D$71:$AV$71/(1+Airports!$C$54+$B62)^Airports!$D$72:$AV$72)+IF(Airports!$C$55=0,Airports!$C$83*(1+Airports!$C$58+E$58)/(Airports!$C$54+$B62-Airports!$C$58-E$58)/(1+Airports!$C$54+$B62)^Airports!$C$84,0))+(SUMPRODUCT(Airports!$D$113:$AV$113/(1+Airports!$C$96+$B62)^Airports!$D$114:$AV$114)+IF(Airports!$C$97=0,Airports!$C$125*(1+Airports!$C$100+E$58)/(Airports!$C$96+$B62-Airports!$C$100-E$58)/(1+Airports!$C$96+$B62)^Airports!$C$126,0))+(SUMPRODUCT(Other_Concessions!$D$29:$AV$29/(1+Other_Concessions!$C$12+$B62)^Other_Concessions!$D$30:$AV$30)+IF(Other_Concessions!$C$13=0,Other_Concessions!$C$41*(1+Other_Concessions!$C$16+E$58)/(Other_Concessions!$C$12+$B62-Other_Concessions!$C$16-E$58)/(1+Other_Concessions!$C$12+$B62)^Other_Concessions!$C$42,0))+(SUMPRODUCT(Energy_Construction!$D$29:$AV$29/(1+Energy_Construction!$C$12+$B62)^Energy_Construction!$D$30:$AV$30)+IF(Energy_Construction!$C$13=0,Energy_Construction!$C$41*(1+Energy_Construction!$C$16+E$58)/(Energy_Construction!$C$12+$B62-Energy_Construction!$C$16-E$58)/(1+Energy_Construction!$C$12+$B62)^Energy_Construction!$C$42,0))+(SUMPRODUCT(Energy_Construction!$D$71:$AV$71/(1+Energy_Construction!$C$54+$B62)^Energy_Construction!$D$72:$AV$72)+IF(Energy_Construction!$C$55=0,Energy_Construction!$C$83*(1+Energy_Construction!$C$58+E$58)/(Energy_Construction!$C$54+$B62-Energy_Construction!$C$58-E$58)/(1+Energy_Construction!$C$54+$B62)^Energy_Construction!$C$84,0))+(SUMPRODUCT(Energy_Construction!$D$113:$AV$113/(1+Energy_Construction!$C$96+$B62)^Energy_Construction!$D$114:$AV$114)+IF(Energy_Construction!$C$97=0,Energy_Construction!$C$125*(1+Energy_Construction!$C$100+E$58)/(Energy_Construction!$C$96+$B62-Energy_Construction!$C$100-E$58)/(1+Energy_Construction!$C$96+$B62)^Energy_Construction!$C$126,0))+(F17+F20+F21+F22+F25)-Inputs!$C$25*MAX(0,(SUMPRODUCT(Airports!$D$29:$AV$29/(1+Airports!$C$12+$B62)^Airports!$D$30:$AV$30)+IF(Airports!$C$13=0,Airports!$C$41*(1+Airports!$C$16+E$58)/(Airports!$C$12+$B62-Airports!$C$16-E$58)/(1+Airports!$C$12+$B62)^Airports!$C$42,0))-Inputs!$C$23)-Inputs!$C$26*MAX(0,(SUMPRODUCT(Airports!$D$71:$AV$71/(1+Airports!$C$54+$B62)^Airports!$D$72:$AV$72)+IF(Airports!$C$55=0,Airports!$C$83*(1+Airports!$C$58+E$58)/(Airports!$C$54+$B62-Airports!$C$58-E$58)/(1+Airports!$C$54+$B62)^Airports!$C$84,0))-Inputs!$C$24))/$F$27 -> 123.11958
B63: 0.01 | C63: =((SUMPRODUCT(Autoroutes!$D$29:$AV$29/(1+Autoroutes!$C$12+$B63)^Autoroutes!$D$30:$AV$30)+IF(Autoroutes!$C$13=0,Autoroutes!$C$41*(1+Autoroutes!$C$16+C$58)/(Autoroutes!$C$12+$B63-Autoroutes!$C$16-C$58)/(1+Autoroutes!$C$12+$B63)^Autoroutes!$C$42,0))+(SUMPRODUCT(Autoroutes!$D$71:$AV$71/(1+Autoroutes!$C$54+$B63)^Autoroutes!$D$72:$AV$72)+IF(Autoroutes!$C$55=0,Autoroutes!$C$83*(1+Autoroutes!$C$58+C$58)/(Autoroutes!$C$54+$B63-Autoroutes!$C$58-C$58)/(1+Autoroutes!$C$54+$B63)^Autoroutes!$C$84,0))+(SUMPRODUCT(Autoroutes!$D$113:$AV$113/(1+Autoroutes!$C$96+$B63)^Autoroutes!$D$114:$AV$114)+IF(Autoroutes!$C$97=0,Autoroutes!$C$125*(1+Autoroutes!$C$100+C$58)/(Autoroutes!$C$96+$B63-Autoroutes!$C$100-C$58)/(1+Autoroutes!$C$96+$B63)^Autoroutes!$C$126,0))+(SUMPRODUCT(Autoroutes!$D$155:$AV$155/(1+Autoroutes!$C$138+$B63)^Autoroutes!$D$156:$AV$156)+IF(Autoroutes!$C$139=0,Autoroutes!$C$167*(1+Autoroutes!$C$142+C$58)/(Autoroutes!$C$138+$B63-Autoroutes!$C$142-C$58)/(1+Autoroutes!$C$138+$B63)^Autoroutes!$C$168,0))+(SUMPRODUCT(Airports!$D$29:$AV$29/(1+Airports!$C$12+$B63)^Airports!$D$30:$AV$30)+IF(Airports!$C$13=0,Airports!$C$41*(1+Airports!$C$16+C$58)/(Airports!$C$12+$B63-Airports!$C$16-C$58)/(1+Airports!$C$12+$B63)^Airports!$C$42,0))+(SUMPRODUCT(Airports!$D$71:$AV$71/(1+Airports!$C$54+$B63)^Airports!$D$72:$AV$72)+IF(Airports!$C$55=0,Airports!$C$83*(1+Airports!$C$58+C$58)/(Airports!$C$54+$B63-Airports!$C$58-C$58)/(1+Airports!$C$54+$B63)^Airports!$C$84,0))+(SUMPRODUCT(Airports!$D$113:$AV$113/(1+Airports!$C$96+$B63)^Airports!$D$114:$AV$114)+IF(Airports!$C$97=0,Airports!$C$125*(1+Airports!$C$100+C$58)/(Airports!$C$96+$B63-Airports!$C$100-C$58)/(1+Airports!$C$96+$B63)^Airports!$C$126,0))+(SUMPRODUCT(Other_Concessions!$D$29:$AV$29/(1+Other_Concessions!$C$12+$B63)^Other_Concessions!$D$30:$AV$30)+IF(Other_Concessions!$C$13=0,Other_Concessions!$C$41*(1+Other_Concessions!$C$16+C$58)/(Other_Concessions!$C$12+$B63-Other_Concessions!$C$16-C$58)/(1+Other_Concessions!$C$12+$B63)^Other_Concessions!$C$42,0))+(SUMPRODUCT(Energy_Construction!$D$29:$AV$29/(1+Energy_Construction!$C$12+$B63)^Energy_Construction!$D$30:$AV$30)+IF(Energy_Construction!$C$13=0,Energy_Construction!$C$41*(1+Energy_Construction!$C$16+C$58)/(Energy_Construction!$C$12+$B63-Energy_Construction!$C$16-C$58)/(1+Energy_Construction!$C$12+$B63)^Energy_Construction!$C$42,0))+(SUMPRODUCT(Energy_Construction!$D$71:$AV$71/(1+Energy_Construction!$C$54+$B63)^Energy_Construction!$D$72:$AV$72)+IF(Energy_Construction!$C$55=0,Energy_Construction!$C$83*(1+Energy_Construction!$C$58+C$58)/(Energy_Construction!$C$54+$B63-Energy_Construction!$C$58-C$58)/(1+Energy_Construction!$C$54+$B63)^Energy_Construction!$C$84,0))+(SUMPRODUCT(Energy_Construction!$D$113:$AV$113/(1+Energy_Construction!$C$96+$B63)^Energy_Construction!$D$114:$AV$114)+IF(Energy_Construction!$C$97=0,Energy_Construction!$C$125*(1+Energy_Construction!$C$100+C$58)/(Energy_Construction!$C$96+$B63-Energy_Construction!$C$100-C$58)/(1+Energy_Construction!$C$96+$B63)^Energy_Construction!$C$126,0))+(F17+F20+F21+F22+F25)-Inputs!$C$25*MAX(0,(SUMPRODUCT(Airports!$D$29:$AV$29/(1+Airports!$C$12+$B63)^Airports!$D$30:$AV$30)+IF(Airports!$C$13=0,Airports!$C$41*(1+Airports!$C$16+C$58)/(Airports!$C$12+$B63-Airports!$C$16-C$58)/(1+Airports!$C$12+$B63)^Airports!$C$42,0))-Inputs!$C$23)-Inputs!$C$26*MAX(0,(SUMPRODUCT(Airports!$D$71:$AV$71/(1+Airports!$C$54+$B63)^Airports!$D$72:$AV$72)+IF(Airports!$C$55=0,Airports!$C$83*(1+Airports!$C$58+C$58)/(Airports!$C$54+$B63-Airports!$C$58-C$58)/(1+Airports!$C$54+$B63)^Airports!$C$84,0))-Inputs!$C$24))/$F$27 -> 107.47541 | D63: =((SUMPRODUCT(Autoroutes!$D$29:$AV$29/(1+Autoroutes!$C$12+$B63)^Autoroutes!$D$30:$AV$30)+IF(Autoroutes!$C$13=0,Autoroutes!$C$41*(1+Autoroutes!$C$16+D$58)/(Autoroutes!$C$12+$B63-Autoroutes!$C$16-D$58)/(1+Autoroutes!$C$12+$B63)^Autoroutes!$C$42,0))+(SUMPRODUCT(Autoroutes!$D$71:$AV$71/(1+Autoroutes!$C$54+$B63)^Autoroutes!$D$72:$AV$72)+IF(Autoroutes!$C$55=0,Autoroutes!$C$83*(1+Autoroutes!$C$58+D$58)/(Autoroutes!$C$54+$B63-Autoroutes!$C$58-D$58)/(1+Autoroutes!$C$54+$B63)^Autoroutes!$C$84,0))+(SUMPRODUCT(Autoroutes!$D$113:$AV$113/(1+Autoroutes!$C$96+$B63)^Autoroutes!$D$114:$AV$114)+IF(Autoroutes!$C$97=0,Autoroutes!$C$125*(1+Autoroutes!$C$100+D$58)/(Autoroutes!$C$96+$B63-Autoroutes!$C$100-D$58)/(1+Autoroutes!$C$96+$B63)^Autoroutes!$C$126,0))+(SUMPRODUCT(Autoroutes!$D$155:$AV$155/(1+Autoroutes!$C$138+$B63)^Autoroutes!$D$156:$AV$156)+IF(Autoroutes!$C$139=0,Autoroutes!$C$167*(1+Autoroutes!$C$142+D$58)/(Autoroutes!$C$138+$B63-Autoroutes!$C$142-D$58)/(1+Autoroutes!$C$138+$B63)^Autoroutes!$C$168,0))+(SUMPRODUCT(Airports!$D$29:$AV$29/(1+Airports!$C$12+$B63)^Airports!$D$30:$AV$30)+IF(Airports!$C$13=0,Airports!$C$41*(1+Airports!$C$16+D$58)/(Airports!$C$12+$B63-Airports!$C$16-D$58)/(1+Airports!$C$12+$B63)^Airports!$C$42,0))+(SUMPRODUCT(Airports!$D$71:$AV$71/(1+Airports!$C$54+$B63)^Airports!$D$72:$AV$72)+IF(Airports!$C$55=0,Airports!$C$83*(1+Airports!$C$58+D$58)/(Airports!$C$54+$B63-Airports!$C$58-D$58)/(1+Airports!$C$54+$B63)^Airports!$C$84,0))+(SUMPRODUCT(Airports!$D$113:$AV$113/(1+Airports!$C$96+$B63)^Airports!$D$114:$AV$114)+IF(Airports!$C$97=0,Airports!$C$125*(1+Airports!$C$100+D$58)/(Airports!$C$96+$B63-Airports!$C$100-D$58)/(1+Airports!$C$96+$B63)^Airports!$C$126,0))+(SUMPRODUCT(Other_Concessions!$D$29:$AV$29/(1+Other_Concessions!$C$12+$B63)^Other_Concessions!$D$30:$AV$30)+IF(Other_Concessions!$C$13=0,Other_Concessions!$C$41*(1+Other_Concessions!$C$16+D$58)/(Other_Concessions!$C$12+$B63-Other_Concessions!$C$16-D$58)/(1+Other_Concessions!$C$12+$B63)^Other_Concessions!$C$42,0))+(SUMPRODUCT(Energy_Construction!$D$29:$AV$29/(1+Energy_Construction!$C$12+$B63)^Energy_Construction!$D$30:$AV$30)+IF(Energy_Construction!$C$13=0,Energy_Construction!$C$41*(1+Energy_Construction!$C$16+D$58)/(Energy_Construction!$C$12+$B63-Energy_Construction!$C$16-D$58)/(1+Energy_Construction!$C$12+$B63)^Energy_Construction!$C$42,0))+(SUMPRODUCT(Energy_Construction!$D$71:$AV$71/(1+Energy_Construction!$C$54+$B63)^Energy_Construction!$D$72:$AV$72)+IF(Energy_Construction!$C$55=0,Energy_Construction!$C$83*(1+Energy_Construction!$C$58+D$58)/(Energy_Construction!$C$54+$B63-Energy_Construction!$C$58-D$58)/(1+Energy_Construction!$C$54+$B63)^Energy_Construction!$C$84,0))+(SUMPRODUCT(Energy_Construction!$D$113:$AV$113/(1+Energy_Construction!$C$96+$B63)^Energy_Construction!$D$114:$AV$114)+IF(Energy_Construction!$C$97=0,Energy_Construction!$C$125*(1+Energy_Construction!$C$100+D$58)/(Energy_Construction!$C$96+$B63-Energy_Construction!$C$100-D$58)/(1+Energy_Construction!$C$96+$B63)^Energy_Construction!$C$126,0))+(F17+F20+F21+F22+F25)-Inputs!$C$25*MAX(0,(SUMPRODUCT(Airports!$D$29:$AV$29/(1+Airports!$C$12+$B63)^Airports!$D$30:$AV$30)+IF(Airports!$C$13=0,Airports!$C$41*(1+Airports!$C$16+D$58)/(Airports!$C$12+$B63-Airports!$C$16-D$58)/(1+Airports!$C$12+$B63)^Airports!$C$42,0))-Inputs!$C$23)-Inputs!$C$26*MAX(0,(SUMPRODUCT(Airports!$D$71:$AV$71/(1+Airports!$C$54+$B63)^Airports!$D$72:$AV$72)+IF(Airports!$C$55=0,Airports!$C$83*(1+Airports!$C$58+D$58)/(Airports!$C$54+$B63-Airports!$C$58-D$58)/(1+Airports!$C$54+$B63)^Airports!$C$84,0))-Inputs!$C$24))/$F$27 -> 110.82489 | E63: =((SUMPRODUCT(Autoroutes!$D$29:$AV$29/(1+Autoroutes!$C$12+$B63)^Autoroutes!$D$30:$AV$30)+IF(Autoroutes!$C$13=0,Autoroutes!$C$41*(1+Autoroutes!$C$16+E$58)/(Autoroutes!$C$12+$B63-Autoroutes!$C$16-E$58)/(1+Autoroutes!$C$12+$B63)^Autoroutes!$C$42,0))+(SUMPRODUCT(Autoroutes!$D$71:$AV$71/(1+Autoroutes!$C$54+$B63)^Autoroutes!$D$72:$AV$72)+IF(Autoroutes!$C$55=0,Autoroutes!$C$83*(1+Autoroutes!$C$58+E$58)/(Autoroutes!$C$54+$B63-Autoroutes!$C$58-E$58)/(1+Autoroutes!$C$54+$B63)^Autoroutes!$C$84,0))+(SUMPRODUCT(Autoroutes!$D$113:$AV$113/(1+Autoroutes!$C$96+$B63)^Autoroutes!$D$114:$AV$114)+IF(Autoroutes!$C$97=0,Autoroutes!$C$125*(1+Autoroutes!$C$100+E$58)/(Autoroutes!$C$96+$B63-Autoroutes!$C$100-E$58)/(1+Autoroutes!$C$96+$B63)^Autoroutes!$C$126,0))+(SUMPRODUCT(Autoroutes!$D$155:$AV$155/(1+Autoroutes!$C$138+$B63)^Autoroutes!$D$156:$AV$156)+IF(Autoroutes!$C$139=0,Autoroutes!$C$167*(1+Autoroutes!$C$142+E$58)/(Autoroutes!$C$138+$B63-Autoroutes!$C$142-E$58)/(1+Autoroutes!$C$138+$B63)^Autoroutes!$C$168,0))+(SUMPRODUCT(Airports!$D$29:$AV$29/(1+Airports!$C$12+$B63)^Airports!$D$30:$AV$30)+IF(Airports!$C$13=0,Airports!$C$41*(1+Airports!$C$16+E$58)/(Airports!$C$12+$B63-Airports!$C$16-E$58)/(1+Airports!$C$12+$B63)^Airports!$C$42,0))+(SUMPRODUCT(Airports!$D$71:$AV$71/(1+Airports!$C$54+$B63)^Airports!$D$72:$AV$72)+IF(Airports!$C$55=0,Airports!$C$83*(1+Airports!$C$58+E$58)/(Airports!$C$54+$B63-Airports!$C$58-E$58)/(1+Airports!$C$54+$B63)^Airports!$C$84,0))+(SUMPRODUCT(Airports!$D$113:$AV$113/(1+Airports!$C$96+$B63)^Airports!$D$114:$AV$114)+IF(Airports!$C$97=0,Airports!$C$125*(1+Airports!$C$100+E$58)/(Airports!$C$96+$B63-Airports!$C$100-E$58)/(1+Airports!$C$96+$B63)^Airports!$C$126,0))+(SUMPRODUCT(Other_Concessions!$D$29:$AV$29/(1+Other_Concessions!$C$12+$B63)^Other_Concessions!$D$30:$AV$30)+IF(Other_Concessions!$C$13=0,Other_Concessions!$C$41*(1+Other_Concessions!$C$16+E$58)/(Other_Concessions!$C$12+$B63-Other_Concessions!$C$16-E$58)/(1+Other_Concessions!$C$12+$B63)^Other_Concessions!$C$42,0))+(SUMPRODUCT(Energy_Construction!$D$29:$AV$29/(1+Energy_Construction!$C$12+$B63)^Energy_Construction!$D$30:$AV$30)+IF(Energy_Construction!$C$13=0,Energy_Construction!$C$41*(1+Energy_Construction!$C$16+E$58)/(Energy_Construction!$C$12+$B63-Energy_Construction!$C$16-E$58)/(1+Energy_Construction!$C$12+$B63)^Energy_Construction!$C$42,0))+(SUMPRODUCT(Energy_Construction!$D$71:$AV$71/(1+Energy_Construction!$C$54+$B63)^Energy_Construction!$D$72:$AV$72)+IF(Energy_Construction!$C$55=0,Energy_Construction!$C$83*(1+Energy_Construction!$C$58+E$58)/(Energy_Construction!$C$54+$B63-Energy_Construction!$C$58-E$58)/(1+Energy_Construction!$C$54+$B63)^Energy_Construction!$C$84,0))+(SUMPRODUCT(Energy_Construction!$D$113:$AV$113/(1+Energy_Construction!$C$96+$B63)^Energy_Construction!$D$114:$AV$114)+IF(Energy_Construction!$C$97=0,Energy_Construction!$C$125*(1+Energy_Construction!$C$100+E$58)/(Energy_Construction!$C$96+$B63-Energy_Construction!$C$100-E$58)/(1+Energy_Construction!$C$96+$B63)^Energy_Construction!$C$126,0))+(F17+F20+F21+F22+F25)-Inputs!$C$25*MAX(0,(SUMPRODUCT(Airports!$D$29:$AV$29/(1+Airports!$C$12+$B63)^Airports!$D$30:$AV$30)+IF(Airports!$C$13=0,Airports!$C$41*(1+Airports!$C$16+E$58)/(Airports!$C$12+$B63-Airports!$C$16-E$58)/(1+Airports!$C$12+$B63)^Airports!$C$42,0))-Inputs!$C$23)-Inputs!$C$26*MAX(0,(SUMPRODUCT(Airports!$D$71:$AV$71/(1+Airports!$C$54+$B63)^Airports!$D$72:$AV$72)+IF(Airports!$C$55=0,Airports!$C$83*(1+Airports!$C$58+E$58)/(Airports!$C$54+$B63-Airports!$C$58-E$58)/(1+Airports!$C$54+$B63)^Airports!$C$84,0))-Inputs!$C$24))/$F$27 -> 114.69943
B65: Centre cell (0%, 0%) must equal the implied value per share above.

Sheet Inputs
B2: Vinci SA — SOTP global inputs (EUR m unless stated)
B3: Blue = hardcoded input · Black = formula · Green = link to another sheet · Yellow = key judgement / update before use
B4: Input | C4: Value | D4: Source / comment
B5: Valuation date (= latest balance sheet, H1 2026) | C5: 46203 | D5: Vinci Half-year financial report 2026 — balance sheet at 30 Jun 2026
B6: Share price (EUR), close 16 Sep 2026 | C6: 112.3 | D6: Euronext Paris closing price, 16 Sep 2026 (provided by FCO). Update for later dates.
B7: Shares issued (m), 30 Jun 2026 | C7: 585.8917 | D7: H1 2026 report, sec. 5: 585,891,697 shares
B8: Treasury shares, % of capital, 30 Jun 2026 | C8: 0.054 | D8: H1 2026 report, sec. 5: 5.4% (4.4% at 31 Dec 2025)
B9: Unvested performance shares (m) | C9: 7.65954 | D9: FY2025 consolidated FS, share-based payments note: 7,659,540 (treated as fully dilutive)
B10: Tax rate FY2026 (incl. French exceptional CIT surtax) | C10: 0.348 | D10: FY2025 ETR 34.8%; 2026 Finance Bill (art. 12) extends the surtax one more year — H1 2026 report, Note on surtax
B11: Tax rate FY2027+ (French statutory, surtax expired) | C11: 0.258 | D11: Vinci tax note: theoretical CIT rate 25.83%
B12: Net financial debt, 30 Jun 2026 | C12: 22450 | D12: H1 2026 report: €(22,450)m. Includes €152m buy-back liability. Leases excluded (see note below).
B13: of which Concessions incl. holdings | C13: -28353 | D13: H1 2026 segment note C.1.1 (net surplus / (debt))
B14: of which Energy Solutions | C14: 981 | D14: idem
B15: of which Construction | C15: 1902 | D15: idem
B16: of which Holding companies | C16: 3019 | D16: idem
... B27: VINCI Immobilier — value at book capital employed (1.0x) | C27: 1108 | D27: FY2025 segment note C.1.2: capital employed 1,108. Property developer: EBITDA 61 < leases 62 and H1 2026 revenue −17% → a DCF gives a meaningless negative value; book used instead.
B29: Lease treatment: lease repayments are deducted inside each block's free cash flow (post-IFRS 16 "EBITDAaL" logic), so lease liabilities are NOT deducted again in the bridge.
B30: Check: segment net debt sums to group net debt (±2 rounding) | C30: =IF(ABS(Inputs!$C$13+Inputs!$C$14+Inputs!$C$15+Inputs!$C$16+Inputs!$C$12)<=2,"OK","REVISAR") -> OK

Sheet Autoroutes
B2: Autoroutes — French motorway concessions valued to contract expiry, TV = 0
B4: ASF
B5: Base revenue FY2025 (EUR m) | C5: 3929 | D5: ASF network 2,731 km, 100%. Base revenue = FY2025 VINCI Autoroutes revenue by network (URD 2025: ASF 3,929 / Cofiroute 1,684 / Escota 961 / others 159). ASSUMPTION: segment margin (EBITDA 4,784 / revenue 6,733), D&A (1,503), capex (23 operating + 565 growth = 8.7%) and leases (12) applied pro rata to revenue — no network-level accounts available. FY2026 growth −0.7% = H1 2026 revenue trend (traffic −2.9%). FY2027+ 2.1% = Vinci's own average revenue growth over ASF's residual life (impairment note). Capex held at 8.7% to the end as a proxy for hand-back (biens de retour) obligations. WACC 6.5%: low-risk tolled infrastructure (Rf ~3.0%, ERP ~5.0%, beta ~0.75) plus ~50bp for French fiscal/regulatory risk (TELD tax, surtax, tariff risk). End date = 31 Dec of the contract year (FS Note F.12 gives the year only). Contracts revert to the State at no cost → no terminal value.
B6: Revenue growth FY2026 | C6: -0.007
B7: Revenue growth FY2027+ | C7: 0.021
B8: EBITDA margin (CFO before tax & financing / revenue) | C8: 0.7105
B9: D&A % revenue | C9: 0.2232
B10: Capex % revenue (operating + growth investments) | C10: 0.0873
B11: Lease repayments % revenue | C11: 0.0018
B12: Discount rate (post-tax WACC) | C12: 0.065
B13: Type: 1 = finite concession (TV = 0) · 0 = going concern | C13: 1
B14: Concession end date (finite only) | C14: 50040
B15: Last explicit year (going concern only) | C15: 0
B16: Terminal growth g (going concern only) | C16: 0
B17: Terminal capex % revenue (going concern only) | C17: 0
B19: Fiscal year | D19: 2026 | E19: 2027 | F19: 2028 | G19: 2029 | H19: 2030 | I19: 2031 | J19: 2032 | K19: 2033 | L19: 2034 | M19: 2035 | N19: 2036 | O19: 2037 | P19: 2038 | Q19: 2039 | R19: 2040 | S19: 2041 | T19: 2042 | U19: 2043 | V19: 2044 | W19: 2045 | X19: 2046 | Y19: 2047 | Z19: 2048 | AA19: 2049 | AB19: 2050 | AC19: 2051 | AD19: 2052 | AE19: 2053 | AF19: 2054 | AG19: 2055 | AH19: 2056 | AI19: 2057 | AJ19: 2058 | AK19: 2059 | AL19: 2060 | AM19: 2061 | AN19: 2062 | AO19: 2063 | AP19: 2064 | AQ19: 2065 | AR19: 2066 | AS19: 2067 | AT19: 2068 | AU19: 2069 | AV19: 2070
B20: Fraction of year in valuation (after val. date / before concession end) | D20: =IF($C$13=1,MAX(0,MIN(DATE(D$19,12,31),$C$14)-MAX(Inputs!$C$5+1,DATE(D$19,1,1))+1)/365,IF(D$19<=$C$15,(DATE(D$19,12,31)-MAX(Inputs!$C$5+1,DATE(D$19,1,1))+1)/365,0)) -> 0.50410959 | E20: =IF($C$13=1,MAX(0,MIN(DATE(E$19,12,31),$C$14)-MAX(Inputs!$C$5+1,DATE(E$19,1,1))+1)/365,IF(E$19<=$C$15,(DATE(E$19,12,31)-MAX(Inputs!$C$5+1,DATE(E$19,1,1))+1)/365,0)) -> 1 | F20: =IF($C$13=1,MAX(0,MIN(DATE(F$19,12,31),$C$14)-MAX(Inputs!$C$5+1,DATE(F$19,1,1))+1)/365,IF(F$19<=$C$15,(DATE(F$19,12,31)-MAX(Inputs!$C$5+1,DATE(F$19,1,1))+1)/365,0)) -> 1.0027397 | G20: =IF($C$13=1,MAX(0,MIN(DATE(G$19,12,31),$C$14)-MAX(Inputs!$C$5+1,DATE(G$19,1,1))+1)/365,IF(G$19<=$C$15,(DATE(G$19,12,31)-MAX(Inputs!$C$5+1,DATE(G$19,1,1))+1)/365,0)) -> 1 | H20: =IF($C$13=1,MAX(0,MIN(DATE(H$19,12,31),$C$14)-MAX(Inputs!$C$5+1,DATE(H$19,1,1))+1)/365,IF(H$19<=$C$15,(DATE(H$19,12,31)-MAX(Inputs!$C$5+1,DATE(H$19,1,1))+1)/365,0)) -> 1 | I20: =IF($C$13=1,MAX(0,MIN(DATE(I$19,12,31),$C$14)-MAX(Inputs!$C$5+1,DATE(I$19,1,1))+1)/365,IF(I$19<=$C$15,(DATE(I$19,12,31)-MAX(Inputs!$C$5+1,DATE(I$19,1,1))+1)/365,0)) -> 1 | J20: =IF($C$13=1,MAX(0,MIN(DATE(J$19,12,31),$C$14)-MAX(Inputs!$C$5+1,DATE(J$19,1,1))+1)/365,IF(J$19<=$C$15,(DATE(J$19,12,31)-MAX(Inputs!$C$5+1,DATE(J$19,1,1))+1)/365,0)) -> 1.0027397 | K20: =IF($C$13=1,MAX(0,MIN(DATE(K$19,12,31),$C$14)-MAX(Inputs!$C$5+1,DATE(K$19,1,1))+1)/365,IF(K$19<=$C$15,(DATE(K$19,12,31)-MAX(Inputs!$C$5+1,DATE(K$19,1,1))+1)/365,0)) -> 1 | ... AV20: =IF($C$13=1,MAX(0,MIN(DATE(AV$19,12,31),$C$14)-MAX(Inputs!$C$5+1,DATE(AV$19,1,1))+1)/365,IF(AV$19<=$C$15,(DATE(AV$19,12,31)-MAX(Inputs!$C$5+1,DATE(AV$19,1,1))+1)/365,0)) -> 0
B21: Revenue (full-year run-rate) | D21: =$C$5*(1+$C$6) -> 3901.497 | E21: =D21*(1+$C$7) -> 3983.4284 | F21: =E21*(1+$C$7) -> 4067.0804 | G21: =F21*(1+$C$7) -> 4152.4891 | H21: =G21*(1+$C$7) -> 4239.6914 | I21: =H21*(1+$C$7) -> 4328.7249 | J21: =I21*(1+$C$7) -> 4419.6281 | K21: =J21*(1+$C$7) -> 4512.4403 | L21: =K21*(1+$C$7) -> 4607.2016 | ... AV21: =AU21*(1+$C$7) -> 9735.6271
B22: EBITDA | D22: =D21*$C$8 -> 2772.0136 | E22: =E21*$C$8 -> 2830.2259 | F22: =F21*$C$8 -> 2889.6606 | G22: =G21*$C$8 -> 2950.3435 | H22: =H21*$C$8 -> 3012.3007 | I22: =I21*$C$8 -> 3075.5591 | J22: =J21*$C$8 -> 3140.1458 | K22: =K21*$C$8 -> 3206.0889 | ... AV22: =AV21*$C$8 -> 6917.163
B23: D&A | D23: =-D21*$C$9 -> -870.81413 | E23: =-E21*$C$9 -> -889.10123 | F23: =-F21*$C$9 -> -907.77235 | G23: =-G21*$C$9 -> -926.83557 | H23: =-H21*$C$9 -> -946.29912 | I23: =-I21*$C$9 -> -966.1714 | J23: =-J21*$C$9 -> -986.461 | K23: =-K21*$C$9 -> -1007.1767 | ... AV23: =-AV21*$C$9 -> -2172.992
B24: EBIT | D24: =D22+D23 -> 1901.1995 | E24: =E22+E23 -> 1941.1247 | F24: =F22+F23 -> 1981.8883 | G24: =G22+G23 -> 2023.5079 | H24: =H22+H23 -> 2066.0016 | I24: =I22+I23 -> 2109.3877 | J24: =J22+J23 -> 2153.6848 | K24: =K22+K23 -> 2198.9122 | ... AV24: =AV22+AV23 -> 4744.1711
B25: Tax rate | D25: =IF(D$19=2026,Inputs!$C$10,Inputs!$C$11) -> 0.348 | E25: =IF(E$19=2026,Inputs!$C$10,Inputs!$C$11) -> 0.258 | F25: =IF(F$19=2026,Inputs!$C$10,Inputs!$C$11) -> 0.258 | G25: =IF(G$19=2026,Inputs!$C$10,Inputs!$C$11) -> 0.258 | H25: =IF(H$19=2026,Inputs!$C$10,Inputs!$C$11) -> 0.258 | I25: =IF(I$19=2026,Inputs!$C$10,Inputs!$C$11) -> 0.258 | J25: =IF(J$19=2026,Inputs!$C$10,Inputs!$C$11) -> 0.258 | K25: =IF(K$19=2026,Inputs!$C$10,Inputs!$C$11) -> 0.258 | ... AV25: =IF(AV$19=2026,Inputs!$C$10,Inputs!$C$11) -> 0.258
B26: Tax on EBIT | D26: =-MAX(0,D24)*D25 -> -661.61742 | E26: =-MAX(0,E24)*E25 -> -500.81017 | F26: =-MAX(0,F24)*F25 -> -511.32718 | G26: =-MAX(0,G24)*G25 -> -522.06505 | H26: =-MAX(0,H24)*H25 -> -533.02842 | I26: =-MAX(0,I24)*I25 -> -544.22201 | J26: =-MAX(0,J24)*J25 -> -555.65068 | K26: =-MAX(0,K24)*K25 -> -567.31934 | ... AV26: =-MAX(0,AV24)*AV25 -> -1223.9961
B27: Capex | D27: =-D21*$C$10 -> -340.60069 | E27: =-E21*$C$10 -> -347.7533 | F27: =-F21*$C$10 -> -355.05612 | G27: =-G21*$C$10 -> -362.5123 | H27: =-H21*$C$10 -> -370.12506 | I27: =-I21*$C$10 -> -377.89769 | J27: =-J21*$C$10 -> -385.83354 | K27: =-K21*$C$10 -> -393.93604 | ... AV27: =-AV21*$C$10 -> -849.92024
B28: Lease repayments | D28: =-D21*$C$11 -> -7.0226946 | E28: =-E21*$C$11 -> -7.1701712 | F28: =-F21*$C$11 -> -7.3207448 | G28: =-G21*$C$11 -> -7.4744804 | H28: =-H21*$C$11 -> -7.6314445 | I28: =-I21*$C$11 -> -7.7917048 | J28: =-J21*$C$11 -> -7.9553306 | K28: =-K21*$C$11 -> -8.1223926 | ... AV28: =-AV21*$C$11 -> -17.524129
B29: Unlevered FCF in valuation window | D29: =(D22+D26+D27+D28)*D20 -> 888.63068 | E29: =(E22+E26+E27+E28)*E20 -> 1974.4923 | F29: =(F22+F26+F27+F28)*F20 -> 2021.4798 | G29: =(G22+G26+G27+G28)*G20 -> 2058.2917 | H29: =(H22+H26+H27+H28)*H20 -> 2101.5158 | I29: =(I22+I26+I27+I28)*I20 -> 2145.6476 | J29: =(J22+J26+J27+J28)*J20 -> 2196.7082 | K29: =(K22+K26+K27+K28)*K20 -> 2236.7111 | ... AV29: =(AV22+AV26+AV27+AV28)*AV20 -> 0
B30: Discount period (mid-period, years) | D30: =((MAX(Inputs!$C$5+1,DATE(D$19,1,1))+DATE(D$19,12,31))/2-Inputs!$C$5)/365 -> 0.25342466 | E30: =((MAX(Inputs!$C$5+1,DATE(E$19,1,1))+DATE(E$19,12,31))/2-Inputs!$C$5)/365 -> 1.0054795 | F30: =((MAX(Inputs!$C$5+1,DATE(F$19,1,1))+DATE(F$19,12,31))/2-Inputs!$C$5)/365 -> 2.0068493 | G30: =((MAX(Inputs!$C$5+1,DATE(G$19,1,1))+DATE(G$19,12,31))/2-Inputs!$C$5)/365 -> 3.0082192 | H30: =((MAX(Inputs!$C$5+1,DATE(H$19,1,1))+DATE(H$19,12,31))/2-Inputs!$C$5)/365 -> 4.0082192 | I30: =((MAX(Inputs!$C$5+1,DATE(I$19,1,1))+DATE(I$19,12,31))/2-Inputs!$C$5)/365 -> 5.0082192 | J30: =((MAX(Inputs!$C$5+1,DATE(J$19,1,1))+DATE(J$19,12,31))/2-Inputs!$C$5)/365 -> 6.009589 | K30: =((MAX(Inputs!$C$5+1,DATE(K$19,1,1))+DATE(K$19,12,31))/2-Inputs!$C$5)/365 -> 7.0109589 | ... AV30: =((MAX(Inputs!$C$5+1,DATE(AV$19,1,1))+DATE(AV$19,12,31))/2-Inputs!$C$5)/365 -> 44.035616
B31: Discount factor | D31: =1/(1+$C$12)^D30 -> 0.98416731 | E31: =1/(1+$C$12)^E30 -> 0.93864319 | F31: =1/(1+$C$12)^F30 -> 0.88127907 | G31: =1/(1+$C$12)^G30 -> 0.82742071 | H31: =1/(1+$C$12)^H30 -> 0.77692085 | I31: =1/(1+$C$12)^I30 -> 0.72950315 | J31: =1/(1+$C$12)^J30 -> 0.68492039 | K31: =1/(1+$C$12)^K30 -> 0.64306226 | ... AV31: =1/(1+$C$12)^AV30 -> 0.062465923
B32: PV of UFCF | D32: =D29*D31 -> 874.56126 | E32: =E29*E31 -> 1853.3437 | F32: =F29*F31 -> 1781.4878 | G32: =G29*G31 -> 1703.0732 | H32: =H29*H31 -> 1632.7115 | I32: =I29*I31 -> 1565.2567 | J32: =J29*J31 -> 1504.5702 | K32: =K29*K31 -> 1438.3445 | ... AV32: =AV29*AV31 -> 0
B33: Terminal-year normalised FCF (before growth) | D33: =IF(AND($C$13=0,D$19=$C$15),D22-D21*($C$17+$C$11)-MAX(0,D22-D21*$C$17)*Inputs!$C$11,0) -> 0 | E33: =IF(AND($C$13=0,E$19=$C$15),E22-E21*($C$17+$C$11)-MAX(0,E22-E21*$C$17)*Inputs!$C$11,0) -> 0 | F33: =IF(AND($C$13=0,F$19=$C$15),F22-F21*($C$17+$C$11)-MAX(0,F22-F21*$C$17)*Inputs!$C$11,0) -> 0 | G33: =IF(AND($C$13=0,G$19=$C$15),G22-G21*($C$17+$C$11)-MAX(0,G22-G21*$C$17)*Inputs!$C$11,0) -> 0 | H33: =IF(AND($C$13=0,H$19=$C$15),H22-H21*($C$17+$C$11)-MAX(0,H22-H21*$C$17)*Inputs!$C$11,0) -> 0 | I33: =IF(AND($C$13=0,I$19=$C$15),I22-I21*($C$17+$C$11)-MAX(0,I22-I21*$C$17)*Inputs!$C$11,0) -> 0 | J33: =IF(AND($C$13=0,J$19=$C$15),J22-J21*($C$17+$C$11)-MAX(0,J22-J21*$C$17)*Inputs!$C$11,0) -> 0 | K33: =IF(AND($C$13=0,K$19=$C$15),K22-K21*($C$17+$C$11)-MAX(0,K22-K21*$C$17)*Inputs!$C$11,0) -> 0 | ... AV33: =IF(AND($C$13=0,AV$19=$C$15),AV22-AV21*($C$17+$C$11)-MAX(0,AV22-AV21*$C$17)*Inputs!$C$11,0) -> 0
B34: PV of terminal value | D34: =D33*(1+$C$16)/($C$12-$C$16)*D31 -> 0 | E34: =E33*(1+$C$16)/($C$12-$C$16)*E31 -> 0 | F34: =F33*(1+$C$16)/($C$12-$C$16)*F31 -> 0 | G34: =G33*(1+$C$16)/($C$12-$C$16)*G31 -> 0 | H34: =H33*(1+$C$16)/($C$12-$C$16)*H31 -> 0 | I34: =I33*(1+$C$16)/($C$12-$C$16)*I31 -> 0 | J34: =J33*(1+$C$16)/($C$12-$C$16)*J31 -> 0 | K34: =K33*(1+$C$16)/($C$12-$C$16)*K31 -> 0 | ... AV34: =AV33*(1+$C$16)/($C$12-$C$16)*AV31 -> 0
B36: PV of explicit / concession-life cash flows | C36: =SUM($D$32:$AV$32) -> 16324.916
B37: PV of terminal value | C37: =SUM($D$34:$AV$34) -> 0
B38: ENTERPRISE VALUE — ASF (100%) | C38: =C36+C37 -> 16324.916
B39: Terminal value as % of block EV | C39: =IF(C38=0,0,C37/C38) -> 0
B40: Implied EV / FY2026E EBITDA | C40: =IF(D22=0,0,C38/D22) -> 5.8891906
B41: Terminal FCF base (for sensitivity) | C41: =SUM($D$33:$AV$33) -> 0
B42: Terminal discount period (for sensitivity) | C42: =SUMPRODUCT(($D$19:$AV$19=$C$15)*$D$30:$AV$30) -> 0
B43: Check: WACC > g and no cash flow after concession end | C43: =IF(AND($C$12>$C$16,SUMPRODUCT(($D$19:$AV$19>YEAR($C$14))*($C$13=1)*ABS($D$29:$AV$29))=0),"OK","REVISAR") -> OK
B46: Escota
B47: Base revenue FY2025 (EUR m) | C47: 961 | D47: Escota 471 km, 99.5% owned (0.5% minority ignored — immaterial). Base revenue = FY2025 VINCI Autoroutes revenue by network (URD 2025: ASF 3,929 / Cofiroute 1,684 / Escota 961 / others 159). ASSUMPTION: segment margin (EBITDA 4,784 / revenue 6,733), D&A (1,503), capex (23 operating + 565 growth = 8.7%) and leases (12) applied pro rata to revenue — no network-level accounts available. FY2026 growth −0.7% = H1 2026 revenue trend (traffic −2.9%). FY2027+ 2.1% = Vinci's own average revenue growth over ASF's residual life (impairment note). Capex held at 8.7% to the end as a proxy for hand-back (biens de retour) obligations. WACC 6.5%: low-risk tolled infrastructure (Rf ~3.0%, ERP ~5.0%, beta ~0.75) plus ~50bp for French fiscal/regulatory risk (TELD tax, surtax, tariff risk). End date = 31 Dec of the contract year (FS Note F.12 gives the year only). Contracts revert to the State at no cost → no terminal value.
B48: Revenue growth FY2026 | C48: -0.007
B49: Revenue growth FY2027+ | C49: 0.021
B50: EBITDA margin (CFO before tax & financing / revenue) | C50: 0.7105
B51: D&A % revenue | C51: 0.2232
B52: Capex % revenue (operating + growth investments) | C52: 0.0873
B53: Lease repayments % revenue | C53: 0.0018
B54: Discount rate (post-tax WACC) | C54: 0.065
B55: Type: 1 = finite concession (TV = 0) · 0 = going concern | C55: 1
B56: Concession end date (finite only) | C56: 48579
B57: Last explicit year (going concern only) | C57: 0
B58: Terminal growth g (going concern only) | C58: 0
B59: Terminal capex % revenue (going concern only) | C59: 0
B61: Fiscal year | D61: 2026 | E61: 2027 | F61: 2028 | G61: 2029 | H61: 2030 | I61: 2031 | J61: 2032 | K61: 2033 | L61: 2034 | M61: 2035 | N61: 2036 | O61: 2037 | P61: 2038 | Q61: 2039 | R61: 2040 | S61: 2041 | T61: 2042 | U61: 2043 | V61: 2044 | W61: 2045 | X61: 2046 | Y61: 2047 | Z61: 2048 | AA61: 2049 | AB61: 2050 | AC61: 2051 | AD61: 2052 | AE61: 2053 | AF61: 2054 | AG61: 2055 | AH61: 2056 | AI61: 2057 | AJ61: 2058 | AK61: 2059 | AL61: 2060 | AM61: 2061 | AN61: 2062 | AO61: 2063 | AP61: 2064 | AQ61: 2065 | AR61: 2066 | AS61: 2067 | AT61: 2068 | AU61: 2069 | AV61: 2070
B62: Fraction of year in valuation (after val. date / before concession end) | D62: =IF($C$55=1,MAX(0,MIN(DATE(D$61,12,31),$C$56)-MAX(Inputs!$C$5+1,DATE(D$61,1,1))+1)/365,IF(D$61<=$C$57,(DATE(D$61,12,31)-MAX(Inputs!$C$5+1,DATE(D$61,1,1))+1)/365,0)) -> 0.50410959 | E62: =IF($C$55=1,MAX(0,MIN(DATE(E$61,12,31),$C$56)-MAX(Inputs!$C$5+1,DATE(E$61,1,1))+1)/365,IF(E$61<=$C$57,(DATE(E$61,12,31)-MAX(Inputs!$C$5+1,DATE(E$61,1,1))+1)/365,0)) -> 1 | F62: =IF($C$55=1,MAX(0,MIN(DATE(F$61,12,31),$C$56)-MAX(Inputs!$C$5+1,DATE(F$61,1,1))+1)/365,IF(F$61<=$C$57,(DATE(F$61,12,31)-MAX(Inputs!$C$5+1,DATE(F$61,1,1))+1)/365,0)) -> 1.0027397 | G62: =IF($C$55=1,MAX(0,MIN(DATE(G$61,12,31),$C$56)-MAX(Inputs!$C$5+1,DATE(G$61,1,1))+1)/365,IF(G$61<=$C$57,(DATE(G$61,12,31)-MAX(Inputs!$C$5+1,DATE(G$61,1,1))+1)/365,0)) -> 1 | H62: =IF($C$55=1,MAX(0,MIN(DATE(H$61,12,31),$C$56)-MAX(Inputs!$C$5+1,DATE(H$61,1,1))+1)/365,IF(H$61<=$C$57,(DATE(H$61,12,31)-MAX(Inputs!$C$5+1,DATE(H$61,1,1))+1)/365,0)) -> 1 | I62: =IF($C$55=1,MAX(0,MIN(DATE(I$61,12,31),$C$56)-MAX(Inputs!$C$5+1,DATE(I$61,1,1))+1)/365,IF(I$61<=$C$57,(DATE(I$61,12,31)-MAX(Inputs!$C$5+1,DATE(I$61,1,1))+1)/365,0)) -> 1 | J62: =IF($C$55=1,MAX(0,MIN(DATE(J$61,12,31),$C$56)-MAX(Inputs!$C$5+1,DATE(J$61,1,1))+1)/365,IF(J$61<=$C$57,(DATE(J$61,12,31)-MAX(Inputs!$C$5+1,DATE(J$61,1,1))+1)/365,0)) -> 1.0027397 | K62: =IF($C$55=1,MAX(0,MIN(DATE(K$61,12,31),$C$56)-MAX(Inputs!$C$5+1,DATE(K$61,1,1))+1)/365,IF(K$61<=$C$57,(DATE(K$61,12,31)-MAX(Inputs!$C$5+1,DATE(K$61,1,1))+1)/365,0)) -> 0 | ... AV62: =IF($C$55=1,MAX(0,MIN(DATE(AV$61,12,31),$C$56)-MAX(Inputs!$C$5+1,DATE(AV$61,1,1))+1)/365,IF(AV$61<=$C$57,(DATE(AV$61,12,31)-MAX(Inputs!$C$5+1,DATE(AV$61,1,1))+1)/365,0)) -> 0
B63: Revenue (full-year run-rate) | D63: =$C$47*(1+$C$48) -> 954.273 | E63: =D63*(1+$C$49) -> 974.31273 | F63: =E63*(1+$C$49) -> 994.7733 | G63: =F63*(1+$C$49) -> 1015.6635 | H63: =G63*(1+$C$49) -> 1036.9925 | I63: =H63*(1+$C$49) -> 1058.7693 | J63: =I63*(1+$C$49) -> 1081.0035 | K63: =J63*(1+$C$49) -> 1103.7045 | L63: =K63*(1+$C$49) -> 1126.8823 | ... AV63: =AU63*(1+$C$49) -> 2381.2516
B64: EBITDA | D64: =D63*$C$50 -> 678.01097 | E64: =E63*$C$50 -> 692.2492 | F64: =F63*$C$50 -> 706.78643 | G64: =G63*$C$50 -> 721.62894 | H64: =H63*$C$50 -> 736.78315 | I64: =I63*$C$50 -> 752.2556 | J64: =J63*$C$50 -> 768.05297 | K64: =K63*$C$50 -> 784.18208 | ... AV64: =AV63*$C$50 -> 1691.8793
B65: D&A | D65: =-D63*$C$51 -> -212.99373 | E65: =-E63*$C$51 -> -217.4666 | F65: =-F63*$C$51 -> -222.0334 | G65: =-G63*$C$51 -> -226.6961 | H65: =-H63*$C$51 -> -231.45672 | I65: =-I63*$C$51 -> -236.31731 | J65: =-J63*$C$51 -> -241.27997 | K65: =-K63*$C$51 -> -246.34685 | ... AV65: =-AV63*$C$51 -> -531.49536
B66: EBIT | D66: =D64+D65 -> 465.01723 | E66: =E64+E65 -> 474.78259 | F66: =F64+F65 -> 484.75303 | G66: =G64+G65 -> 494.93284 | H66: =H64+H65 -> 505.32643 | I66: =I64+I65 -> 515.93829 | J66: =J64+J65 -> 526.77299 | K66: =K64+K65 -> 537.83522 | ... AV66: =AV64+AV65 -> 1160.3839
B67: Tax rate | D67: =IF(D$61=2026,Inputs!$C$10,Inputs!$C$11) -> 0.348 | E67: =IF(E$61=2026,Inputs!$C$10,Inputs!$C$11) -> 0.258 | F67: =IF(F$61=2026,Inputs!$C$10,Inputs!$C$11) -> 0.258 | G67: =IF(G$61=2026,Inputs!$C$10,Inputs!$C$11) -> 0.258 | H67: =IF(H$61=2026,Inputs!$C$10,Inputs!$C$11) -> 0.258 | I67: =IF(I$61=2026,Inputs!$C$10,Inputs!$C$11) -> 0.258 | J67: =IF(J$61=2026,Inputs!$C$10,Inputs!$C$11) -> 0.258 | K67: =IF(K$61=2026,Inputs!$C$10,Inputs!$C$11) -> 0.258 | ... AV67: =IF(AV$61=2026,Inputs!$C$10,Inputs!$C$11) -> 0.258
B68: Tax on EBIT | D68: =-MAX(0,D66)*D67 -> -161.826 | E68: =-MAX(0,E66)*E67 -> -122.49391 | F68: =-MAX(0,F66)*F67 -> -125.06628 | G68: =-MAX(0,G66)*G67 -> -127.69267 | H68: =-MAX(0,H66)*H67 -> -130.37422 | I68: =-MAX(0,I66)*I67 -> -133.11208 | J68: =-MAX(0,J66)*J67 -> -135.90743 | K68: =-MAX(0,K66)*K67 -> -138.76149 | ... AV68: =-MAX(0,AV66)*AV67 -> -299.37905
B69: Capex | D69: =-D63*$C$52 -> -83.308033 | E69: =-E63*$C$52 -> -85.057502 | F69: =-F63*$C$52 -> -86.843709 | G69: =-G63*$C$52 -> -88.667427 | H69: =-H63*$C$52 -> -90.529443 | I69: =-I63*$C$52 -> -92.430561 | J69: =-J63*$C$52 -> -94.371603 | K69: =-K63*$C$52 -> -96.353407 | ... AV69: =-AV63*$C$52 -> -207.88327
B70: Lease repayments | D70: =-D63*$C$53 -> -1.7176914 | E70: =-E63*$C$53 -> -1.7537629 | F70: =-F63*$C$53 -> -1.7905919 | G70: =-G63*$C$53 -> -1.8281944 | H70: =-H63*$C$53 -> -1.8665865 | I70: =-I63*$C$53 -> -1.9057848 | J70: =-J63*$C$53 -> -1.9458062 | K70: =-K63*$C$53 -> -1.9866682 | ... AV70: =-AV63*$C$53 -> -4.2862529
B71: Unlevered FCF in valuation window | D71: =(D64+D68+D69+D70)*D62 -> 217.35151 | E71: =(E64+E68+E69+E70)*E62 -> 482.94402 | F71: =(F64+F68+F69+F70)*F62 -> 494.43677 | G71: =(G64+G68+G69+G70)*G62 -> 503.44065 | H71: =(H64+H68+H69+H70)*H62 -> 514.0129 | I71: =(I64+I68+I69+I70)*I62 -> 524.80717 | J71: =(J64+J68+J69+J70)*J62 -> 537.29615 | K71: =(K64+K68+K69+K70)*K62 -> 0 | ... AV71: =(AV64+AV68+AV69+AV70)*AV62 -> 0
B72: Discount period (mid-period, years) | D72: =((MAX(Inputs!$C$5+1,DATE(D$61,1,1))+DATE(D$61,12,31))/2-Inputs!$C$5)/365 -> 0.25342466 | E72: =((MAX(Inputs!$C$5+1,DATE(E$61,1,1))+DATE(E$61,12,31))/2-Inputs!$C$5)/365 -> 1.0054795 | F72: =((MAX(Inputs!$C$5+1,DATE(F$61,1,1))+DATE(F$61,12,31))/2-Inputs!$C$5)/365 -> 2.0068493 | G72: =((MAX(Inputs!$C$5+1,DATE(G$61,1,1))+DATE(G$61,12,31))/2-Inputs!$C$5)/365 -> 3.0082192 | H72: =((MAX(Inputs!$C$5+1,DATE(H$61,1,1))+DATE(H$61,12,31))/2-Inputs!$C$5)/365 -> 4.0082192 | I72: =((MAX(Inputs!$C$5+1,DATE(I$61,1,1))+DATE(I$61,12,31))/2-Inputs!$C$5)/365 -> 5.0082192 | J72: =((MAX(Inputs!$C$5+1,DATE(J$61,1,1))+DATE(J$61,12,31))/2-Inputs!$C$5)/365 -> 6.009589 | K72: =((MAX(Inputs!$C$5+1,DATE(K$61,1,1))+DATE(K$61,12,31))/2-Inputs!$C$5)/365 -> 7.0109589 | ... AV72: =((MAX(Inputs!$C$5+1,DATE(AV$61,1,1))+DATE(AV$61,12,31))/2-Inputs!$C$5)/365 -> 44.035616
B73: Discount factor | D73: =1/(1+$C$54)^D72 -> 0.98416731 | E73: =1/(1+$C$54)^E72 -> 0.93864319 | F73: =1/(1+$C$54)^F72 -> 0.88127907 | G73: =1/(1+$C$54)^G72 -> 0.82742071 | H73: =1/(1+$C$54)^H72 -> 0.77692085 | I73: =1/(1+$C$54)^I72 -> 0.72950315 | J73: =1/(1+$C$54)^J72 -> 0.68492039 | K73: =1/(1+$C$54)^K72 -> 0.64306226 | ... AV73: =1/(1+$C$54)^AV72 -> 0.062465923
B74: PV of UFCF | D74: =D71*D73 -> 213.91025 | E74: =E71*E73 -> 453.31212 | F74: =F71*F73 -> 435.73678 | G74: =G71*G73 -> 416.55722 | H74: =H71*H73 -> 399.34734 | I74: =I71*I73 -> 382.84849 | J74: =J71*J73 -> 368.00509 | K74: =K71*K73 -> 0 | ... AV74: =AV71*AV73 -> 0
B75: Terminal-year normalised FCF (before growth) | D75: =IF(AND($C$55=0,D$61=$C$57),D64-D63*($C$59+$C$53)-MAX(0,D64-D63*$C$59)*Inputs!$C$11,0) -> 0 | E75: =IF(AND($C$55=0,E$61=$C$57),E64-E63*($C$59+$C$53)-MAX(0,E64-E63*$C$59)*Inputs!$C$11,0) -> 0 | F75: =IF(AND($C$55=0,F$61=$C$57),F64-F63*($C$59+$C$53)-MAX(0,F64-F63*$C$59)*Inputs!$C$11,0) -> 0 | G75: =IF(AND($C$55=0,G$61=$C$57),G64-G63*($C$59+$C$53)-MAX(0,G64-G63*$C$59)*Inputs!$C$11,0) -> 0 | H75: =IF(AND($C$55=0,H$61=$C$57),H64-H63*($C$59+$C$53)-MAX(0,H64-H63*$C$59)*Inputs!$C$11,0) -> 0 | I75: =IF(AND($C$55=0,I$61=$C$57),I64-I63*($C$59+$C$53)-MAX(0,I64-I63*$C$59)*Inputs!$C$11,0) -> 0 | J75: =IF(AND($C$55=0,J$61=$C$57),J64-J63*($C$59+$C$53)-MAX(0,J64-J63*$C$59)*Inputs!$C$11,0) -> 0 | K75: =IF(AND($C$55=0,K$61=$C$57),K64-K63*($C$59+$C$53)-MAX(0,K64-K63*$C$59)*Inputs!$C$11,0) -> 0 | ... AV75: =IF(AND($C$55=0,AV$61=$C$57),AV64-AV63*($C$59+$C$53)-MAX(0,AV64-AV63*$C$59)*Inputs!$C$11,0) -> 0
B76: PV of terminal value | D76: =D75*(1+$C$58)/($C$54-$C$58)*D73 -> 0 | E76: =E75*(1+$C$58)/($C$54-$C$58)*E73 -> 0 | F76: =F75*(1+$C$58)/($C$54-$C$58)*F73 -> 0 | G76: =G75*(1+$C$58)/($C$54-$C$58)*G73 -> 0 | H76: =H75*(1+$C$58)/($C$54-$C$58)*H73 -> 0 | I76: =I75*(1+$C$58)/($C$54-$C$58)*I73 -> 0 | J76: =J75*(1+$C$58)/($C$54-$C$58)*J73 -> 0 | K76: =K75*(1+$C$58)/($C$54-$C$58)*K73 -> 0 | ... AV76: =AV75*(1+$C$58)/($C$54-$C$58)*AV73 -> 0
B78: PV of explicit / concession-life cash flows | C78: =SUM($D$74:$AV$74) -> 2669.7173
B79: PV of terminal value | C79: =SUM($D$76:$AV$76) -> 0
B80: ENTERPRISE VALUE — Escota (100%) | C80: =C78+C79 -> 2669.7173
B81: Terminal value as % of block EV | C81: =IF(C80=0,0,C79/C80) -> 0
B82: Implied EV / FY2026E EBITDA | C82: =IF(D64=0,0,C80/D64) -> 3.9375724
B83: Terminal FCF base (for sensitivity) | C83: =SUM($D$75:$AV$75) -> 0
B84: Terminal discount period (for sensitivity) | C84: =SUMPRODUCT(($D$61:$AV$61=$C$57)*$D$72:$AV$72) -> 0
B85: Check: WACC > g and no cash flow after concession end | C85: =IF(AND($C$54>$C$58,SUMPRODUCT(($D$61:$AV$61>YEAR($C$56))*($C$55=1)*ABS($D$71:$AV$71))=0),"OK","REVISAR") -> OK
B88: Cofiroute
B89: Base revenue FY2025 (EUR m) | C89: 1684 | D89: Cofiroute intercity network 1,100 km, 100%. Tariffs index at 83% of inflation to end of concession (URD). Base revenue = FY2025 VINCI Autoroutes revenue by network (URD 2025: ASF 3,929 / Cofiroute 1,684 / Escota 961 / others 159). ASSUMPTION: segment margin (EBITDA 4,784 / revenue 6,733), D&A (1,503), capex (23 operating + 565 growth = 8.7%) and leases (12) applied pro rata to revenue — no network-level accounts available. FY2026 growth −0.7% = H1 2026 revenue trend (traffic −2.9%). FY2027+ 2.1% = Vinci's own average revenue growth over ASF's residual life (impairment note). Capex held at 8.7% to the end as a proxy for hand-back (biens de retour) obligations. WACC 6.5%: low-risk tolled infrastructure (Rf ~3.0%, ERP ~5.0%, beta ~0.75) plus ~50bp for French fiscal/regulatory risk (TELD tax, surtax, tariff risk). End date = 31 Dec of the contract year (FS Note F.12 gives the year only). Contracts revert to the State at no cost → no terminal value.
B90: Revenue growth FY2026 | C90: -0.007
B91: Revenue growth FY2027+ | C91: 0.021
B92: EBITDA margin (CFO before tax & financing / revenue) | C92: 0.7105
B93: D&A % revenue | C93: 0.2232
B94: Capex % revenue (operating + growth investments) | C94: 0.0873
B95: Lease repayments % revenue | C95: 0.0018
B96: Discount rate (post-tax WACC) | C96: 0.065
B97: Type: 1 = finite concession (TV = 0) · 0 = going concern | C97: 1
B98: Concession end date (finite only) | C98: 49309
B99: Last explicit year (going concern only) | C99: 0
B100: Terminal growth g (going concern only) | C100: 0
B101: Terminal capex % revenue (going concern only) | C101: 0
B103: Fiscal year | D103: 2026 | E103: 2027 | F103: 2028 | G103: 2029 | H103: 2030 | I103: 2031 | J103: 2032 | K103: 2033 | L103: 2034 | M103: 2035 | N103: 2036 | O103: 2037 | P103: 2038 | Q103: 2039 | R103: 2040 | S103: 2041 | T103: 2042 | U103: 2043 | V103: 2044 | W103: 2045 | X103: 2046 | Y103: 2047 | Z103: 2048 | AA103: 2049 | AB103: 2050 | AC103: 2051 | AD103: 2052 | AE103: 2053 | AF103: 2054 | AG103: 2055 | AH103: 2056 | AI103: 2057 | AJ103: 2058 | AK103: 2059 | AL103: 2060 | AM103: 2061 | AN103: 2062 | AO103: 2063 | AP103: 2064 | AQ103: 2065 | AR103: 2066 | AS103: 2067 | AT103: 2068 | AU103: 2069 | AV103: 2070
B104: Fraction of year in valuation (after val. date / before concession end) | D104: =IF($C$97=1,MAX(0,MIN(DATE(D$103,12,31),$C$98)-MAX(Inputs!$C$5+1,DATE(D$103,1,1))+1)/365,IF(D$103<=$C$99,(DATE(D$103,12,31)-MAX(Inputs!$C$5+1,DATE(D$103,1,1))+1)/365,0)) -> 0.50410959 | E104: =IF($C$97=1,MAX(0,MIN(DATE(E$103,12,31),$C$98)-MAX(Inputs!$C$5+1,DATE(E$103,1,1))+1)/365,IF(E$103<=$C$99,(DATE(E$103,12,31)-MAX(Inputs!$C$5+1,DATE(E$103,1,1))+1)/365,0)) -> 1 | F104: =IF($C$97=1,MAX(0,MIN(DATE(F$103,12,31),$C$98)-MAX(Inputs!$C$5+1,DATE(F$103,1,1))+1)/365,IF(F$103<=$C$99,(DATE(F$103,12,31)-MAX(Inputs!$C$5+1,DATE(F$103,1,1))+1)/365,0)) -> 1.0027397 | G104: =IF($C$97=1,MAX(0,MIN(DATE(G$103,12,31),$C$98)-MAX(Inputs!$C$5+1,DATE(G$103,1,1))+1)/365,IF(G$103<=$C$99,(DATE(G$103,12,31)-MAX(Inputs!$C$5+1,DATE(G$103,1,1))+1)/365,0)) -> 1 | H104: =IF($C$97=1,MAX(0,MIN(DATE(H$103,12,31),$C$98)-MAX(Inputs!$C$5+1,DATE(H$103,1,1))+1)/365,IF(H$103<=$C$99,(DATE(H$103,12,31)-MAX(Inputs!$C$5+1,DATE(H$103,1,1))+1)/365,0)) -> 1 | I104: =IF($C$97=1,MAX(0,MIN(DATE(I$103,12,31),$C$98)-MAX(Inputs!$C$5+1,DATE(I$103,1,1))+1)/365,IF(I$103<=$C$99,(DATE(I$103,12,31)-MAX(Inputs!$C$5+1,DATE(I$103,1,1))+1)/365,0)) -> 1 | J104: =IF($C$97=1,MAX(0,MIN(DATE(J$103,12,31),$C$98)-MAX(Inputs!$C$5+1,DATE(J$103,1,1))+1)/365,IF(J$103<=$C$99,(DATE(J$103,12,31)-MAX(Inputs!$C$5+1,DATE(J$103,1,1))+1)/365,0)) -> 1.0027397 | K104: =IF($C$97=1,MAX(0,MIN(DATE(K$103,12,31),$C$98)-MAX(Inputs!$C$5+1,DATE(K$103,1,1))+1)/365,IF(K$103<=$C$99,(DATE(K$103,12,31)-MAX(Inputs!$C$5+1,DATE(K$103,1,1))+1)/365,0)) -> 1 | ... AV104: =IF($C$97=1,MAX(0,MIN(DATE(AV$103,12,31),$C$98)-MAX(Inputs!$C$5+1,DATE(AV$103,1,1))+1)/365,IF(AV$103<=$C$99,(DATE(AV$103,12,31)-MAX(Inputs!$C$5+1,DATE(AV$103,1,1))+1)/365,0)) -> 0
B105: Revenue (full-year run-rate) | D105: =$C$89*(1+$C$90) -> 1672.212 | E105: =D105*(1+$C$91) -> 1707.3285 | F105: =E105*(1+$C$91) -> 1743.1823 | G105: =F105*(1+$C$91) -> 1779.7892 | H105: =G105*(1+$C$91) -> 1817.1648 | I105: =H105*(1+$C$91) -> 1855.3252 | J105: =I105*(1+$C$91) -> 1894.287 | K105: =J105*(1+$C$91) -> 1934.0671 | L105: =K105*(1+$C$91) -> 1974.6825 | ... AV105: =AU105*(1+$C$91) -> 4172.7656
B106: EBITDA | D106: =D105*$C$92 -> 1188.1066 | E106: =E105*$C$92 -> 1213.0569 | F106: =F105*$C$92 -> 1238.5311 | G106: =G105*$C$92 -> 1264.5402 | H106: =H105*$C$92 -> 1291.0956 | I106: =I105*$C$92 -> 1318.2086 | J106: =J105*$C$92 -> 1345.8909 | K106: =K105*$C$92 -> 1374.1547 | ... AV106: =AV105*$C$92 -> 2964.7499
B107: D&A | D107: =-D105*$C$93 -> -373.23772 | E107: =-E105*$C$93 -> -381.07571 | F107: =-F105*$C$93 -> -389.0783 | G107: =-G105*$C$93 -> -397.24894 | H107: =-H105*$C$93 -> -405.59117 | I107: =-I105*$C$93 -> -414.10859 | J107: =-J105*$C$93 -> -422.80487 | K107: =-K105*$C$93 -> -431.68377 | ... AV107: =-AV105*$C$93 -> -931.36128
B108: EBIT | D108: =D106+D107 -> 814.86891 | E108: =E106+E107 -> 831.98115 | F108: =F106+F107 -> 849.45276 | G108: =G106+G107 -> 867.29127 | H108: =H106+H107 -> 885.50438 | I108: =I106+I107 -> 904.09998 | J108: =J106+J107 -> 923.08607 | K108: =K106+K107 -> 942.47088 | ... AV108: =AV106+AV107 -> 2033.3887
B109: Tax rate | D109: =IF(D$103=2026,Inputs!$C$10,Inputs!$C$11) -> 0.348 | E109: =IF(E$103=2026,Inputs!$C$10,Inputs!$C$11) -> 0.258 | F109: =IF(F$103=2026,Inputs!$C$10,Inputs!$C$11) -> 0.258 | G109: =IF(G$103=2026,Inputs!$C$10,Inputs!$C$11) -> 0.258 | H109: =IF(H$103=2026,Inputs!$C$10,Inputs!$C$11) -> 0.258 | I109: =IF(I$103=2026,Inputs!$C$10,Inputs!$C$11) -> 0.258 | J109: =IF(J$103=2026,Inputs!$C$10,Inputs!$C$11) -> 0.258 | K109: =IF(K$103=2026,Inputs!$C$10,Inputs!$C$11) -> 0.258 | ... AV109: =IF(AV$103=2026,Inputs!$C$10,Inputs!$C$11) -> 0.258
B110: Tax on EBIT | D110: =-MAX(0,D108)*D109 -> -283.57438 | E110: =-MAX(0,E108)*E109 -> -214.65114 | F110: =-MAX(0,F108)*F109 -> -219.15881 | G110: =-MAX(0,G108)*G109 -> -223.76115 | H110: =-MAX(0,H108)*H109 -> -228.46013 | I110: =-MAX(0,I108)*I109 -> -233.25779 | J110: =-MAX(0,J108)*J109 -> -238.15621 | K110: =-MAX(0,K108)*K109 -> -243.15749 | ... AV110: =-MAX(0,AV108)*AV109 -> -524.61428
B111: Capex | D111: =-D105*$C$94 -> -145.98411 | E111: =-E105*$C$94 -> -149.04977 | F111: =-F105*$C$94 -> -152.17982 | G111: =-G105*$C$94 -> -155.3756 | H111: =-H105*$C$94 -> -158.63848 | I111: =-I105*$C$94 -> -161.96989 | J111: =-J105*$C$94 -> -165.37126 | K111: =-K105*$C$94 -> -168.84406 | ... AV111: =-AV105*$C$94 -> -364.28244
...

Sheet Airports
B2: Airports — airports by ownership regime
B4: Gatwick + Edinburgh (freehold, 50.01%)
B5: Base revenue FY2025 (EUR m) | C5: 1740 | D5: Revenue FY2025: Gatwick 1,321 + Edinburgh 419 (Note I.23.5). ASSUMPTION: VINCI Airports segment margin 63.4%, D&A 11.7%, capex 13.3% (375 operating + 263 growth), leases 0.5% applied. Explicit to 2035 (covers Gatwick northern-runway capex cycle), then Gordon with g 2.0% and normalised capex 6%. Owned outright → a terminal value is legitimate. Consolidated at 100%; the 49.99% third-party share is deducted in the SOTP bridge on implied equity value. H1 2026 VINCI Airports revenue +1.8% → 2.0% for FY2026.
B6: Revenue growth FY2026 | C6: 0.02
B7: Revenue growth FY2027+ | C7: 0.035
B8: EBITDA margin (CFO before tax & financing / revenue) | C8: 0.6343
B9: D&A % revenue | C9: 0.1172
B10: Capex % revenue (operating + growth investments) | C10: 0.133
B11: Lease repayments % revenue | C11: 0.0048
B12: Discount rate (post-tax WACC) | C12: 0.075
B13: Type: 1 = finite concession (TV = 0) · 0 = going concern | C13: 0
B14: Concession end date (finite only) | C14: 46387
B15: Last explicit year (going concern only) | C15: 2035
B16: Terminal growth g (going concern only) | C16: 0.02
B17: Terminal capex % revenue (going concern only) | C17: 0.06
B19: Fiscal year | D19: 2026 | E19: 2027 | F19: 2028 | G19: 2029 | H19: 2030 | I19: 2031 | J19: 2032 | K19: 2033 | L19: 2034 | M19: 2035 | N19: 2036 | O19: 2037 | P19: 2038 | Q19: 2039 | R19: 2040 | S19: 2041 | T19: 2042 | U19: 2043 | V19: 2044 | W19: 2045 | X19: 2046 | Y19: 2047 | Z19: 2048 | AA19: 2049 | AB19: 2050 | AC19: 2051 | AD19: 2052 | AE19: 2053 | AF19: 2054 | AG19: 2055 | AH19: 2056 | AI19: 2057 | AJ19: 2058 | AK19: 2059 | AL19: 2060 | AM19: 2061 | AN19: 2062 | AO19: 2063 | AP19: 2064 | AQ19: 2065 | AR19: 2066 | AS19: 2067 | AT19: 2068 | AU19: 2069 | AV19: 2070
B20: Fraction of year in valuation (after val. date / before concession end) | D20: =IF($C$13=1,MAX(0,MIN(DATE(D$19,12,31),$C$14)-MAX(Inputs!$C$5+1,DATE(D$19,1,1))+1)/365,IF(D$19<=$C$15,(DATE(D$19,12,31)-MAX(Inputs!$C$5+1,DATE(D$19,1,1))+1)/365,0)) -> 0.50410959 | E20: =IF($C$13=1,MAX(0,MIN(DATE(E$19,12,31),$C$14)-MAX(Inputs!$C$5+1,DATE(E$19,1,1))+1)/365,IF(E$19<=$C$15,(DATE(E$19,12,31)-MAX(Inputs!$C$5+1,DATE(E$19,1,1))+1)/365,0)) -> 1 | F20: =IF($C$13=1,MAX(0,MIN(DATE(F$19,12,31),$C$14)-MAX(Inputs!$C$5+1,DATE(F$19,1,1))+1)/365,IF(F$19<=$C$15,(DATE(F$19,12,31)-MAX(Inputs!$C$5+1,DATE(F$19,1,1))+1)/365,0)) -> 1.0027397 | G20: =IF($C$13=1,MAX(0,MIN(DATE(G$19,12,31),$C$14)-MAX(Inputs!$C$5+1,DATE(G$19,1,1))+1)/365,IF(G$19<=$C$15,(DATE(G$19,12,31)-MAX(Inputs!$C$5+1,DATE(G$19,1,1))+1)/365,0)) -> 1 | H20: =IF($C$13=1,MAX(0,MIN(DATE(H$19,12,31),$C$14)-MAX(Inputs!$C$5+1,DATE(H$19,1,1))+1)/365,IF(H$19<=$C$15,(DATE(H$19,12,31)-MAX(Inputs!$C$5+1,DATE(H$19,1,1))+1)/365,0)) -> 1 | I20: =IF($C$13=1,MAX(0,MIN(DATE(I$19,12,31),$C$14)-MAX(Inputs!$C$5+1,DATE(I$19,1,1))+1)/365,IF(I$19<=$C$15,(DATE(I$19,12,31)-MAX(Inputs!$C$5+1,DATE(I$19,1,1))+1)/365,0)) -> 1 | J20: =IF($C$13=1,MAX(0,MIN(DATE(J$19,12,31),$C$14)-MAX(Inputs!$C$5+1,DATE(J$19,1,1))+1)/365,IF(J$19<=$C$15,(DATE(J$19,12,31)-MAX(Inputs!$C$5+1,DATE(J$19,1,1))+1)/365,0)) -> 1.0027397 | K20: =IF($C$13=1,MAX(0,MIN(DATE(K$19,12,31),$C$14)-MAX(Inputs!$C$5+1,DATE(K$19,1,1))+1)/365,IF(K$19<=$C$15,(DATE(K$19,12,31)-MAX(Inputs!$C$5+1,DATE(K$19,1,1))+1)/365,0)) -> 1 | ... AV20: =IF($C$13=1,MAX(0,MIN(DATE(AV$19,12,31),$C$14)-MAX(Inputs!$C$5+1,DATE(AV$19,1,1))+1)/365,IF(AV$19<=$C$15,(DATE(AV$19,12,31)-MAX(Inputs!$C$5+1,DATE(AV$19,1,1))+1)/365,0)) -> 0
B21: Revenue (full-year run-rate) | D21: =$C$5*(1+$C$6) -> 1774.8 | E21: =D21*(1+$C$7) -> 1836.918 | F21: =E21*(1+$C$7) -> 1901.2101 | G21: =F21*(1+$C$7) -> 1967.7525 | H21: =G21*(1+$C$7) -> 2036.6238 | I21: =H21*(1+$C$7) -> 2107.9057 | J21: =I21*(1+$C$7) -> 2181.6824 | K21: =J21*(1+$C$7) -> 2258.0412 | L21: =K21*(1+$C$7) -> 2337.0727 | ... AV21: =AU21*(1+$C$7) -> 8063.5227
B22: EBITDA | D22: =D21*$C$8 -> 1125.7556 | E22: =E21*$C$8 -> 1165.1571 | F22: =F21*$C$8 -> 1205.9376 | G22: =G21*$C$8 -> 1248.1454 | H22: =H21*$C$8 -> 1291.8305 | I22: =I21*$C$8 -> 1337.0446 | J22: =J21*$C$8 -> 1383.8411 | K22: =K21*$C$8 -> 1432.2756 | ... AV22: =AV21*$C$8 -> 5114.6924
B23: D&A | D23: =-D21*$C$9 -> -208.00656 | E23: =-E21*$C$9 -> -215.28679 | F23: =-F21*$C$9 -> -222.82183 | G23: =-G21*$C$9 -> -230.62059 | H23: =-H21*$C$9 -> -238.69231 | I23: =-I21*$C$9 -> -247.04654 | J23: =-J21*$C$9 -> -255.69317 | K23: =-K21*$C$9 -> -264.64243 | ... AV23: =-AV21*$C$9 -> -945.04486
B24: EBIT | D24: =D22+D23 -> 917.74908 | E24: =E22+E23 -> 949.8703 | F24: =F22+F23 -> 983.11576 | G24: =G22+G23 -> 1017.5248 | H24: =H22+H23 -> 1053.1382 | I24: =I22+I23 -> 1089.998 | J24: =J22+J23 -> 1128.1479 | K24: =K22+K23 -> 1167.6331 | ... AV24: =AV22+AV23 -> 4169.6476
B25: Tax rate | D25: =IF(D$19=2026,Inputs!$C$10,Inputs!$C$11) -> 0.348 | E25: =IF(E$19=2026,Inputs!$C$10,Inputs!$C$11) -> 0.258 | F25: =IF(F$19=2026,Inputs!$C$10,Inputs!$C$11) -> 0.258 | G25: =IF(G$19=2026,Inputs!$C$10,Inputs!$C$11) -> 0.258 | H25: =IF(H$19=2026,Inputs!$C$10,Inputs!$C$11) -> 0.258 | I25: =IF(I$19=2026,Inputs!$C$10,Inputs!$C$11) -> 0.258 | J25: =IF(J$19=2026,Inputs!$C$10,Inputs!$C$11) -> 0.258 | K25: =IF(K$19=2026,Inputs!$C$10,Inputs!$C$11) -> 0.258 | ... AV25: =IF(AV$19=2026,Inputs!$C$10,Inputs!$C$11) -> 0.258
B26: Tax on EBIT | D26: =-MAX(0,D24)*D25 -> -319.37668 | E26: =-MAX(0,E24)*E25 -> -245.06654 | F26: =-MAX(0,F24)*F25 -> -253.64387 | G26: =-MAX(0,G24)*G25 -> -262.5214 | H26: =-MAX(0,H24)*H25 -> -271.70965 | I26: =-MAX(0,I24)*I25 -> -281.21949 | J26: =-MAX(0,J24)*J25 -> -291.06217 | K26: =-MAX(0,K24)*K25 -> -301.24935 | ... AV26: =-MAX(0,AV24)*AV25 -> -1075.7691
B27: Capex | D27: =-D21*$C$10 -> -236.0484 | E27: =-E21*$C$10 -> -244.31009 | F27: =-F21*$C$10 -> -252.86095 | G27: =-G21*$C$10 -> -261.71108 | H27: =-H21*$C$10 -> -270.87097 | I27: =-I21*$C$10 -> -280.35145 | J27: =-J21*$C$10 -> -290.16375 | K27: =-K21*$C$10 -> -300.31948 | ... AV27: =-AV21*$C$10 -> -1072.4485
B28: Lease repayments | D28: =-D21*$C$11 -> -8.51904 | E28: =-E21*$C$11 -> -8.8172064 | F28: =-F21*$C$11 -> -9.1258086 | G28: =-G21*$C$11 -> -9.4452119 | H28: =-H21*$C$11 -> -9.7757943 | I28: =-I21*$C$11 -> -10.117947 | J28: =-J21*$C$11 -> -10.472075 | K28: =-K21*$C$11 -> -10.838598 | ... AV28: =-AV21*$C$11 -> -38.704909
B29: Unlevered FCF in valuation window | D29: =(D22+D26+D27+D28)*D20 -> 283.21457 | E29: =(E22+E26+E27+E28)*E20 -> 666.96325 | F29: =(F22+F26+F27+F28)*F20 -> 692.19822 | G29: =(G22+G26+G27+G28)*G20 -> 714.46771 | H29: =(H22+H26+H27+H28)*H20 -> 739.47408 | I29: =(I22+I26+I27+I28)*I20 -> 765.35567 | J29: =(J22+J26+J27+J28)*J20 -> 794.31337 | K29: =(K22+K26+K27+K28)*K20 -> 819.86813 | ... AV29: =(AV22+AV26+AV27+AV28)*AV20 -> 0
B30: Discount period (mid-period, years) | D30: =((MAX(Inputs!$C$5+1,DATE(D$19,1,1))+DATE(D$19,12,31))/2-Inputs!$C$5)/365 -> 0.25342466 | E30: =((MAX(Inputs!$C$5+1,DATE(E$19,1,1))+DATE(E$19,12,31))/2-Inputs!$C$5)/365 -> 1.0054795 | F30: =((MAX(Inputs!$C$5+1,DATE(F$19,1,1))+DATE(F$19,12,31))/2-Inputs!$C$5)/365 -> 2.0068493 | G30: =((MAX(Inputs!$C$5+1,DATE(G$19,1,1))+DATE(G$19,12,31))/2-Inputs!$C$5)/365 -> 3.0082192 | H30: =((MAX(Inputs!$C$5+1,DATE(H$19,1,1))+DATE(H$19,12,31))/2-Inputs!$C$5)/365 -> 4.0082192 | I30: =((MAX(Inputs!$C$5+1,DATE(I$19,1,1))+DATE(I$19,12,31))/2-Inputs!$C$5)/365 -> 5.0082192 | J30: =((MAX(Inputs!$C$5+1,DATE(J$19,1,1))+DATE(J$19,12,31))/2-Inputs!$C$5)/365 -> 6.009589 | K30: =((MAX(Inputs!$C$5+1,DATE(K$19,1,1))+DATE(K$19,12,31))/2-Inputs!$C$5)/365 -> 7.0109589 | ... AV30: =((MAX(Inputs!$C$5+1,DATE(AV$19,1,1))+DATE(AV$19,12,31))/2-Inputs!$C$5)/365 -> 44.035616
B31: Discount factor | D31: =1/(1+$C$12)^D30 -> 0.98183909 | E31: =1/(1+$C$12)^E30 -> 0.929864 | F31: =1/(1+$C$12)^F30 -> 0.86490408 | G31: =1/(1+$C$12)^G30 -> 0.80448223 | H31: =1/(1+$C$12)^H30 -> 0.74835556 | I31: =1/(1+$C$12)^I30 -> 0.69614471 | J31: =1/(1+$C$12)^J30 -> 0.64751232 | K31: =1/(1+$C$12)^K30 -> 0.60227737 | ... AV31: =1/(1+$C$12)^AV30 -> 0.041391286
B32: PV of UFCF | D32: =D29*D31 -> 278.07114 | E32: =E29*E31 -> 620.18512 | F32: =F29*F31 -> 598.68506 | G32: =G29*G31 -> 574.77657 | H32: =H29*H31 -> 553.38954 | I32: =I29*I31 -> 532.7983 | J32: =J29*J31 -> 514.3277 | K32: =K29*K31 -> 493.78802 | ... AV32: =AV29*AV31 -> 0
B33: Terminal-year normalised FCF (before growth) | D33: =IF(AND($C$13=0,D$19=$C$15),D22-D21*($C$17+$C$11)-MAX(0,D22-D21*$C$17)*Inputs!$C$11,0) -> 0 | E33: =IF(AND($C$13=0,E$19=$C$15),E22-E21*($C$17+$C$11)-MAX(0,E22-E21*$C$17)*Inputs!$C$11,0) -> 0 | F33: =IF(AND($C$13=0,F$19=$C$15),F22-F21*($C$17+$C$11)-MAX(0,F22-F21*$C$17)*Inputs!$C$11,0) -> 0 | G33: =IF(AND($C$13=0,G$19=$C$15),G22-G21*($C$17+$C$11)-MAX(0,G22-G21*$C$17)*Inputs!$C$11,0) -> 0 | H33: =IF(AND($C$13=0,H$19=$C$15),H22-H21*($C$17+$C$11)-MAX(0,H22-H21*$C$17)*Inputs!$C$11,0) -> 0 | I33: =IF(AND($C$13=0,I$19=$C$15),I22-I21*($C$17+$C$11)-MAX(0,I22-I21*$C$17)*Inputs!$C$11,0) -> 0 | J33: =IF(AND($C$13=0,J$19=$C$15),J22-J21*($C$17+$C$11)-MAX(0,J22-J21*$C$17)*Inputs!$C$11,0) -> 0 | K33: =IF(AND($C$13=0,K$19=$C$15),K22-K21*($C$17+$C$11)-MAX(0,K22-K21*$C$17)*Inputs!$C$11,0) -> 0 | ... AV33: =IF(AND($C$13=0,AV$19=$C$15),AV22-AV21*($C$17+$C$11)-MAX(0,AV22-AV21*$C$17)*Inputs!$C$11,0) -> 0
B34: PV of terminal value | D34: =D33*(1+$C$16)/($C$12-$C$16)*D31 -> 0 | E34: =E33*(1+$C$16)/($C$12-$C$16)*E31 -> 0 | F34: =F33*(1+$C$16)/($C$12-$C$16)*F31 -> 0 | G34: =G33*(1+$C$16)/($C$12-$C$16)*G31 -> 0 | H34: =H33*(1+$C$16)/($C$12-$C$16)*H31 -> 0 | I34: =I33*(1+$C$16)/($C$12-$C$16)*I31 -> 0 | J34: =J33*(1+$C$16)/($C$12-$C$16)*J31 -> 0 | K34: =K33*(1+$C$16)/($C$12-$C$16)*K31 -> 0 | ... AV34: =AV33*(1+$C$16)/($C$12-$C$16)*AV31 -> 0
B36: PV of explicit / concession-life cash flows | C36: =SUM($D$32:$AV$32) -> 5099.1606
B37: PV of terminal value | C37: =SUM($D$34:$AV$34) -> 9850.3729
B38: ENTERPRISE VALUE — Gatwick + Edinburgh (freehold, 50.01%) (100%) | C38: =C36+C37 -> 14949.534
B39: Terminal value as % of block EV | C39: =IF(C38=0,0,C37/C38) -> 0.65890838
B40: Implied EV / FY2026E EBITDA | C40: =IF(D22=0,0,C38/D22) -> 13.279555
B41: Terminal FCF base (for sensitivity) | C41: =SUM($D$33:$AV$33) -> 1019.144
B42: Terminal discount period (for sensitivity) | C42: =SUMPRODUCT(($D$19:$AV$19=$C$15)*$D$30:$AV$30) -> 9.0109589
B43: Check: WACC > g and no cash flow after concession end | C43: =IF(AND($C$12>$C$16,SUMPRODUCT(($D$19:$AV$19>YEAR($C$14))*($C$13=1)*ABS($D$29:$AV$29))=0),"OK","REVISAR") -> OK
B46: OMA Mexico (to 2048, 29.99%)
B47: Base revenue FY2025 (EUR m) | C47: 633 | D47: Revenue FY2025 633 (Note I.23.5). 13 airports, concession ends 2048. Fully consolidated with 29.99% economic interest → 70.01% deducted in bridge on implied equity value. WACC 9.5% for Mexican country risk and MXN exposure. Growth 4.0% (nominal MXN-linked, below Vinci airports average 3.9% + inflation differential). Segment-average margins (ASSUMPTION).
B48: Revenue growth FY2026 | C48: 0.02
B49: Revenue growth FY2027+ | C49: 0.04
B50: EBITDA margin (CFO before tax & financing / revenue) | C50: 0.6343
B51: D&A % revenue | C51: 0.1172
B52: Capex % revenue (operating + growth investments) | C52: 0.133
B53: Lease repayments % revenue | C53: 0.0048
B54: Discount rate (post-tax WACC) | C54: 0.095
B55: Type: 1 = finite concession (TV = 0) · 0 = going concern | C55: 1
B56: Concession end date (finite only) | C56: 54423
B57: Last explicit year (going concern only) | C57: 0
B58: Terminal growth g (going concern only) | C58: 0
B59: Terminal capex % revenue (going concern only) | C59: 0
B61: Fiscal year | D61: 2026 | E61: 2027 | F61: 2028 | G61: 2029 | H61: 2030 | I61: 2031 | J61: 2032 | K61: 2033 | L61: 2034 | M61: 2035 | N61: 2036 | O61: 2037 | P61: 2038 | Q61: 2039 | R61: 2040 | S61: 2041 | T61: 2042 | U61: 2043 | V61: 2044 | W61: 2045 | X61: 2046 | Y61: 2047 | Z61: 2048 | AA61: 2049 | AB61: 2050 | AC61: 2051 | AD61: 2052 | AE61: 2053 | AF61: 2054 | AG61: 2055 | AH61: 2056 | AI61: 2057 | AJ61: 2058 | AK61: 2059 | AL61: 2060 | AM61: 2061 | AN61: 2062 | AO61: 2063 | AP61: 2064 | AQ61: 2065 | AR61: 2066 | AS61: 2067 | AT61: 2068 | AU61: 2069 | AV61: 2070
B62: Fraction of year in valuation (after val. date / before concession end) | D62: =IF($C$55=1,MAX(0,MIN(DATE(D$61,12,31),$C$56)-MAX(Inputs!$C$5+1,DATE(D$61,1,1))+1)/365,IF(D$61<=$C$57,(DATE(D$61,12,31)-MAX(Inputs!$C$5+1,DATE(D$61,1,1))+1)/365,0)) -> 0.50410959 | E62: =IF($C$55=1,MAX(0,MIN(DATE(E$61,12,31),$C$56)-MAX(Inputs!$C$5+1,DATE(E$61,1,1))+1)/365,IF(E$61<=$C$57,(DATE(E$61,12,31)-MAX(Inputs!$C$5+1,DATE(E$61,1,1))+1)/365,0)) -> 1 | F62: =IF($C$55=1,MAX(0,MIN(DATE(F$61,12,31),$C$56)-MAX(Inputs!$C$5+1,DATE(F$61,1,1))+1)/365,IF(F$61<=$C$57,(DATE(F$61,12,31)-MAX(Inputs!$C$5+1,DATE(F$61,1,1))+1)/365,0)) -> 1.0027397 | G62: =IF($C$55=1,MAX(0,MIN(DATE(G$61,12,31),$C$56)-MAX(Inputs!$C$5+1,DATE(G$61,1,1))+1)/365,IF(G$61<=$C$57,(DATE(G$61,12,31)-MAX(Inputs!$C$5+1,DATE(G$61,1,1))+1)/365,0)) -> 1 | H62: =IF($C$55=1,MAX(0,MIN(DATE(H$61,12,31),$C$56)-MAX(Inputs!$C$5+1,DATE(H$61,1,1))+1)/365,IF(H$61<=$C$57,(DATE(H$61,12,31)-MAX(Inputs!$C$5+1,DATE(H$61,1,1))+1)/365,0)) -> 1 | I62: =IF($C$55=1,MAX(0,MIN(DATE(I$61,12,31),$C$56)-MAX(Inputs!$C$5+1,DATE(I$61,1,1))+1)/365,IF(I$61<=$C$57,(DATE(I$61,12,31)-MAX(Inputs!$C$5+1,DATE(I$61,1,1))+1)/365,0)) -> 1 | J62: =IF($C$55=1,MAX(0,MIN(DATE(J$61,12,31),$C$56)-MAX(Inputs!$C$5+1,DATE(J$61,1,1))+1)/365,IF(J$61<=$C$57,(DATE(J$61,12,31)-MAX(Inputs!$C$5+1,DATE(J$61,1,1))+1)/365,0)) -> 1.0027397 | K62: =IF($C$55=1,MAX(0,MIN(DATE(K$61,12,31),$C$56)-MAX(Inputs!$C$5+1,DATE(K$61,1,1))+1)/365,IF(K$61<=$C$57,(DATE(K$61,12,31)-MAX(Inputs!$C$5+1,DATE(K$61,1,1))+1)/365,0)) -> 1 | ... AV62: =IF($C$55=1,MAX(0,MIN(DATE(AV$61,12,31),$C$56)-MAX(Inputs!$C$5+1,DATE(AV$61,1,1))+1)/365,IF(AV$61<=$C$57,(DATE(AV$61,12,31)-MAX(Inputs!$C$5+1,DATE(AV$61,1,1))+1)/365,0)) -> 0
B63: Revenue (full-year run-rate) | D63: =$C$47*(1+$C$48) -> 645.66 | E63: =D63*(1+$C$49) -> 671.4864 | F63: =E63*(1+$C$49) -> 698.34586 | G63: =F63*(1+$C$49) -> 726.27969 | H63: =G63*(1+$C$49) -> 755.33088 | I63: =H63*(1+$C$49) -> 785.54411 | J63: =I63*(1+$C$49) -> 816.96588 | K63: =J63*(1+$C$49) -> 849.64451 | L63: =K63*(1+$C$49) -> 883.63029 | ... AV63: =AU63*(1+$C$49) -> 3626.3591
B64: EBITDA | D64: =D63*$C$50 -> 409.54214 | E64: =E63*$C$50 -> 425.92382 | F64: =F63*$C$50 -> 442.96078 | G64: =G63*$C$50 -> 460.67921 | H64: =H63*$C$50 -> 479.10638 | I64: =I63*$C$50 -> 498.27063 | J64: =J63*$C$50 -> 518.20146 | K64: =K63*$C$50 -> 538.92951 | ... AV64: =AV63*$C$50 -> 2300.1996
B65: D&A | D65: =-D63*$C$51 -> -75.671352 | E65: =-E63*$C$51 -> -78.698206 | F65: =-F63*$C$51 -> -81.846134 | G65: =-G63*$C$51 -> -85.11998 | H65: =-H63*$C$51 -> -88.524779 | I65: =-I63*$C$51 -> -92.06577 | J65: =-J63*$C$51 -> -95.748401 | K65: =-K63*$C$51 -> -99.578337 | ... AV65: =-AV63*$C$51 -> -425.00929
B66: EBIT | D66: =D64+D65 -> 333.87079 | E66: =E64+E65 -> 347.22562 | F66: =F64+F65 -> 361.11464 | G66: =G64+G65 -> 375.55923 | H66: =H64+H65 -> 390.5816 | I66: =I64+I65 -> 406.20486 | J66: =J64+J65 -> 422.45306 | K66: =K64+K65 -> 439.35118 | ... AV66: =AV64+AV65 -> 1875.1903
B67: Tax rate | D67: =IF(D$61=2026,Inputs!$C$10,Inputs!$C$11) -> 0.348 | E67: =IF(E$61=2026,Inputs!$C$10,Inputs!$C$11) -> 0.258 | F67: =IF(F$61=2026,Inputs!$C$10,Inputs!$C$11) -> 0.258 | G67: =IF(G$61=2026,Inputs!$C$10,Inputs!$C$11) -> 0.258 | H67: =IF(H$61=2026,Inputs!$C$10,Inputs!$C$11) -> 0.258 | I67: =IF(I$61=2026,Inputs!$C$10,Inputs!$C$11) -> 0.258 | J67: =IF(J$61=2026,Inputs!$C$10,Inputs!$C$11) -> 0.258 | K67: =IF(K$61=2026,Inputs!$C$10,Inputs!$C$11) -> 0.258 | ... AV67: =IF(AV$61=2026,Inputs!$C$10,Inputs!$C$11) -> 0.258
B68: Tax on EBIT | D68: =-MAX(0,D66)*D67 -> -116.18703 | E68: =-MAX(0,E66)*E67 -> -89.584209 | F68: =-MAX(0,F66)*F67 -> -93.167578 | G68: =-MAX(0,G66)*G67 -> -96.894281 | H68: =-MAX(0,H66)*H67 -> -100.77005 | I68: =-MAX(0,I66)*I67 -> -104.80085 | J68: =-MAX(0,J66)*J67 -> -108.99289 | K68: =-MAX(0,K66)*K67 -> -113.3526 | ... AV68: =-MAX(0,AV66)*AV67 -> -483.7991
B69: Capex | D69: =-D63*$C$52 -> -85.87278 | E69: =-E63*$C$52 -> -89.307691 | F69: =-F63*$C$52 -> -92.879999 | G69: =-G63*$C$52 -> -96.595199 | H69: =-H63*$C$52 -> -100.45901 | I69: =-I63*$C$52 -> -104.47737 | J69: =-J63*$C$52 -> -108.65646 | K69: =-K63*$C$52 -> -113.00272 | ... AV69: =-AV63*$C$52 -> -482.30576
B70: Lease repayments | D70: =-D63*$C$53 -> -3.099168 | E70: =-E63*$C$53 -> -3.2231347 | F70: =-F63*$C$53 -> -3.3520601 | G70: =-G63*$C$53 -> -3.4861425 | H70: =-H63*$C$53 -> -3.6255882 | I70: =-I63*$C$53 -> -3.7706117 | J70: =-J63*$C$53 -> -3.9214362 | K70: =-K63*$C$53 -> -4.0782937 | ... AV70: =-AV63*$C$53 -> -17.406524
B71: Unlevered FCF in valuation window | D71: =(D64+D68+D69+D70)*D62 -> 103.03151 | E71: =(E64+E68+E69+E70)*E62 -> 243.80879 | F71: =(F64+F68+F69+F70)*F62 -> 254.25583 | G71: =(G64+G68+G69+G70)*G62 -> 263.70359 | H71: =(H64+H68+H69+H70)*H62 -> 274.25173 | I71: =(I64+I68+I69+I70)*I62 -> 285.2218 | J71: =(J64+J68+J69+J70)*J62 -> 297.44336 | K71: =(K64+K68+K69+K70)*K62 -> 308.4959 | ... AV71: =(AV64+AV68+AV69+AV70)*AV62 -> 0
B72: Discount period (mid-period, years) | D72: =((MAX(Inputs!$C$5+1,DATE(D$61,1,1))+DATE(D$61,12,31))/2-Inputs!$C$5)/365 -> 0.25342466 | E72: =((MAX(Inputs!$C$5+1,DATE(E$61,1,1))+DATE(E$61,12,31))/2-Inputs!$C$5)/365 -> 1.0054795 | F72: =((MAX(Inputs!$C$5+1,DATE(F$61,1,1))+DATE(F$61,12,31))/2-Inputs!$C$5)/365 -> 2.0068493 | G72: =((MAX(Inputs!$C$5+1,DATE(G$61,1,1))+DATE(G$61,12,31))/2-Inputs!$C$5)/365 -> 3.0082192 | H72: =((MAX(Inputs!$C$5+1,DATE(H$61,1,1))+DATE(H$61,12,31))/2-Inputs!$C$5)/365 -> 4.0082192 | I72: =((MAX(Inputs!$C$5+1,DATE(I$61,1,1))+DATE(I$61,12,31))/2-Inputs!$C$5)/365 -> 5.0082192 | J72: =((MAX(Inputs!$C$5+1,DATE(J$61,1,1))+DATE(J$61,12,31))/2-Inputs!$C$5)/365 -> 6.009589 | K72: =((MAX(Inputs!$C$5+1,DATE(K$61,1,1))+DATE(K$61,12,31))/2-Inputs!$C$5)/365 -> 7.0109589 | ... AV72: =((MAX(Inputs!$C$5+1,DATE(AV$61,1,1))+DATE(AV$61,12,31))/2-Inputs!$C$5)/365 -> 44.035616
B73: Discount factor | D73: =1/(1+$C$54)^D72 -> 0.97726308 | E73: =1/(1+$C$54)^E72 -> 0.91278798 | F73: =1/(1+$C$54)^F72 -> 0.8334927 | G73: =1/(1+$C$54)^G72 -> 0.76108593 | H73: =1/(1+$C$54)^H72 -> 0.69505564 | I73: =1/(1+$C$54)^I72 -> 0.63475401 | J73: =1/(1+$C$54)^J72 -> 0.57961196 | K73: =1/(1+$C$54)^K72 -> 0.52926019 | ... AV73: =1/(1+$C$54)^AV72 -> 0.018381247
B74: PV of UFCF | D74: =D71*D73 -> 100.68889 | E74: =E71*E73 -> 222.54573 | F74: =F71*F73 -> 211.92038 | G74: =G71*G73 -> 200.70109 | H74: =H71*H73 -> 190.62021 | I74: =I71*I73 -> 181.04568 | J74: =J71*J73 -> 172.40173 | K74: =K71*K73 -> 163.2746 | ... AV74: =AV71*AV73 -> 0
B75: Terminal-year normalised FCF (before growth) | D75: =IF(AND($C$55=0,D$61=$C$57),D64-D63*($C$59+$C$53)-MAX(0,D64-D63*$C$59)*Inputs!$C$11,0) -> 0 | E75: =IF(AND($C$55=0,E$61=$C$57),E64-E63*($C$59+$C$53)-MAX(0,E64-E63*$C$59)*Inputs!$C$11,0) -> 0 | F75: =IF(AND($C$55=0,F$61=$C$57),F64-F63*($C$59+$C$53)-MAX(0,F64-F63*$C$59)*Inputs!$C$11,0) -> 0 | G75: =IF(AND($C$55=0,G$61=$C$57),G64-G63*($C$59+$C$53)-MAX(0,G64-G63*$C$59)*Inputs!$C$11,0) -> 0 | H75: =IF(AND($C$55=0,H$61=$C$57),H64-H63*($C$59+$C$53)-MAX(0,H64-H63*$C$59)*Inputs!$C$11,0) -> 0 | I75: =IF(AND($C$55=0,I$61=$C$57),I64-I63*($C$59+$C$53)-MAX(0,I64-I63*$C$59)*Inputs!$C$11,0) -> 0 | J75: =IF(AND($C$55=0,J$61=$C$57),J64-J63*($C$59+$C$53)-MAX(0,J64-J63*$C$59)*Inputs!$C$11,0) -> 0 | K75: =IF(AND($C$55=0,K$61=$C$57),K64-K63*($C$59+$C$53)-MAX(0,K64-K63*$C$59)*Inputs!$C$11,0) -> 0 | ... AV75: =IF(AND($C$55=0,AV$61=$C$57),AV64-AV63*($C$59+$C$53)-MAX(0,AV64-AV63*$C$59)*Inputs!$C$11,0) -> 0
B76: PV of terminal value | D76: =D75*(1+$C$58)/($C$54-$C$58)*D73 -> 0 | E76: =E75*(1+$C$58)/($C$54-$C$58)*E73 -> 0 | F76: =F75*(1+$C$58)/($C$54-$C$58)*F73 -> 0 | G76: =G75*(1+$C$58)/($C$54-$C$58)*G73 -> 0 | H76: =H75*(1+$C$58)/($C$54-$C$58)*H73 -> 0 | I76: =I75*(1+$C$58)/($C$54-$C$58)*I73 -> 0 | J76: =J75*(1+$C$58)/($C$54-$C$58)*J73 -> 0 | K76: =K75*(1+$C$58)/($C$54-$C$58)*K73 -> 0 | ... AV76: =AV75*(1+$C$58)/($C$54-$C$58)*AV73 -> 0
B78: PV of explicit / concession-life cash flows | C78: =SUM($D$74:$AV$74) -> 3105.9041
B79: PV of terminal value | C79: =SUM($D$76:$AV$76) -> 0
B80: ENTERPRISE VALUE — OMA Mexico (to 2048, 29.99%) (100%) | C80: =C78+C79 -> 3105.9041
B81: Terminal value as % of block EV | C81: =IF(C80=0,0,C79/C80) -> 0
B82: Implied EV / FY2026E EBITDA | C82: =IF(D64=0,0,C80/D64) -> 7.583845
B83: Terminal FCF base (for sensitivity) | C83: =SUM($D$75:$AV$75) -> 0
B84: Terminal discount period (for sensitivity) | C84: =SUMPRODUCT(($D$61:$AV$61=$C$57)*$D$72:$AV$72) -> 0
B85: Check: WACC > g and no cash flow after concession end | C85: =IF(AND($C$54>$C$58,SUMPRODUCT(($D$61:$AV$61>YEAR($C$56))*($C$55=1)*ABS($D$71:$AV$71))=0),"OK","REVISAR") -> OK
B88: Other fully consolidated airports (ANA, Aerodom, Lyon, Belgrade, Brazil…)
B89: Base revenue FY2025 (EUR m) | C89: 2423 | D89: Revenue = VINCI Airports 4,796 − Gatwick 1,321 − Edinburgh 419 − OMA 633. Contract ends: ANA 2062 (largest), Aerodom 2060, Cabo Verde 2063, Amazonia 2051, Salvador 2047, Lyon 2047, Belgrade 2045, Cambodia 2040, Belfast 2993. ASSUMPTION: single revenue-weighted end date of 2058 (ANA-dominated) — refine per airport if data become available. WACC 8.0% (Portugal/LatAm/Serbia mix). Minorities in Lyon (69.4%) and Cambodia (30%) deducted at book in bridge.
B90: Revenue growth FY2026 | C90: 0.02
B91: Revenue growth FY2027+ | C91: 0.03
B92: EBITDA margin (CFO before tax & financing / revenue) | C92: 0.6343
B93: D&A % revenue | C93: 0.1172
B94: Capex % revenue (operating + growth investments) | C94: 0.133
B95: Lease repayments % revenue | C95: 0.0048
B96: Discount rate (post-tax WACC) | C96: 0.08
B97: Type: 1 = finite concession (TV = 0) · 0 = going concern | C97: 1
B98: Concession end date (finite only) | C98: 58075
B99: Last explicit year (going concern only) | C99: 0
B100: Terminal growth g (going concern only) | C100: 0
B101: Terminal capex % revenue (going concern only) | C101: 0
B103: Fiscal year | D103: 2026 | E103: 2027 | F103: 2028 | G103: 2029 | H103: 2030 | I103: 2031 | J103: 2032 | K103: 2033 | L103: 2034 | M103: 2035 | N103: 2036 | O103: 2037 | P103: 2038 | Q103: 2039 | R103: 2040 | S103: 2041 | T103: 2042 | U103: 2043 | V103: 2044 | W103: 2045 | X103: 2046 | Y103: 2047 | Z103: 2048 | AA103: 2049 | AB103: 2050 | AC103: 2051 | AD103: 2052 | AE103: 2053 | AF103: 2054 | AG103: 2055 | AH103: 2056 | AI103: 2057 | AJ103: 2058 | AK103: 2059 | AL103: 2060 | AM103: 2061 | AN103: 2062 | AO103: 2063 | AP103: 2064 | AQ103: 2065 | AR103: 2066 | AS103: 2067 | AT103: 2068 | AU103: 2069 | AV103: 2070
B104: Fraction of year in valuation (after val. date / before concession end) | D104: =IF($C$97=1,MAX(0,MIN(DATE(D$103,12,31),$C$98)-MAX(Inputs!$C$5+1,DATE(D$103,1,1))+1)/365,IF(D$103<=$C$99,(DATE(D$103,12,31)-MAX(Inputs!$C$5+1,DATE(D$103,1,1))+1)/365,0)) -> 0.50410959 | E104: =IF($C$97=1,MAX(0,MIN(DATE(E$103,12,31),$C$98)-MAX(Inputs!$C$5+1,DATE(E$103,1,1))+1)/365,IF(E$103<=$C$99,(DATE(E$103,12,31)-MAX(Inputs!$C$5+1,DATE(E$103,1,1))+1)/365,0)) -> 1 | F104: =IF($C$97=1,MAX(0,MIN(DATE(F$103,12,31),$C$98)-MAX(Inputs!$C$5+1,DATE(F$103,1,1))+1)/365,IF(F$103<=$C$99,(DATE(F$103,12,31)-MAX(Inputs!$C$5+1,DATE(F$103,1,1))+1)/365,0)) -> 1.0027397 | G104: =IF($C$97=1,MAX(0,MIN(DATE(G$103,12,31),$C$98)-MAX(Inputs!$C$5+1,DATE(G$103,1,1))+1)/365,IF(G$103<=$C$99,(DATE(G$103,12,31)-MAX(Inputs!$C$5+1,DATE(G$103,1,1))+1)/365,0)) -> 1 | H104: =IF($C$97=1,MAX(0,MIN(DATE(H$103,12,31),$C$98)-MAX(Inputs!$C$5+1,DATE(H$103,1,1))+1)/365,IF(H$103<=$C$99,(DATE(H$103,12,31)-MAX(Inputs!$C$5+1,DATE(H$103,1,1))+1)/365,0)) -> 1 | I104: =IF($C$97=1,MAX(0,MIN(DATE(I$103,12,31),$C$98)-MAX(Inputs!$C$5+1,DATE(I$103,1,1))+1)/365,IF(I$103<=$C$99,(DATE(I$103,12,31)-MAX(Inputs!$C$5+1,DATE(I$103,1,1))+1)/365,0)) -> 1 | J104: =IF($C$97=1,MAX(0,MIN(DATE(J$103,12,31),$C$98)-MAX(Inputs!$C$5+1,DATE(J$103,1,1))+1)/365,IF(J$103<=$C$99,(DATE(J$103,12,31)-MAX(Inputs!$C$5+1,DATE(J$103,1,1))+1)/365,0)) -> 1.0027397 | K104: =IF($C$97=1,MAX(0,MIN(DATE(K$103,12,31),$C$98)-MAX(Inputs!$C$5+1,DATE(K$103,1,1))+1)/365,IF(K$103<=$C$99,(DATE(K$103,12,31)-MAX(Inputs!$C$5+1,DATE(K$103,1,1))+1)/365,0)) -> 1 | ... AV104: =IF($C$97=1,MAX(0,MIN(DATE(AV$103,12,31),$C$98)-MAX(Inputs!$C$5+1,DATE(AV$103,1,1))+1)/365,IF(AV$103<=$C$99,(DATE(AV$103,12,31)-MAX(Inputs!$C$5+1,DATE(AV$103,1,1))+1)/365,0)) -> 0
B105: Revenue (full-year run-rate) | D105: =$C$89*(1+$C$90) -> 2471.46 | E105: =D105*(1+$C$91) -> 2545.6038 | F105: =E105*(1+$C$91) -> 2621.9719 | G105: =F105*(1+$C$91) -> 2700.6311 | H105: =G105*(1+$C$91) -> 2781.65 | I105: =H105*(1+$C$91) -> 2865.0995 | J105: =I105*(1+$C$91) -> 2951.0525 | K105: =J105*(1+$C$91) -> 3039.5841 | L105: =K105*(1+$C$91) -> 3130.7716 | ... AV105: =AU105*(1+$C$91) -> 9073.8474
B106: EBITDA | D106: =D105*$C$92 -> 1567.6471 | E106: =E105*$C$92 -> 1614.6765 | F106: =F105*$C$92 -> 1663.1168 | G106: =G105*$C$92 -> 1713.0103 | H106: =H105*$C$92 -> 1764.4006 | I106: =I105*$C$92 -> 1817.3326 | J106: =J105*$C$92 -> 1871.8526 | K106: =K105*$C$92 -> 1928.0082 | ... AV106: =AV105*$C$92 -> 5755.5414
B107: D&A | D107: =-D105*$C$93 -> -289.65511 | E107: =-E105*$C$93 -> -298.34477 | F107: =-F105*$C$93 -> -307.29511 | G107: =-G105*$C$93 -> -316.51396 | H107: =-H105*$C$93 -> -326.00938 | I107: =-I105*$C$93 -> -335.78966 | J107: =-J105*$C$93 -> -345.86335 | K107: =-K105*$C$93 -> -356.23925 | ... AV107: =-AV105*$C$93 -> -1063.4549
B108: EBIT | D108: =D106+D107 -> 1277.992 | E108: =E106+E107 -> 1316.3317 | F108: =F106+F107 -> 1355.8217 | G108: =G106+G107 -> 1396.4963 | H108: =H106+H107 -> 1438.3912 | I108: =I106+I107 -> 1481.543 | J108: =J106+J107 -> 1525.9892 | K108: =K106+K107 -> 1571.7689 | ... AV108: =AV106+AV107 -> 4692.0865
B109: Tax rate | D109: =IF(D$103=2026,Inputs!$C$10,Inputs!$C$11) -> 0.348 | E109: =IF(E$103=2026,Inputs!$C$10,Inputs!$C$11) -> 0.258 | F109: =IF(F$103=2026,Inputs!$C$10,Inputs!$C$11) -> 0.258 | G109: =IF(G$103=2026,Inputs!$C$10,Inputs!$C$11) -> 0.258 | H109: =IF(H$103=2026,Inputs!$C$10,Inputs!$C$11) -> 0.258 | I109: =IF(I$103=2026,Inputs!$C$10,Inputs!$C$11) -> 0.258 | J109: =IF(J$103=2026,Inputs!$C$10,Inputs!$C$11) -> 0.258 | K109: =IF(K$103=2026,Inputs!$C$10,Inputs!$C$11) -> 0.258 | ... AV109: =IF(AV$103=2026,Inputs!$C$10,Inputs!$C$11) -> 0.258
B110: Tax on EBIT | D110: =-MAX(0,D108)*D109 -> -444.7412 | E110: =-MAX(0,E108)*E109 -> -339.61359 | F110: =-MAX(0,F108)*F109 -> -349.80199 | G110: =-MAX(0,G108)*G109 -> -360.29605 | H110: =-MAX(0,H108)*H109 -> -371.10493 | I110: =-MAX(0,I108)*I109 -> -382.23808 | J110: =-MAX(0,J108)*J109 -> -393.70522 | K110: =-MAX(0,K108)*K109 -> -405.51638 | ... AV110: =-MAX(0,AV108)*AV109 -> -1210.5583
B111: Capex | D111: =-D105*$C$94 -> -328.70418 | E111: =-E105*$C$94 -> -338.56531 | F111: =-F105*$C$94 -> -348.72226 | G111: =-G105*$C$94 -> -359.18393 | H111: =-H105*$C$94 -> -369.95945 | I111: =-I105*$C$94 -> -381.05823 | J111: =-J105*$C$94 -> -392.48998 | K111: =-K105*$C$94 -> -404.26468 | ... AV111: =-AV105*$C$94 -> -1206.8217
...

Sheet Other_Concessions
B2: Other Concessions — VINCI Highways, Railways, Stadium
B4: Other concessions (VINCI Highways etc.)
B5: Base revenue FY2025 (EUR m) | C5: 690 | D5: FY2025 segment (Note C.1.2): revenue 690, EBITDA 344, D&A 102, operating capex 32, leases 3 (growth investments +10 ignored). Contracts: Entrevias 2047, Via Cristais 2055, Vía Sumapaz 2046, Lima Expresa 2049, Northwest Parkway 2106, Gefyra 2039, Confederation Bridge 2032. ASSUMPTION: single end date 2050. FY2026 growth 5.3% = Vinci impairment-test average for Highways; 4.0% thereafter. WACC 8.0% (LatAm/US mix).
B6: Revenue growth FY2026 | C6: 0.053
B7: Revenue growth FY2027+ | C7: 0.04
B8: EBITDA margin (CFO before tax & financing / revenue) | C8: 0.4986
B9: D&A % revenue | C9: 0.1478
B10: Capex % revenue (operating + growth investments) | C10: 0.0464
B11: Lease repayments % revenue | C11: 0.0043
B12: Discount rate (post-tax WACC) | C12: 0.08
B13: Type: 1 = finite concession (TV = 0) · 0 = going concern | C13: 1
B14: Concession end date (finite only) | C14: 55153
B15: Last explicit year (going concern only) | C15: 0
B16: Terminal growth g (going concern only) | C16: 0
B17: Terminal capex % revenue (going concern only) | C17: 0
B19: Fiscal year | D19: 2026 | E19: 2027 | F19: 2028 | G19: 2029 | H19: 2030 | I19: 2031 | J19: 2032 | K19: 2033 | L19: 2034 | M19: 2035 | N19: 2036 | O19: 2037 | P19: 2038 | Q19: 2039 | R19: 2040 | S19: 2041 | T19: 2042 | U19: 2043 | V19: 2044 | W19: 2045 | X19: 2046 | Y19: 2047 | Z19: 2048 | AA19: 2049 | AB19: 2050 | AC19: 2051 | AD19: 2052 | AE19: 2053 | AF19: 2054 | AG19: 2055 | AH19: 2056 | AI19: 2057 | AJ19: 2058 | AK19: 2059 | AL19: 2060 | AM19: 2061 | AN19: 2062 | AO19: 2063 | AP19: 2064 | AQ19: 2065 | AR19: 2066 | AS19: 2067 | AT19: 2068 | AU19: 2069 | AV19: 2070
B20: Fraction of year in valuation (after val. date / before concession end) | D20: =IF($C$13=1,MAX(0,MIN(DATE(D$19,12,31),$C$14)-MAX(Inputs!$C$5+1,DATE(D$19,1,1))+1)/365,IF(D$19<=$C$15,(DATE(D$19,12,31)-MAX(Inputs!$C$5+1,DATE(D$19,1,1))+1)/365,0)) -> 0.50410959 | E20: =IF($C$13=1,MAX(0,MIN(DATE(E$19,12,31),$C$14)-MAX(Inputs!$C$5+1,DATE(E$19,1,1))+1)/365,IF(E$19<=$C$15,(DATE(E$19,12,31)-MAX(Inputs!$C$5+1,DATE(E$19,1,1))+1)/365,0)) -> 1 | F20: =IF($C$13=1,MAX(0,MIN(DATE(F$19,12,31),$C$14)-MAX(Inputs!$C$5+1,DATE(F$19,1,1))+1)/365,IF(F$19<=$C$15,(DATE(F$19,12,31)-MAX(Inputs!$C$5+1,DATE(F$19,1,1))+1)/365,0)) -> 1.0027397 | G20: =IF($C$13=1,MAX(0,MIN(DATE(G$19,12,31),$C$14)-MAX(Inputs!$C$5+1,DATE(G$19,1,1))+1)/365,IF(G$19<=$C$15,(DATE(G$19,12,31)-MAX(Inputs!$C$5+1,DATE(G$19,1,1))+1)/365,0)) -> 1 | H20: =IF($C$13=1,MAX(0,MIN(DATE(H$19,12,31),$C$14)-MAX(Inputs!$C$5+1,DATE(H$19,1,1))+1)/365,IF(H$19<=$C$15,(DATE(H$19,12,31)-MAX(Inputs!$C$5+1,DATE(H$19,1,1))+1)/365,0)) -> 1 | I20: =IF($C$13=1,MAX(0,MIN(DATE(I$19,12,31),$C$14)-MAX(Inputs!$C$5+1,DATE(I$19,1,1))+1)/365,IF(I$19<=$C$15,(DATE(I$19,12,31)-MAX(Inputs!$C$5+1,DATE(I$19,1,1))+1)/365,0)) -> 1 | J20: =IF($C$13=1,MAX(0,MIN(DATE(J$19,12,31),$C$14)-MAX(Inputs!$C$5+1,DATE(J$19,1,1))+1)/365,IF(J$19<=$C$15,(DATE(J$19,12,31)-MAX(Inputs!$C$5+1,DATE(J$19,1,1))+1)/365,0)) -> 1.0027397 | K20: =IF($C$13=1,MAX(0,MIN(DATE(K$19,12,31),$C$14)-MAX(Inputs!$C$5+1,DATE(K$19,1,1))+1)/365,IF(K$19<=$C$15,(DATE(K$19,12,31)-MAX(Inputs!$C$5+1,DATE(K$19,1,1))+1)/365,0)) -> 1 | ... AV20: =IF($C$13=1,MAX(0,MIN(DATE(AV$19,12,31),$C$14)-MAX(Inputs!$C$5+1,DATE(AV$19,1,1))+1)/365,IF(AV$19<=$C$15,(DATE(AV$19,12,31)-MAX(Inputs!$C$5+1,DATE(AV$19,1,1))+1)/365,0)) -> 0
B21: Revenue (full-year run-rate) | D21: =$C$5*(1+$C$6) -> 726.57 | E21: =D21*(1+$C$7) -> 755.6328 | F21: =E21*(1+$C$7) -> 785.85811 | G21: =F21*(1+$C$7) -> 817.29244 | H21: =G21*(1+$C$7) -> 849.98413 | I21: =H21*(1+$C$7) -> 883.9835 | J21: =I21*(1+$C$7) -> 919.34284 | K21: =J21*(1+$C$7) -> 956.11655 | L21: =K21*(1+$C$7) -> 994.36121 | ... AV21: =AU21*(1+$C$7) -> 4080.7914
B22: EBITDA | D22: =D21*$C$8 -> 362.2678 | E22: =E21*$C$8 -> 376.75851 | F22: =F21*$C$8 -> 391.82885 | G22: =G21*$C$8 -> 407.50201 | H22: =H21*$C$8 -> 423.80209 | I22: =I21*$C$8 -> 440.75417 | J22: =J21*$C$8 -> 458.38434 | K22: =K21*$C$8 -> 476.71971 | ... AV22: =AV21*$C$8 -> 2034.6826
B23: D&A | D23: =-D21*$C$9 -> -107.38705 | E23: =-E21*$C$9 -> -111.68253 | F23: =-F21*$C$9 -> -116.14983 | G23: =-G21*$C$9 -> -120.79582 | H23: =-H21*$C$9 -> -125.62765 | I23: =-I21*$C$9 -> -130.65276 | J23: =-J21*$C$9 -> -135.87887 | K23: =-K21*$C$9 -> -141.31403 | ... AV23: =-AV21*$C$9 -> -603.14096
B24: EBIT | D24: =D22+D23 -> 254.88076 | E24: =E22+E23 -> 265.07599 | F24: =F22+F23 -> 275.67903 | G24: =G22+G23 -> 286.70619 | H24: =H22+H23 -> 298.17443 | I24: =I22+I23 -> 310.10141 | J24: =J22+J23 -> 322.50547 | K24: =K22+K23 -> 335.40569 | ... AV24: =AV22+AV23 -> 1431.5416
B25: Tax rate | D25: =IF(D$19=2026,Inputs!$C$10,Inputs!$C$11) -> 0.348 | E25: =IF(E$19=2026,Inputs!$C$10,Inputs!$C$11) -> 0.258 | F25: =IF(F$19=2026,Inputs!$C$10,Inputs!$C$11) -> 0.258 | G25: =IF(G$19=2026,Inputs!$C$10,Inputs!$C$11) -> 0.258 | H25: =IF(H$19=2026,Inputs!$C$10,Inputs!$C$11) -> 0.258 | I25: =IF(I$19=2026,Inputs!$C$10,Inputs!$C$11) -> 0.258 | J25: =IF(J$19=2026,Inputs!$C$10,Inputs!$C$11) -> 0.258 | K25: =IF(K$19=2026,Inputs!$C$10,Inputs!$C$11) -> 0.258 | ... AV25: =IF(AV$19=2026,Inputs!$C$10,Inputs!$C$11) -> 0.258
B26: Tax on EBIT | D26: =-MAX(0,D24)*D25 -> -88.698503 | E26: =-MAX(0,E24)*E25 -> -68.389604 | F26: =-MAX(0,F24)*F25 -> -71.125189 | G26: =-MAX(0,G24)*G25 -> -73.970196 | H26: =-MAX(0,H24)*H25 -> -76.929004 | I26: =-MAX(0,I24)*I25 -> -80.006164 | J26: =-MAX(0,J24)*J25 -> -83.206411 | K26: =-MAX(0,K24)*K25 -> -86.534667 | ... AV26: =-MAX(0,AV24)*AV25 -> -369.33774
B27: Capex | D27: =-D21*$C$10 -> -33.712848 | E27: =-E21*$C$10 -> -35.061362 | F27: =-F21*$C$10 -> -36.463816 | G27: =-G21*$C$10 -> -37.922369 | H27: =-H21*$C$10 -> -39.439264 | I27: =-I21*$C$10 -> -41.016834 | J27: =-J21*$C$10 -> -42.657508 | K27: =-K21*$C$10 -> -44.363808 | ... AV27: =-AV21*$C$10 -> -189.34872
B28: Lease repayments | D28: =-D21*$C$11 -> -3.124251 | E28: =-E21*$C$11 -> -3.249221 | F28: =-F21*$C$11 -> -3.3791899 | G28: =-G21*$C$11 -> -3.5143575 | H28: =-H21*$C$11 -> -3.6549318 | I28: =-I21*$C$11 -> -3.801129 | J28: =-J21*$C$11 -> -3.9531742 | K28: =-K21*$C$11 -> -4.1113012 | ... AV28: =-AV21*$C$11 -> -17.547403
B29: Unlevered FCF in valuation window | D29: =(D22+D26+D27+D28)*D20 -> 119.33897 | E29: =(E22+E26+E27+E28)*E20 -> 270.05833 | F29: =(F22+F26+F27+F28)*F20 -> 281.63014 | G29: =(G22+G26+G27+G28)*G20 -> 292.09509 | H29: =(H22+H26+H27+H28)*H20 -> 303.77889 | I29: =(I22+I26+I27+I28)*I20 -> 315.93005 | J29: =(J22+J26+J27+J28)*J20 -> 329.46743 | K29: =(K22+K26+K27+K28)*K20 -> 341.70994 | ... AV29: =(AV22+AV26+AV27+AV28)*AV20 -> 0
B30: Discount period (mid-period, years) | D30: =((MAX(Inputs!$C$5+1,DATE(D$19,1,1))+DATE(D$19,12,31))/2-Inputs!$C$5)/365 -> 0.25342466 | E30: =((MAX(Inputs!$C$5+1,DATE(E$19,1,1))+DATE(E$19,12,31))/2-Inputs!$C$5)/365 -> 1.0054795 | F30: =((MAX(Inputs!$C$5+1,DATE(F$19,1,1))+DATE(F$19,12,31))/2-Inputs!$C$5)/365 -> 2.0068493 | G30: =((MAX(Inputs!$C$5+1,DATE(G$19,1,1))+DATE(G$19,12,31))/2-Inputs!$C$5)/365 -> 3.0082192 | H30: =((MAX(Inputs!$C$5+1,DATE(H$19,1,1))+DATE(H$19,12,31))/2-Inputs!$C$5)/365 -> 4.0082192 | I30: =((MAX(Inputs!$C$5+1,DATE(I$19,1,1))+DATE(I$19,12,31))/2-Inputs!$C$5)/365 -> 5.0082192 | J30: =((MAX(Inputs!$C$5+1,DATE(J$19,1,1))+DATE(J$19,12,31))/2-Inputs!$C$5)/365 -> 6.009589 | K30: =((MAX(Inputs!$C$5+1,DATE(K$19,1,1))+DATE(K$19,12,31))/2-Inputs!$C$5)/365 -> 7.0109589 | ... AV30: =((MAX(Inputs!$C$5+1,DATE(AV$19,1,1))+DATE(AV$19,12,31))/2-Inputs!$C$5)/365 -> 44.035616
B31: Discount factor | D31: =1/(1+$C$12)^D30 -> 0.98068514 | E31: =1/(1+$C$12)^E30 -> 0.92553554 | F31: =1/(1+$C$12)^F30 -> 0.85688701 | G31: =1/(1+$C$12)^G30 -> 0.79333026 | H31: =1/(1+$C$12)^H30 -> 0.73456505 | I31: =1/(1+$C$12)^I30 -> 0.68015283 | J31: =1/(1+$C$12)^J30 -> 0.62970474 | K31: =1/(1+$C$12)^K30 -> 0.58299848 | ... AV31: =1/(1+$C$12)^AV30 -> 0.033741495
B32: PV of UFCF | D32: =D29*D31 -> 117.03396 | E32: =E29*E31 -> 249.94858 | F32: =F29*F31 -> 241.32521 | G32: =G29*G31 -> 231.72787 | H32: =H29*H31 -> 223.14536 | I32: =I29*I31 -> 214.88071 | J32: =J29*J31 -> 207.4672 | K32: =K29*K31 -> 199.21637 | ... AV32: =AV29*AV31 -> 0
B33: Terminal-year normalised FCF (before growth) | D33: =IF(AND($C$13=0,D$19=$C$15),D22-D21*($C$17+$C$11)-MAX(0,D22-D21*$C$17)*Inputs!$C$11,0) -> 0 | E33: =IF(AND($C$13=0,E$19=$C$15),E22-E21*($C$17+$C$11)-MAX(0,E22-E21*$C$17)*Inputs!$C$11,0) -> 0 | F33: =IF(AND($C$13=0,F$19=$C$15),F22-F21*($C$17+$C$11)-MAX(0,F22-F21*$C$17)*Inputs!$C$11,0) -> 0 | G33: =IF(AND($C$13=0,G$19=$C$15),G22-G21*($C$17+$C$11)-MAX(0,G22-G21*$C$17)*Inputs!$C$11,0) -> 0 | H33: =IF(AND($C$13=0,H$19=$C$15),H22-H21*($C$17+$C$11)-MAX(0,H22-H21*$C$17)*Inputs!$C$11,0) -> 0 | I33: =IF(AND($C$13=0,I$19=$C$15),I22-I21*($C$17+$C$11)-MAX(0,I22-I21*$C$17)*Inputs!$C$11,0) -> 0 | J33: =IF(AND($C$13=0,J$19=$C$15),J22-J21*($C$17+$C$11)-MAX(0,J22-J21*$C$17)*Inputs!$C$11,0) -> 0 | K33: =IF(AND($C$13=0,K$19=$C$15),K22-K21*($C$17+$C$11)-MAX(0,K22-K21*$C$17)*Inputs!$C$11,0) -> 0 | ... AV33: =IF(AND($C$13=0,AV$19=$C$15),AV22-AV21*($C$17+$C$11)-MAX(0,AV22-AV21*$C$17)*Inputs!$C$11,0) -> 0
B34: PV of terminal value | D34: =D33*(1+$C$16)/($C$12-$C$16)*D31 -> 0 | E34: =E33*(1+$C$16)/($C$12-$C$16)*E31 -> 0 | F34: =F33*(1+$C$16)/($C$12-$C$16)*F31 -> 0 | G34: =G33*(1+$C$16)/($C$12-$C$16)*G31 -> 0 | H34: =H33*(1+$C$16)/($C$12-$C$16)*H31 -> 0 | I34: =I33*(1+$C$16)/($C$12-$C$16)*I31 -> 0 | J34: =J33*(1+$C$16)/($C$12-$C$16)*J31 -> 0 | K34: =K33*(1+$C$16)/($C$12-$C$16)*K31 -> 0 | ... AV34: =AV33*(1+$C$16)/($C$12-$C$16)*AV31 -> 0
B36: PV of explicit / concession-life cash flows | C36: =SUM($D$32:$AV$32) -> 4138.1812
B37: PV of terminal value | C37: =SUM($D$34:$AV$34) -> 0
B38: ENTERPRISE VALUE — Other concessions (VINCI Highways etc.) (100%) | C38: =C36+C37 -> 4138.1812
B39: Terminal value as % of block EV | C39: =IF(C38=0,0,C37/C38) -> 0
B40: Implied EV / FY2026E EBITDA | C40: =IF(D22=0,0,C38/D22) -> 11.422989
B41: Terminal FCF base (for sensitivity) | C41: =SUM($D$33:$AV$33) -> 0
B42: Terminal discount period (for sensitivity) | C42: =SUMPRODUCT(($D$19:$AV$19=$C$15)*$D$30:$AV$30) -> 0
B43: Check: WACC > g and no cash flow after concession end | C43: =IF(AND($C$12>$C$16,SUMPRODUCT(($D$19:$AV$19>YEAR($C$14))*($C$13=1)*ABS($D$29:$AV$29))=0),"OK","REVISAR") -> OK

Sheet Energy_Construction
B2: Energy Construction — going-concern businesses (5-year DCF + Gordon TV)
B4: VINCI Energies
B5: Base revenue FY2025 (EUR m) | C5: 21608 | D5: FY2025 segment: revenue 21,608, EBITDA 2,019, D&A 621, capex 281, leases 446. Guidance 2026: Energy Solutions mid-to-high single-digit growth with margin improvement (H1 2026: +6.8%). Margin held flat (conservative vs guidance). TV capex 1.4% ≈ D&A net of lease-related amortisation. No working-capital inflow capitalised (negative NWC is not a perpetual source of cash).
B6: Revenue growth FY2026 | C6: 0.065
B7: Revenue growth FY2027+ | C7: 0.05
B8: EBITDA margin (CFO before tax & financing / revenue) | C8: 0.0934
B9: D&A % revenue | C9: 0.0287
B10: Capex % revenue (operating + growth investments) | C10: 0.013
B11: Lease repayments % revenue | C11: 0.0206
B12: Discount rate (post-tax WACC) | C12: 0.075
B13: Type: 1 = finite concession (TV = 0) · 0 = going concern | C13: 0
B14: Concession end date (finite only) | C14: 46387
B15: Last explicit year (going concern only) | C15: 2030
B16: Terminal growth g (going concern only) | C16: 0.02
B17: Terminal capex % revenue (going concern only) | C17: 0.014
B19: Fiscal year | D19: 2026 | E19: 2027 | F19: 2028 | G19: 2029 | H19: 2030 | I19: 2031 | J19: 2032 | K19: 2033 | L19: 2034 | M19: 2035 | N19: 2036 | O19: 2037 | P19: 2038 | Q19: 2039 | R19: 2040 | S19: 2041 | T19: 2042 | U19: 2043 | V19: 2044 | W19: 2045 | X19: 2046 | Y19: 2047 | Z19: 2048 | AA19: 2049 | AB19: 2050 | AC19: 2051 | AD19: 2052 | AE19: 2053 | AF19: 2054 | AG19: 2055 | AH19: 2056 | AI19: 2057 | AJ19: 2058 | AK19: 2059 | AL19: 2060 | AM19: 2061 | AN19: 2062 | AO19: 2063 | AP19: 2064 | AQ19: 2065 | AR19: 2066 | AS19: 2067 | AT19: 2068 | AU19: 2069 | AV19: 2070
B20: Fraction of year in valuation (after val. date / before concession end) | D20: =IF($C$13=1,MAX(0,MIN(DATE(D$19,12,31),$C$14)-MAX(Inputs!$C$5+1,DATE(D$19,1,1))+1)/365,IF(D$19<=$C$15,(DATE(D$19,12,31)-MAX(Inputs!$C$5+1,DATE(D$19,1,1))+1)/365,0)) -> 0.50410959 | E20: =IF($C$13=1,MAX(0,MIN(DATE(E$19,12,31),$C$14)-MAX(Inputs!$C$5+1,DATE(E$19,1,1))+1)/365,IF(E$19<=$C$15,(DATE(E$19,12,31)-MAX(Inputs!$C$5+1,DATE(E$19,1,1))+1)/365,0)) -> 1 | F20: =IF($C$13=1,MAX(0,MIN(DATE(F$19,12,31),$C$14)-MAX(Inputs!$C$5+1,DATE(F$19,1,1))+1)/365,IF(F$19<=$C$15,(DATE(F$19,12,31)-MAX(Inputs!$C$5+1,DATE(F$19,1,1))+1)/365,0)) -> 1.0027397 | G20: =IF($C$13=1,MAX(0,MIN(DATE(G$19,12,31),$C$14)-MAX(Inputs!$C$5+1,DATE(G$19,1,1))+1)/365,IF(G$19<=$C$15,(DATE(G$19,12,31)-MAX(Inputs!$C$5+1,DATE(G$19,1,1))+1)/365,0)) -> 1 | H20: =IF($C$13=1,MAX(0,MIN(DATE(H$19,12,31),$C$14)-MAX(Inputs!$C$5+1,DATE(H$19,1,1))+1)/365,IF(H$19<=$C$15,(DATE(H$19,12,31)-MAX(Inputs!$C$5+1,DATE(H$19,1,1))+1)/365,0)) -> 1 | I20: =IF($C$13=1,MAX(0,MIN(DATE(I$19,12,31),$C$14)-MAX(Inputs!$C$5+1,DATE(I$19,1,1))+1)/365,IF(I$19<=$C$15,(DATE(I$19,12,31)-MAX(Inputs!$C$5+1,DATE(I$19,1,1))+1)/365,0)) -> 0 | J20: =IF($C$13=1,MAX(0,MIN(DATE(J$19,12,31),$C$14)-MAX(Inputs!$C$5+1,DATE(J$19,1,1))+1)/365,IF(J$19<=$C$15,(DATE(J$19,12,31)-MAX(Inputs!$C$5+1,DATE(J$19,1,1))+1)/365,0)) -> 0 | K20: =IF($C$13=1,MAX(0,MIN(DATE(K$19,12,31),$C$14)-MAX(Inputs!$C$5+1,DATE(K$19,1,1))+1)/365,IF(K$19<=$C$15,(DATE(K$19,12,31)-MAX(Inputs!$C$5+1,DATE(K$19,1,1))+1)/365,0)) -> 0 | ... AV20: =IF($C$13=1,MAX(0,MIN(DATE(AV$19,12,31),$C$14)-MAX(Inputs!$C$5+1,DATE(AV$19,1,1))+1)/365,IF(AV$19<=$C$15,(DATE(AV$19,12,31)-MAX(Inputs!$C$5+1,DATE(AV$19,1,1))+1)/365,0)) -> 0
B21: Revenue (full-year run-rate) | D21: =$C$5*(1+$C$6) -> 23012.52 | E21: =D21*(1+$C$7) -> 24163.146 | F21: =E21*(1+$C$7) -> 25371.303 | G21: =F21*(1+$C$7) -> 26639.868 | H21: =G21*(1+$C$7) -> 27971.862 | I21: =H21*(1+$C$7) -> 29370.455 | J21: =I21*(1+$C$7) -> 30838.978 | K21: =J21*(1+$C$7) -> 32380.927 | L21: =K21*(1+$C$7) -> 33999.973 | ... AV21: =AU21*(1+$C$7) -> 196921.59
B22: EBITDA | D22: =D21*$C$8 -> 2149.3694 | E22: =E21*$C$8 -> 2256.8378 | F22: =F21*$C$8 -> 2369.6797 | G22: =G21*$C$8 -> 2488.1637 | H22: =H21*$C$8 -> 2612.5719 | I22: =I21*$C$8 -> 2743.2005 | J22: =J21*$C$8 -> 2880.3605 | K22: =K21*$C$8 -> 3024.3785 | ... AV22: =AV21*$C$8 -> 18392.477
B23: D&A | D23: =-D21*$C$9 -> -660.45932 | E23: =-E21*$C$9 -> -693.48229 | F23: =-F21*$C$9 -> -728.1564 | G23: =-G21*$C$9 -> -764.56422 | H23: =-H21*$C$9 -> -802.79244 | I23: =-I21*$C$9 -> -842.93206 | J23: =-J21*$C$9 -> -885.07866 | K23: =-K21*$C$9 -> -929.33259 | ... AV23: =-AV21*$C$9 -> -5651.6497
B24: EBIT | D24: =D22+D23 -> 1488.91 | E24: =E22+E23 -> 1563.3555 | F24: =F22+F23 -> 1641.5233 | G24: =G22+G23 -> 1723.5995 | H24: =H22+H23 -> 1809.7795 | I24: =I22+I23 -> 1900.2684 | J24: =J22+J23 -> 1995.2819 | K24: =K22+K23 -> 2095.046 | ... AV24: =AV22+AV23 -> 12740.827
B25: Tax rate | D25: =IF(D$19=2026,Inputs!$C$10,Inputs!$C$11) -> 0.348 | E25: =IF(E$19=2026,Inputs!$C$10,Inputs!$C$11) -> 0.258 | F25: =IF(F$19=2026,Inputs!$C$10,Inputs!$C$11) -> 0.258 | G25: =IF(G$19=2026,Inputs!$C$10,Inputs!$C$11) -> 0.258 | H25: =IF(H$19=2026,Inputs!$C$10,Inputs!$C$11) -> 0.258 | I25: =IF(I$19=2026,Inputs!$C$10,Inputs!$C$11) -> 0.258 | J25: =IF(J$19=2026,Inputs!$C$10,Inputs!$C$11) -> 0.258 | K25: =IF(K$19=2026,Inputs!$C$10,Inputs!$C$11) -> 0.258 | ... AV25: =IF(AV$19=2026,Inputs!$C$10,Inputs!$C$11) -> 0.258
B26: Tax on EBIT | D26: =-MAX(0,D24)*D25 -> -518.1407 | E26: =-MAX(0,E24)*E25 -> -403.34573 | F26: =-MAX(0,F24)*F25 -> -423.51302 | G26: =-MAX(0,G24)*G25 -> -444.68867 | H26: =-MAX(0,H24)*H25 -> -466.9231 | I26: =-MAX(0,I24)*I25 -> -490.26926 | J26: =-MAX(0,J24)*J25 -> -514.78272 | K26: =-MAX(0,K24)*K25 -> -540.52186 | ... AV26: =-MAX(0,AV24)*AV25 -> -3287.1334
B27: Capex | D27: =-D21*$C$10 -> -299.16276 | E27: =-E21*$C$10 -> -314.1209 | F27: =-F21*$C$10 -> -329.82694 | G27: =-G21*$C$10 -> -346.31829 | H27: =-H21*$C$10 -> -363.6342 | I27: =-I21*$C$10 -> -381.81591 | J27: =-J21*$C$10 -> -400.90671 | K27: =-K21*$C$10 -> -420.95205 | ... AV27: =-AV21*$C$10 -> -2559.9807
B28: Lease repayments | D28: =-D21*$C$11 -> -474.05791 | E28: =-E21*$C$11 -> -497.76081 | F28: =-F21*$C$11 -> -522.64885 | G28: =-G21*$C$11 -> -548.78129 | H28: =-H21*$C$11 -> -576.22035 | I28: =-I21*$C$11 -> -605.03137 | J28: =-J21*$C$11 -> -635.28294 | K28: =-K21*$C$11 -> -667.04709 | ... AV28: =-AV21*$C$11 -> -4056.5848
B29: Unlevered FCF in valuation window | D29: =(D22+D26+D27+D28)*D20 -> 432.53006 | E29: =(E22+E26+E27+E28)*E20 -> 1041.6104 | F29: =(F22+F26+F27+F28)*F20 -> 1096.6873 | G29: =(G22+G26+G27+G28)*G20 -> 1148.3755 | H29: =(H22+H26+H27+H28)*H20 -> 1205.7942 | I29: =(I22+I26+I27+I28)*I20 -> 0 | J29: =(J22+J26+J27+J28)*J20 -> 0 | K29: =(K22+K26+K27+K28)*K20 -> 0 | ... AV29: =(AV22+AV26+AV27+AV28)*AV20 -> 0
B30: Discount period (mid-period, years) | D30: =((MAX(Inputs!$C$5+1,DATE(D$19,1,1))+DATE(D$19,12,31))/2-Inputs!$C$5)/365 -> 0.25342466 | E30: =((MAX(Inputs!$C$5+1,DATE(E$19,1,1))+DATE(E$19,12,31))/2-Inputs!$C$5)/365 -> 1.0054795 | F30: =((MAX(Inputs!$C$5+1,DATE(F$19,1,1))+DATE(F$19,12,31))/2-Inputs!$C$5)/365 -> 2.0068493 | G30: =((MAX(Inputs!$C$5+1,DATE(G$19,1,1))+DATE(G$19,12,31))/2-Inputs!$C$5)/365 -> 3.0082192 | H30: =((MAX(Inputs!$C$5+1,DATE(H$19,1,1))+DATE(H$19,12,31))/2-Inputs!$C$5)/365 -> 4.0082192 | I30: =((MAX(Inputs!$C$5+1,DATE(I$19,1,1))+DATE(I$19,12,31))/2-Inputs!$C$5)/365 -> 5.0082192 | J30: =((MAX(Inputs!$C$5+1,DATE(J$19,1,1))+DATE(J$19,12,31))/2-Inputs!$C$5)/365 -> 6.009589 | K30: =((MAX(Inputs!$C$5+1,DATE(K$19,1,1))+DATE(K$19,12,31))/2-Inputs!$C$5)/365 -> 7.0109589 | ... AV30: =((MAX(Inputs!$C$5+1,DATE(AV$19,1,1))+DATE(AV$19,12,31))/2-Inputs!$C$5)/365 -> 44.035616
B31: Discount factor | D31: =1/(1+$C$12)^D30 -> 0.98183909 | E31: =1/(1+$C$12)^E30 -> 0.929864 | F31: =1/(1+$C$12)^F30 -> 0.86490408 | G31: =1/(1+$C$12)^G30 -> 0.80448223 | H31: =1/(1+$C$12)^H30 -> 0.74835556 | I31: =1/(1+$C$12)^I30 -> 0.69614471 | J31: =1/(1+$C$12)^J30 -> 0.64751232 | K31: =1/(1+$C$12)^K30 -> 0.60227737 | ... AV31: =1/(1+$C$12)^AV30 -> 0.041391286
B32: PV of UFCF | D32: =D29*D31 -> 424.67492 | E32: =E29*E31 -> 968.55601 | F32: =F29*F31 -> 948.52935 | G32: =G29*G31 -> 923.84766 | H32: =H29*H31 -> 902.36283 | I32: =I29*I31 -> 0 | J32: =J29*J31 -> 0 | K32: =K29*K31 -> 0 | ... AV32: =AV29*AV31 -> 0
B33: Terminal-year normalised FCF (before growth) | D33: =IF(AND($C$13=0,D$19=$C$15),D22-D21*($C$17+$C$11)-MAX(0,D22-D21*$C$17)*Inputs!$C$11,0) -> 0 | E33: =IF(AND($C$13=0,E$19=$C$15),E22-E21*($C$17+$C$11)-MAX(0,E22-E21*$C$17)*Inputs!$C$11,0) -> 0 | F33: =IF(AND($C$13=0,F$19=$C$15),F22-F21*($C$17+$C$11)-MAX(0,F22-F21*$C$17)*Inputs!$C$11,0) -> 0 | G33: =IF(AND($C$13=0,G$19=$C$15),G22-G21*($C$17+$C$11)-MAX(0,G22-G21*$C$17)*Inputs!$C$11,0) -> 0 | H33: =IF(AND($C$13=0,H$19=$C$15),H22-H21*($C$17+$C$11)-MAX(0,H22-H21*$C$17)*Inputs!$C$11,0) -> 1071.7363 | I33: =IF(AND($C$13=0,I$19=$C$15),I22-I21*($C$17+$C$11)-MAX(0,I22-I21*$C$17)*Inputs!$C$11,0) -> 0 | J33: =IF(AND($C$13=0,J$19=$C$15),J22-J21*($C$17+$C$11)-MAX(0,J22-J21*$C$17)*Inputs!$C$11,0) -> 0 | K33: =IF(AND($C$13=0,K$19=$C$15),K22-K21*($C$17+$C$11)-MAX(0,K22-K21*$C$17)*Inputs!$C$11,0) -> 0 | ... AV33: =IF(AND($C$13=0,AV$19=$C$15),AV22-AV21*($C$17+$C$11)-MAX(0,AV22-AV21*$C$17)*Inputs!$C$11,0) -> 0
B34: PV of terminal value | D34: =D33*(1+$C$16)/($C$12-$C$16)*D31 -> 0 | E34: =E33*(1+$C$16)/($C$12-$C$16)*E31 -> 0 | F34: =F33*(1+$C$16)/($C$12-$C$16)*F31 -> 0 | G34: =G33*(1+$C$16)/($C$12-$C$16)*G31 -> 0 | H34: =H33*(1+$C$16)/($C$12-$C$16)*H31 -> 14874.193 | I34: =I33*(1+$C$16)/($C$12-$C$16)*I31 -> 0 | J34: =J33*(1+$C$16)/($C$12-$C$16)*J31 -> 0 | K34: =K33*(1+$C$16)/($C$12-$C$16)*K31 -> 0 | ... AV34: =AV33*(1+$C$16)/($C$12-$C$16)*AV31 -> 0
B36: PV of explicit / concession-life cash flows | C36: =SUM($D$32:$AV$32) -> 4167.9708
B37: PV of terminal value | C37: =SUM($D$34:$AV$34) -> 14874.193
B38: ENTERPRISE VALUE — VINCI Energies (100%) | C38: =C36+C37 -> 19042.164
B39: Terminal value as % of block EV | C39: =IF(C38=0,0,C37/C38) -> 0.78111885
B40: Implied EV / FY2026E EBITDA | C40: =IF(D22=0,0,C38/D22) -> 8.859419
B41: Terminal FCF base (for sensitivity) | C41: =SUM($D$33:$AV$33) -> 1071.7363
B42: Terminal discount period (for sensitivity) | C42: =SUMPRODUCT(($D$19:$AV$19=$C$15)*$D$30:$AV$30) -> 4.0082192
B43: Check: WACC > g and no cash flow after concession end | C43: =IF(AND($C$12>$C$16,SUMPRODUCT(($D$19:$AV$19>YEAR($C$14))*($C$13=1)*ABS($D$29:$AV$29))=0),"OK","REVISAR") -> OK
B46: Cobra IS
B47: Base revenue FY2025 (EUR m) | C47: 8004 | D47: FY2025 segment: revenue 8,004, EBITDA 786, D&A 171, capex 1,232 operating + 327 growth (19.5% of revenue — renewables build-out, Zero-e). ASSUMPTION: explicit capex 12% (build-out moderates), 3% in TV. The EBITDA from renewables being built is not modelled explicitly → value likely understated. WACC 9.0% (EPC + emerging-market exposure; Vinci uses 12.5% pre-tax).
B48: Revenue growth FY2026 | C48: 0.06
B49: Revenue growth FY2027+ | C49: 0.05
B50: EBITDA margin (CFO before tax & financing / revenue) | C50: 0.0982
B51: D&A % revenue | C51: 0.0214
B52: Capex % revenue (operating + growth investments) | C52: 0.12
B53: Lease repayments % revenue | C53: 0.0005
B54: Discount rate (post-tax WACC) | C54: 0.09
B55: Type: 1 = finite concession (TV = 0) · 0 = going concern | C55: 0
B56: Concession end date (finite only) | C56: 46387
B57: Last explicit year (going concern only) | C57: 2030
B58: Terminal growth g (going concern only) | C58: 0.02
B59: Terminal capex % revenue (going concern only) | C59: 0.03
B61: Fiscal year | D61: 2026 | E61: 2027 | F61: 2028 | G61: 2029 | H61: 2030 | I61: 2031 | J61: 2032 | K61: 2033 | L61: 2034 | M61: 2035 | N61: 2036 | O61: 2037 | P61: 2038 | Q61: 2039 | R61: 2040 | S61: 2041 | T61: 2042 | U61: 2043 | V61: 2044 | W61: 2045 | X61: 2046 | Y61: 2047 | Z61: 2048 | AA61: 2049 | AB61: 2050 | AC61: 2051 | AD61: 2052 | AE61: 2053 | AF61: 2054 | AG61: 2055 | AH61: 2056 | AI61: 2057 | AJ61: 2058 | AK61: 2059 | AL61: 2060 | AM61: 2061 | AN61: 2062 | AO61: 2063 | AP61: 2064 | AQ61: 2065 | AR61: 2066 | AS61: 2067 | AT61: 2068 | AU61: 2069 | AV61: 2070
B62: Fraction of year in valuation (after val. date / before concession end) | D62: =IF($C$55=1,MAX(0,MIN(DATE(D$61,12,31),$C$56)-MAX(Inputs!$C$5+1,DATE(D$61,1,1))+1)/365,IF(D$61<=$C$57,(DATE(D$61,12,31)-MAX(Inputs!$C$5+1,DATE(D$61,1,1))+1)/365,0)) -> 0.50410959 | E62: =IF($C$55=1,MAX(0,MIN(DATE(E$61,12,31),$C$56)-MAX(Inputs!$C$5+1,DATE(E$61,1,1))+1)/365,IF(E$61<=$C$57,(DATE(E$61,12,31)-MAX(Inputs!$C$5+1,DATE(E$61,1,1))+1)/365,0)) -> 1 | F62: =IF($C$55=1,MAX(0,MIN(DATE(F$61,12,31),$C$56)-MAX(Inputs!$C$5+1,DATE(F$61,1,1))+1)/365,IF(F$61<=$C$57,(DATE(F$61,12,31)-MAX(Inputs!$C$5+1,DATE(F$61,1,1))+1)/365,0)) -> 1.0027397 | G62: =IF($C$55=1,MAX(0,MIN(DATE(G$61,12,31),$C$56)-MAX(Inputs!$C$5+1,DATE(G$61,1,1))+1)/365,IF(G$61<=$C$57,(DATE(G$61,12,31)-MAX(Inputs!$C$5+1,DATE(G$61,1,1))+1)/365,0)) -> 1 | H62: =IF($C$55=1,MAX(0,MIN(DATE(H$61,12,31),$C$56)-MAX(Inputs!$C$5+1,DATE(H$61,1,1))+1)/365,IF(H$61<=$C$57,(DATE(H$61,12,31)-MAX(Inputs!$C$5+1,DATE(H$61,1,1))+1)/365,0)) -> 1 | I62: =IF($C$55=1,MAX(0,MIN(DATE(I$61,12,31),$C$56)-MAX(Inputs!$C$5+1,DATE(I$61,1,1))+1)/365,IF(I$61<=$C$57,(DATE(I$61,12,31)-MAX(Inputs!$C$5+1,DATE(I$61,1,1))+1)/365,0)) -> 0 | J62: =IF($C$55=1,MAX(0,MIN(DATE(J$61,12,31),$C$56)-MAX(Inputs!$C$5+1,DATE(J$61,1,1))+1)/365,IF(J$61<=$C$57,(DATE(J$61,12,31)-MAX(Inputs!$C$5+1,DATE(J$61,1,1))+1)/365,0)) -> 0 | K62: =IF($C$55=1,MAX(0,MIN(DATE(K$61,12,31),$C$56)-MAX(Inputs!$C$5+1,DATE(K$61,1,1))+1)/365,IF(K$61<=$C$57,(DATE(K$61,12,31)-MAX(Inputs!$C$5+1,DATE(K$61,1,1))+1)/365,0)) -> 0 | ... AV62: =IF($C$55=1,MAX(0,MIN(DATE(AV$61,12,31),$C$56)-MAX(Inputs!$C$5+1,DATE(AV$61,1,1))+1)/365,IF(AV$61<=$C$57,(DATE(AV$61,12,31)-MAX(Inputs!$C$5+1,DATE(AV$61,1,1))+1)/365,0)) -> 0
B63: Revenue (full-year run-rate) | D63: =$C$47*(1+$C$48) -> 8484.24 | E63: =D63*(1+$C$49) -> 8908.452 | F63: =E63*(1+$C$49) -> 9353.8746 | G63: =F63*(1+$C$49) -> 9821.5683 | H63: =G63*(1+$C$49) -> 10312.647 | I63: =H63*(1+$C$49) -> 10828.279 | J63: =I63*(1+$C$49) -> 11369.693 | K63: =J63*(1+$C$49) -> 11938.178 | L63: =K63*(1+$C$49) -> 12535.087 | ... AV63: =AU63*(1+$C$49) -> 72600.917
B64: EBITDA | D64: =D63*$C$50 -> 833.15237 | E64: =E63*$C$50 -> 874.80999 | F64: =F63*$C$50 -> 918.55049 | G64: =G63*$C$50 -> 964.47801 | H64: =H63*$C$50 -> 1012.7019 | I64: =I63*$C$50 -> 1063.337 | J64: =J63*$C$50 -> 1116.5039 | K64: =K63*$C$50 -> 1172.329 | ... AV64: =AV63*$C$50 -> 7129.41
B65: D&A | D65: =-D63*$C$51 -> -181.56274 | E65: =-E63*$C$51 -> -190.64087 | F65: =-F63*$C$51 -> -200.17292 | G65: =-G63*$C$51 -> -210.18156 | H65: =-H63*$C$51 -> -220.69064 | I65: =-I63*$C$51 -> -231.72517 | J65: =-J63*$C$51 -> -243.31143 | K65: =-K63*$C$51 -> -255.477 | ... AV65: =-AV63*$C$51 -> -1553.6596
B66: EBIT | D66: =D64+D65 -> 651.58963 | E66: =E64+E65 -> 684.16911 | F66: =F64+F65 -> 718.37757 | G66: =G64+G65 -> 754.29645 | H66: =H64+H65 -> 792.01127 | I66: =I64+I65 -> 831.61183 | J66: =J64+J65 -> 873.19243 | K66: =K64+K65 -> 916.85205 | ... AV66: =AV64+AV65 -> 5575.7504
B67: Tax rate | D67: =IF(D$61=2026,Inputs!$C$10,Inputs!$C$11) -> 0.348 | E67: =IF(E$61=2026,Inputs!$C$10,Inputs!$C$11) -> 0.258 | F67: =IF(F$61=2026,Inputs!$C$10,Inputs!$C$11) -> 0.258 | G67: =IF(G$61=2026,Inputs!$C$10,Inputs!$C$11) -> 0.258 | H67: =IF(H$61=2026,Inputs!$C$10,Inputs!$C$11) -> 0.258 | I67: =IF(I$61=2026,Inputs!$C$10,Inputs!$C$11) -> 0.258 | J67: =IF(J$61=2026,Inputs!$C$10,Inputs!$C$11) -> 0.258 | K67: =IF(K$61=2026,Inputs!$C$10,Inputs!$C$11) -> 0.258 | ... AV67: =IF(AV$61=2026,Inputs!$C$10,Inputs!$C$11) -> 0.258
B68: Tax on EBIT | D68: =-MAX(0,D66)*D67 -> -226.75319 | E68: =-MAX(0,E66)*E67 -> -176.51563 | F68: =-MAX(0,F66)*F67 -> -185.34141 | G68: =-MAX(0,G66)*G67 -> -194.60848 | H68: =-MAX(0,H66)*H67 -> -204.33891 | I68: =-MAX(0,I66)*I67 -> -214.55585 | J68: =-MAX(0,J66)*J67 -> -225.28365 | K68: =-MAX(0,K66)*K67 -> -236.54783 | ... AV68: =-MAX(0,AV66)*AV67 -> -1438.5436
B69: Capex | D69: =-D63*$C$52 -> -1018.1088 | E69: =-E63*$C$52 -> -1069.0142 | F69: =-F63*$C$52 -> -1122.465 | G69: =-G63*$C$52 -> -1178.5882 | H69: =-H63*$C$52 -> -1237.5176 | I69: =-I63*$C$52 -> -1299.3935 | J69: =-J63*$C$52 -> -1364.3632 | K69: =-K63*$C$52 -> -1432.5813 | ... AV69: =-AV63*$C$52 -> -8712.11
B70: Lease repayments | D70: =-D63*$C$53 -> -4.24212 | E70: =-E63*$C$53 -> -4.454226 | F70: =-F63*$C$53 -> -4.6769373 | G70: =-G63*$C$53 -> -4.9107842 | H70: =-H63*$C$53 -> -5.1563234 | I70: =-I63*$C$53 -> -5.4141395 | J70: =-J63*$C$53 -> -5.6848465 | K70: =-K63*$C$53 -> -5.9690888 | ... AV70: =-AV63*$C$53 -> -36.300458
B71: Unlevered FCF in valuation window | D71: =(D64+D68+D69+D70)*D62 -> -209.68526 | E71: =(E64+E68+E69+E70)*E62 -> -375.17411 | F71: =(F64+F68+F69+F70)*F62 -> -395.01208 | G71: =(G64+G68+G69+G70)*G62 -> -413.62946 | H71: =(H64+H68+H69+H70)*H62 -> -434.31093 | I71: =(I64+I68+I69+I70)*I62 -> 0 | J71: =(J64+J68+J69+J70)*J62 -> 0 | K71: =(K64+K68+K69+K70)*K62 -> 0 | ... AV71: =(AV64+AV68+AV69+AV70)*AV62 -> 0
B72: Discount period (mid-period, years) | D72: =((MAX(Inputs!$C$5+1,DATE(D$61,1,1))+DATE(D$61,12,31))/2-Inputs!$C$5)/365 -> 0.25342466 | E72: =((MAX(Inputs!$C$5+1,DATE(E$61,1,1))+DATE(E$61,12,31))/2-Inputs!$C$5)/365 -> 1.0054795 | F72: =((MAX(Inputs!$C$5+1,DATE(F$61,1,1))+DATE(F$61,12,31))/2-Inputs!$C$5)/365 -> 2.0068493 | G72: =((MAX(Inputs!$C$5+1,DATE(G$61,1,1))+DATE(G$61,12,31))/2-Inputs!$C$5)/365 -> 3.0082192 | H72: =((MAX(Inputs!$C$5+1,DATE(H$61,1,1))+DATE(H$61,12,31))/2-Inputs!$C$5)/365 -> 4.0082192 | I72: =((MAX(Inputs!$C$5+1,DATE(I$61,1,1))+DATE(I$61,12,31))/2-Inputs!$C$5)/365 -> 5.0082192 | J72: =((MAX(Inputs!$C$5+1,DATE(J$61,1,1))+DATE(J$61,12,31))/2-Inputs!$C$5)/365 -> 6.009589 | K72: =((MAX(Inputs!$C$5+1,DATE(K$61,1,1))+DATE(K$61,12,31))/2-Inputs!$C$5)/365 -> 7.0109589 | ... AV72: =((MAX(Inputs!$C$5+1,DATE(AV$61,1,1))+DATE(AV$61,12,31))/2-Inputs!$C$5)/365 -> 44.035616
B73: Discount factor | D73: =1/(1+$C$54)^D72 -> 0.9783972 | E73: =1/(1+$C$54)^E72 -> 0.91699808 | F73: =1/(1+$C$54)^F72 -> 0.84118333 | G73: =1/(1+$C$54)^G72 -> 0.77163673 | H73: =1/(1+$C$54)^H72 -> 0.7079236 | I73: =1/(1+$C$54)^I72 -> 0.6494712 | J73: =1/(1+$C$54)^J72 -> 0.5957748 | K73: =1/(1+$C$54)^K72 -> 0.54651786 | ... AV73: =1/(1+$C$54)^AV72 -> 0.022485425
B74: PV of UFCF | D74: =D71*D73 -> -205.15547 | E74: =E71*E73 -> -344.03394 | F74: =F71*F73 -> -332.27758 | G74: =G71*G73 -> -319.17168 | H74: =H71*H73 -> -307.45896 | I74: =I71*I73 -> 0 | J74: =J71*J73 -> 0 | K74: =K71*K73 -> 0 | ... AV74: =AV71*AV73 -> 0
B75: Terminal-year normalised FCF (before growth) | D75: =IF(AND($C$55=0,D$61=$C$57),D64-D63*($C$59+$C$53)-MAX(0,D64-D63*$C$59)*Inputs!$C$11,0) -> 0 | E75: =IF(AND($C$55=0,E$61=$C$57),E64-E63*($C$59+$C$53)-MAX(0,E64-E63*$C$59)*Inputs!$C$11,0) -> 0 | F75: =IF(AND($C$55=0,F$61=$C$57),F64-F63*($C$59+$C$53)-MAX(0,F64-F63*$C$59)*Inputs!$C$11,0) -> 0 | G75: =IF(AND($C$55=0,G$61=$C$57),G64-G63*($C$59+$C$53)-MAX(0,G64-G63*$C$59)*Inputs!$C$11,0) -> 0 | H75: =IF(AND($C$55=0,H$61=$C$57),H64-H63*($C$59+$C$53)-MAX(0,H64-H63*$C$59)*Inputs!$C$11,0) -> 516.70898 | I75: =IF(AND($C$55=0,I$61=$C$57),I64-I63*($C$59+$C$53)-MAX(0,I64-I63*$C$59)*Inputs!$C$11,0) -> 0 | J75: =IF(AND($C$55=0,J$61=$C$57),J64-J63*($C$59+$C$53)-MAX(0,J64-J63*$C$59)*Inputs!$C$11,0) -> 0 | K75: =IF(AND($C$55=0,K$61=$C$57),K64-K63*($C$59+$C$53)-MAX(0,K64-K63*$C$59)*Inputs!$C$11,0) -> 0 | ... AV75: =IF(AND($C$55=0,AV$61=$C$57),AV64-AV63*($C$59+$C$53)-MAX(0,AV64-AV63*$C$59)*Inputs!$C$11,0) -> 0
B76: PV of terminal value | D76: =D75*(1+$C$58)/($C$54-$C$58)*D73 -> 0 | E76: =E75*(1+$C$58)/($C$54-$C$58)*E73 -> 0 | F76: =F75*(1+$C$58)/($C$54-$C$58)*F73 -> 0 | G76: =G75*(1+$C$58)/($C$54-$C$58)*G73 -> 0 | H76: =H75*(1+$C$58)/($C$54-$C$58)*H73 -> 5330.0899 | I76: =I75*(1+$C$58)/($C$54-$C$58)*I73 -> 0 | J76: =J75*(1+$C$58)/($C$54-$C$58)*J73 -> 0 | K76: =K75*(1+$C$58)/($C$54-$C$58)*K73 -> 0 | ... AV76: =AV75*(1+$C$58)/($C$54-$C$58)*AV73 -> 0
B78: PV of explicit / concession-life cash flows | C78: =SUM($D$74:$AV$74) -> -1508.0976
B79: PV of terminal value | C79: =SUM($D$76:$AV$76) -> 5330.0899
B80: ENTERPRISE VALUE — Cobra IS (100%) | C80: =C78+C79 -> 3821.9922
B81: Terminal value as % of block EV | C81: =IF(C80=0,0,C79/C80) -> 1.3945842
B82: Implied EV / FY2026E EBITDA | C82: =IF(D64=0,0,C80/D64) -> 4.5873869
B83: Terminal FCF base (for sensitivity) | C83: =SUM($D$75:$AV$75) -> 516.70898
B84: Terminal discount period (for sensitivity) | C84: =SUMPRODUCT(($D$61:$AV$61=$C$57)*$D$72:$AV$72) -> 4.0082192
B85: Check: WACC > g and no cash flow after concession end | C85: =IF(AND($C$54>$C$58,SUMPRODUCT(($D$61:$AV$61>YEAR($C$56))*($C$55=1)*ABS($D$71:$AV$71))=0),"OK","REVISAR") -> OK
B88: VINCI Construction
B89: Base revenue FY2025 (EUR m) | C89: 32137 | D89: FY2025 segment: revenue 32,137, EBITDA 2,133, D&A 1,106, capex 881 + 29 growth, leases 321. H1 2026 Construction revenue slightly down → −1% FY2026. WACC 8.0%, g 1.5% (cyclical, low-margin).
B90: Revenue growth FY2026 | C90: -0.01
B91: Revenue growth FY2027+ | C91: 0.025
B92: EBITDA margin (CFO before tax & financing / revenue) | C92: 0.0664
B93: D&A % revenue | C93: 0.0344
B94: Capex % revenue (operating + growth investments) | C94: 0.0283
B95: Lease repayments % revenue | C95: 0.01
B96: Discount rate (post-tax WACC) | C96: 0.08
B97: Type: 1 = finite concession (TV = 0) · 0 = going concern | C97: 0
B98: Concession end date (finite only) | C98: 46387
B99: Last explicit year (going concern only) | C99: 2030
B100: Terminal growth g (going concern only) | C100: 0.015
B101: Terminal capex % revenue (going concern only) | C101: 0.03
B103: Fiscal year | D103: 2026 | E103: 2027 | F103: 2028 | G103: 2029 | H103: 2030 | I103: 2031 | J103: 2032 | K103: 2033 | L103: 2034 | M103: 2035 | N103: 2036 | O103: 2037 | P103: 2038 | Q103: 2039 | R103: 2040 | S103: 2041 | T103: 2042 | U103: 2043 | V103: 2044 | W103: 2045 | X103: 2046 | Y103: 2047 | Z103: 2048 | AA103: 2049 | AB103: 2050 | AC103: 2051 | AD103: 2052 | AE103: 2053 | AF103: 2054 | AG103: 2055 | AH103: 2056 | AI103: 2057 | AJ103: 2058 | AK103: 2059 | AL103: 2060 | AM103: 2061 | AN103: 2062 | AO103: 2063 | AP103: 2064 | AQ103: 2065 | AR103: 2066 | AS103: 2067 | AT103: 2068 | AU103: 2069 | AV103: 2070
B104: Fraction of year in valuation (after val. date / before concession end) | D104: =IF($C$97=1,MAX(0,MIN(DATE(D$103,12,31),$C$98)-MAX(Inputs!$C$5+1,DATE(D$103,1,1))+1)/365,IF(D$103<=$C$99,(DATE(D$103,12,31)-MAX(Inputs!$C$5+1,DATE(D$103,1,1))+1)/365,0)) -> 0.50410959 | E104: =IF($C$97=1,MAX(0,MIN(DATE(E$103,12,31),$C$98)-MAX(Inputs!$C$5+1,DATE(E$103,1,1))+1)/365,IF(E$103<=$C$99,(DATE(E$103,12,31)-MAX(Inputs!$C$5+1,DATE(E$103,1,1))+1)/365,0)) -> 1 | F104: =IF($C$97=1,MAX(0,MIN(DATE(F$103,12,31),$C$98)-MAX(Inputs!$C$5+1,DATE(F$103,1,1))+1)/365,IF(F$103<=$C$99,(DATE(F$103,12,31)-MAX(Inputs!$C$5+1,DATE(F$103,1,1))+1)/365,0)) -> 1.0027397 | G104: =IF($C$97=1,MAX(0,MIN(DATE(G$103,12,31),$C$98)-MAX(Inputs!$C$5+1,DATE(G$103,1,1))+1)/365,IF(G$103<=$C$99,(DATE(G$103,12,31)-MAX(Inputs!$C$5+1,DATE(G$103,1,1))+1)/365,0)) -> 1 | H104: =IF($C$97=1,MAX(0,MIN(DATE(H$103,12,31),$C$98)-MAX(Inputs!$C$5+1,DATE(H$103,1,1))+1)/365,IF(H$103<=$C$99,(DATE(H$103,12,31)-MAX(Inputs!$C$5+1,DATE(H$103,1,1))+1)/365,0)) -> 1 | I104: =IF($C$97=1,MAX(0,MIN(DATE(I$103,12,31),$C$98)-MAX(Inputs!$C$5+1,DATE(I$103,1,1))+1)/365,IF(I$103<=$C$99,(DATE(I$103,12,31)-MAX(Inputs!$C$5+1,DATE(I$103,1,1))+1)/365,0)) -> 0 | J104: =IF($C$97=1,MAX(0,MIN(DATE(J$103,12,31),$C$98)-MAX(Inputs!$C$5+1,DATE(J$103,1,1))+1)/365,IF(J$103<=$C$99,(DATE(J$103,12,31)-MAX(Inputs!$C$5+1,DATE(J$103,1,1))+1)/365,0)) -> 0 | K104: =IF($C$97=1,MAX(0,MIN(DATE(K$103,12,31),$C$98)-MAX(Inputs!$C$5+1,DATE(K$103,1,1))+1)/365,IF(K$103<=$C$99,(DATE(K$103,12,31)-MAX(Inputs!$C$5+1,DATE(K$103,1,1))+1)/365,0)) -> 0 | ... AV104: =IF($C$97=1,MAX(0,MIN(DATE(AV$103,12,31),$C$98)-MAX(Inputs!$C$5+1,DATE(AV$103,1,1))+1)/365,IF(AV$103<=$C$99,(DATE(AV$103,12,31)-MAX(Inputs!$C$5+1,DATE(AV$103,1,1))+1)/365,0)) -> 0
B105: Revenue (full-year run-rate) | D105: =$C$89*(1+$C$90) -> 31815.63 | E105: =D105*(1+$C$91) -> 32611.021 | F105: =E105*(1+$C$91) -> 33426.296 | G105: =F105*(1+$C$91) -> 34261.954 | H105: =G105*(1+$C$91) -> 35118.503 | I105: =H105*(1+$C$91) -> 35996.465 | J105: =I105*(1+$C$91) -> 36896.377 | K105: =J105*(1+$C$91) -> 37818.786 | L105: =K105*(1+$C$91) -> 38764.256 | ... AV105: =AU105*(1+$C$91) -> 94295.421
B106: EBITDA | D106: =D105*$C$92 -> 2112.5578 | E106: =E105*$C$92 -> 2165.3718 | F106: =F105*$C$92 -> 2219.5061 | G106: =G105*$C$92 -> 2274.9937 | H106: =H105*$C$92 -> 2331.8686 | I106: =I105*$C$92 -> 2390.1653 | J106: =J105*$C$92 -> 2449.9194 | K106: =K105*$C$92 -> 2511.1674 | ... AV106: =AV105*$C$92 -> 6261.216
B107: D&A | D107: =-D105*$C$93 -> -1094.4577 | E107: =-E105*$C$93 -> -1121.8191 | F107: =-F105*$C$93 -> -1149.8646 | G107: =-G105*$C$93 -> -1178.6112 | H107: =-H105*$C$93 -> -1208.0765 | I107: =-I105*$C$93 -> -1238.2784 | J107: =-J105*$C$93 -> -1269.2354 | K107: =-K105*$C$93 -> -1300.9662 | ... AV107: =-AV105*$C$93 -> -3243.7625
B108: EBIT | D108: =D106+D107 -> 1018.1002 | E108: =E106+E107 -> 1043.5527 | F108: =F106+F107 -> 1069.6415 | G108: =G106+G107 -> 1096.3825 | H108: =H106+H107 -> 1123.7921 | I108: =I106+I107 -> 1151.8869 | J108: =J106+J107 -> 1180.6841 | K108: =K106+K107 -> 1210.2012 | ... AV108: =AV106+AV107 -> 3017.4535
B109: Tax rate | D109: =IF(D$103=2026,Inputs!$C$10,Inputs!$C$11) -> 0.348 | E109: =IF(E$103=2026,Inputs!$C$10,Inputs!$C$11) -> 0.258 | F109: =IF(F$103=2026,Inputs!$C$10,Inputs!$C$11) -> 0.258 | G109: =IF(G$103=2026,Inputs!$C$10,Inputs!$C$11) -> 0.258 | H109: =IF(H$103=2026,Inputs!$C$10,Inputs!$C$11) -> 0.258 | I109: =IF(I$103=2026,Inputs!$C$10,Inputs!$C$11) -> 0.258 | J109: =IF(J$103=2026,Inputs!$C$10,Inputs!$C$11) -> 0.258 | K109: =IF(K$103=2026,Inputs!$C$10,Inputs!$C$11) -> 0.258 | ... AV109: =IF(AV$103=2026,Inputs!$C$10,Inputs!$C$11) -> 0.258
B110: Tax on EBIT | D110: =-MAX(0,D108)*D109 -> -354.29886 | E110: =-MAX(0,E108)*E109 -> -269.23659 | F110: =-MAX(0,F108)*F109 -> -275.9675 | G110: =-MAX(0,G108)*G109 -> -282.86669 | H110: =-MAX(0,H108)*H109 -> -289.93836 | I110: =-MAX(0,I108)*I109 -> -297.18682 | J110: =-MAX(0,J108)*J109 -> -304.61649 | K110: =-MAX(0,K108)*K109 -> -312.2319 | ... AV110: =-MAX(0,AV108)*AV109 -> -778.503
B111: Capex | D111: =-D105*$C$94 -> -900.38233 | E111: =-E105*$C$94 -> -922.89189 | F111: =-F105*$C$94 -> -945.96418 | G111: =-G105*$C$94 -> -969.61329 | H111: =-H105*$C$94 -> -993.85362 | I111: =-I105*$C$94 -> -1018.7 | J111: =-J105*$C$94 -> -1044.1675 | K111: =-K105*$C$94 -> -1070.2716 | ... AV111: =-AV105*$C$94 -> -2668.5604
...

Sheet Historicals
B2: Vinci SA — Historicals & Sources (all figures EUR millions unless noted)
B3: Source: Vinci SA FY2025 Consolidated Financial Statements (year ended 31-Dec-2025), p.3 unless noted
B5: 1. Income Statement (exact Vinci cascade, p.3)
C6: FY2025 | D6: FY2024 | E6: FY2023
B7: Revenue | C7: 74599 | D7: 71623 | E7: 68838
B8: Concession subsidiaries' revenue derived from works | C8: 772 | D8: 837 | E8: 780
B9: Total revenue | C9: 75372 | D9: 72459 | E9: 69619
B10: Check: Revenue + Concession works = Total revenue? | C10: =IF(ABS(C7+C8-C9)<=1,"OK (rounding)","REVIEW") -> OK (rounding) | D10: =IF(ABS(D7+D8-D9)<=1,"OK (rounding)","REVIEW") -> OK (rounding) | E10: =IF(ABS(E7+E8-E9)<=1,"OK (rounding)","REVIEW") -> OK (rounding)
B12: Revenue from ancillary activities | C12: 331 | D12: 308 | E12: 267
B13: Operating expenses | C13: -66145 | D13: -63770 | E13: -61529
B14: Operating income from ordinary activities (EBIT) | C14: 9558 | D14: 8997 | E14: 8357
B15: Check: cascade to EBIT ties out? | C15: =IF(ABS(C9+C12+C13-C14)<=1,"OK","REVIEW") -> OK | D15: =IF(ABS(D9+D12+D13-D14)<=1,"OK","REVIEW") -> OK | E15: =IF(ABS(E9+E12+E13-E14)<=1,"OK","REVIEW") -> OK
B16: EBIT margin % (of Revenue) | C16: =C14/C7 -> 0.12812504 | D16: =D14/D7 -> 0.12561607 | E16: =E14/E7 -> 0.12140097
B18: Share-based payments (IFRS 2) | C18: -567 | D18: -462 | E18: -360
B19: Profit/(loss) of companies accounted for under the equity method | C19: 300 | D19: 219 | E19: 111
B20: Other recurring operating items | C20: 110 | D20: 97 | E20: 68
B21: Recurring operating income | C21: 9401 | D21: 8850 | E21: 8175
B22: Non-recurring operating items | C22: -37 | D22: -68 | E22: -105
B23: Operating income | C23: 9364 | D23: 8783 | E23: 8071
B25: Cost of gross financial debt | C25: -1760 | D25: -1785 | E25: -1363
B26: Financial income from cash investments | C26: 513 | D26: 595 | E26: 469
B27: Cost of net financial debt | C27: -1247 | D27: -1191 | E27: -894
B28: Other financial income and expense | C28: -181 | D28: -217 | E28: -157
B29: Income before tax and profit of equity-method cos. (matches Vinci tax note basis) | C29: =C23+C27+C28-C19 -> 7636 | D29: =D23+D27+D28-D19 -> 7156 | E29: =E23+E27+E28 -> 7020
B30: Income tax expense | C30: -2661 | D30: -2102 | E30: -1917
B31: Effective tax rate (cross-check only, not used in DCF) | C31: =-C30/C29 -> 0.34848088 | D31: =-D30/D29 -> 0.29373952 | E31: =-E30/E29 -> 0.27307692
B32: Net income | C32: 5275 | D32: 5274 | E32: 5102
B33: Net income attributable to non-controlling interests | C33: 372 | D33: 410 | E33: 400
B34: Net income attributable to owners of the parent | C34: 4903 | D34: 4863 | E34: 4702
B36: Depreciation & amortisation (D&A) | C36: 4206 | D36: 3998 | E36: 3799
B37: D&A % of Revenue | C37: =C36/C7 -> 0.056381453 | D37: =D36/D7 -> 0.055820058 | E37: =E36/E7 -> 0.055187542
B38: EBITDA (memo = EBIT + D&A) | C38: =C14+C36 -> 13764 | D38: =D14+D36 -> 12995 | E38: =E14+E36 -> 12156
B39: EBITDA margin % | C39: =C38/C7 -> 0.18450649 | D39: =D38/D7 -> 0.18143613 | E39: =E38/E7 -> 0.17658851
B41: Per-Share Data (memo — for trading comps / share count cross-check, not used in UFCF)
B42: Basic EPS (EUR) | C42: 8.76 | D42: 8.53 | E42: 8.28
B43: Diluted EPS (EUR) | C43: 8.65 | D43: 8.43 | E43: 8.18
B44: Implied basic shares outstanding (mm) — cross-check | C44: =C34/C42 -> 559.7032 | D44: =D34/D42 -> 570.10551 | E44: =E34/E42 -> 567.8744
B45: Implied diluted shares outstanding (mm) — cross-check | C45: =C34/C43 -> 566.82081 | D45: =D34/D43 -> 576.86833 | E45: =E34/E43 -> 574.81663
B47: 1b. Tax Rate — Methodology & Sourcing
B48: French theoretical CIT rate (excl. exceptional contribution) — per Vinci's own tax note | C48: 0.258
B49: Large-company exceptional surtax — applies? (Vinci turnover vs. threshold) | C49: YES — turnover >EUR 3bn tier
B50: Vinci's own disclosed effective tax rate, FY2025 (incl. exceptional contribution) | C50: 0.348
B51: Confirmed: same elevated rate continues into FY2026 (per Vinci's own guidance) | C51: "around 36%" per Vinci press release
B52: Cross-check: FY2024 vs FY2025 effective rate jump consistent with new surtax? | C52: =C31 -> 0.34848088 | D52: =D31 -> 0.29373952 | E52: =E31 -> 0.27307692
B53: Recommended marginal rate for DCF (near-term forecast years, while surtax is in force) | C53: 0.348
B54: Recommended marginal rate for DCF (terminal/long-run years) | C54: 0.258
B56: 2. Balance Sheet
C57: FY2025 | D57: FY2024 | E57: FY2023
B58: Non-current assets
B59: Concession intangible assets | C59: 29007 | D59: 29672 | E59: 29000
B60: Goodwill | C60: 20177 | D60: 19519 | E60: 17577
B61: Other intangible assets | C61: 11258 | D61: 11786 | E61: 8038
B62: Property, plant and equipment (PP&E) | C62: 16681 | D62: 15300 | E62: 13012
B63: Investments in companies under the equity method | C63: 1995 | D63: 2105 | E63: 1267
B64: Other non-current financial assets | C64: 2909 | D64: 2743 | E64: 2646
B65: Derivative financial instruments (non-current assets) | C65: 151 | D65: 167 | E65: 125
B66: Deferred tax assets | C66: 1333 | D66: 1268 | E66: 1122
B67: Total non-current assets | C67: =SUM(C59:C66) -> 83511 | D67: =SUM(D59:D66) -> 82560 | E67: =SUM(E59:E66) -> 72787
B69: Current assets
B70: Inventories and work in progress | C70: 1700 | D70: 1772 | E70: 1878
B71: Trade and other receivables | C71: 19504 | D71: 19365 | E71: 18698
B72: Other current assets | C72: 8265 | D72: 8333 | E72: 7798
B73: Current tax assets | C73: 419 | D73: 415 | E73: 351
B74: Other current financial assets | C74: 119 | D74: 76 | E74: 79
B75: Derivative financial instruments (current assets) | C75: 188 | D75: 137 | E75: 94
B76: Cash management financial assets | C76: 1244 | D76: 895 | E76: 545
B77: Cash and cash equivalents | C77: 17254 | D77: 15199 | E77: 15627
B78: Total current assets | C78: =SUM(C70:C77) -> 48693 | D78: =SUM(D70:D77) -> 46192 | E78: =SUM(E70:E77) -> 45070
B79: Assets held for sale | C79: 860 | D79: 739 | E79: 702
B80: TOTAL ASSETS | C80: =C67+SUM(C70:C77)+C79 -> 133064 | D80: =D67+SUM(D70:D77)+D79 -> 129491 | E80: =E67+SUM(E70:E77)+E79 -> 118559
B82: Equity
B83: Share capital | C83: 1455 | D83: 1455 | E83: 1473
B84: Share premium | C84: 14811 | D84: 14059 | E84: 13407
B85: Treasury shares | C85: -2796 | D85: -1566 | E85: -1419
B86: Consolidated reserves | C86: 13454 | D86: 11724 | E86: 10422
B87: Currency translation reserves | C87: -906 | D87: -32 | E87: -91
B88: Net income attributable to owners of the parent | C88: 4903 | D88: 4863 | E88: 4702
B89: Amounts recognised directly in equity | C89: -168 | D89: -555 | E89: -382
B90: Equity attributable to owners of the parent | C90: =SUM(C83:C89) -> 30753 | D90: =SUM(D83:D89) -> 29948 | E90: =SUM(E83:E89) -> 28112
B91: Equity attributable to non-controlling interests | C91: 3576 | D91: 4085 | E91: 3928
B92: Total equity | C92: =SUM(C83:C89)+C91 -> 34329 | D92: =SUM(D83:D89)+D91 -> 34033 | E92: =SUM(E83:E89)+E91 -> 32040
B94: Non-current liabilities
B95: Non-current provisions | C95: 1068 | D95: 1011 | E95: 1127
B96: Provisions for employee benefits | C96: 1169 | D96: 1224 | E96: 1176
B97: Bonds | C97: 24787 | D97: 24454 | E97: 22048
B98: Other loans and borrowings | C98: 5185 | D98: 4664 | E98: 3785
B99: Derivative financial instruments (non-current liabilities) | C99: 809 | D99: 1014 | E99: 1257
B100: Non-current lease liabilities | C100: 2112 | D100: 1949 | E100: 1675
B101: Other non-current liabilities | C101: 747 | D101: 1117 | E101: 1076
B102: Deferred tax liabilities | C102: 4764 | D102: 4991 | E102: 4030
B103: Total non-current liabilities | C103: =SUM(C95:C102) -> 40641 | D103: =SUM(D95:D102) -> 40424 | E103: =SUM(E95:E102) -> 36174
B105: Current liabilities
B106: Current provisions | C106: 8353 | D106: 7828 | E106: 7304
B107: Trade payables | C107: 14868 | D107: 14463 | E107: 13572
B108: Other current liabilities | C108: 25612 | D108: 24144 | E108: 22431
B109: Current tax liabilities | C109: 709 | D109: 746 | E109: 594
B110: Current lease liabilities | C110: 737 | D110: 639 | E110: 572
B111: Derivative financial instruments (current liabilities) | C111: 399 | D111: 535 | E111: 476
B112: Current borrowings | C112: 6740 | D112: 6152 | E112: 4956
B113: Total current liabilities | C113: =SUM(C106:C112) -> 57418 | D113: =SUM(D106:D112) -> 54507 | E113: =SUM(E106:E112) -> 49905
...
