Workbook

Sheet README
B1: Vinci SA — DCF Valuation
B2: Euronext Paris: DG · EUR millions · Valuation date 4 Jul 2026
B4: Context
B5: Motorway and airport concessions, energy and construction — the clearest fit for the civil-engineering-to-infrastructure angle, operating the same assets an engineer trains to build. Anchor of a three-company European PUI portfolio (with National Grid and Ferrovial).
B7: Methodology
B8: Unlevered DCF off three tied-out years of historicals (FY2023–25). Stub + mid-year discounting, dual terminal value (Gordon Growth + exit multiple) cross-checked, net-debt WACC weights.
B10: Key assumptions
B11: WACC 5.98% (CoE 6.75%, after-tax CoD 3.26%)
B12: Rf 2.99% (ECB AAA 10Y, 2 Jul 2026) · Beta 0.75 · ERP 5.01% (Damodaran, France)
B13: Cost of debt 4.4% pre-tax (Vinci's own disclosed average, FY2025)
B14: Tax 25.8% long-run; 34.8% in FY2026 (French temporary surtax)
B15: Net debt €19,075m · Diluted shares 530.01m
... B33: 1 of 3: Vinci (anchor) · National Grid (regulated utility) · Ferrovial (concessions + SOTP).

Sheet Historicals
B2: Vinci SA — Historicals & Sources (all figures EUR millions unless noted)
B3: Source: Vinci SA FY2025 Consolidated Financial Statements (year ended 31-Dec-2025), p.3 unless noted
B5: 1. Income Statement (exact Vinci cascade, p.3)
C6: FY2025 | D6: FY2024 | E6: FY2023
B7: Revenue | C7: 74599 | D7: 71623 | E7: 68838
B8: Concession subsidiaries' revenue derived from works | C8: 772 | D8: 837 | E8: 780
B9: Total revenue | C9: 75372 | D9: 72459 | E9: 69619
B10: Check: Revenue + Concession works = Total revenue? | C10: =IF(ABS(C7+C8-C9)<=1,"OK (rounding)","REVIEW") -> OK (rounding) | D10: =IF(ABS(D7+D8-D9)<=1,"OK (rounding)","REVIEW") -> OK (rounding) | E10: =IF(ABS(E7+E8-E9)<=1,"OK (rounding)","REVIEW") -> OK (rounding)
B12: Revenue from ancillary activities | C12: 331 | D12: 308 | E12: 267
B13: Operating expenses | C13: -66145 | D13: -63770 | E13: -61529
B14: Operating income from ordinary activities (EBIT) | C14: 9558 | D14: 8997 | E14: 8357
B15: Check: cascade to EBIT ties out? | C15: =IF(ABS(C9+C12+C13-C14)<=1,"OK","REVIEW") -> OK | D15: =IF(ABS(D9+D12+D13-D14)<=1,"OK","REVIEW") -> OK | E15: =IF(ABS(E9+E12+E13-E14)<=1,"OK","REVIEW") -> OK
B16: EBIT margin % (of Revenue) | C16: =C14/C7 -> 0.12812504 | D16: =D14/D7 -> 0.12561607 | E16: =E14/E7 -> 0.12140097
B18: Share-based payments (IFRS 2) | C18: -567 | D18: -462 | E18: -360
B19: Profit/(loss) of companies accounted for under the equity method | C19: 300 | D19: 219 | E19: 111
B20: Other recurring operating items | C20: 110 | D20: 97 | E20: 68
B21: Recurring operating income | C21: 9401 | D21: 8850 | E21: 8175
B22: Non-recurring operating items | C22: -37 | D22: -68 | E22: -105
B23: Operating income | C23: 9364 | D23: 8783 | E23: 8071
B25: Cost of gross financial debt | C25: -1760 | D25: -1785 | E25: -1363
B26: Financial income from cash investments | C26: 513 | D26: 595 | E26: 469
B27: Cost of net financial debt | C27: -1247 | D27: -1191 | E27: -894
B28: Other financial income and expense | C28: -181 | D28: -217 | E28: -157
B29: Income before tax and profit of equity-method cos. (matches Vinci tax note basis) | C29: =C23+C27+C28-C19 -> 7636 | D29: =D23+D27+D28-D19 -> 7156 | E29: =E23+E27+E28 -> 7020
B30: Income tax expense | C30: -2661 | D30: -2102 | E30: -1917
B31: Effective tax rate (cross-check only, not used in DCF) | C31: =-C30/C29 -> 0.34848088 | D31: =-D30/D29 -> 0.29373952 | E31: =-E30/E29 -> 0.27307692
B32: Net income | C32: 5275 | D32: 5274 | E32: 5102
B33: Net income attributable to non-controlling interests | C33: 372 | D33: 410 | E33: 400
B34: Net income attributable to owners of the parent | C34: 4903 | D34: 4863 | E34: 4702
B36: Depreciation & amortisation (D&A) | C36: 4206 | D36: 3998 | E36: 3799
B37: D&A % of Revenue | C37: =C36/C7 -> 0.056381453 | D37: =D36/D7 -> 0.055820058 | E37: =E36/E7 -> 0.055187542
B38: EBITDA (memo = EBIT + D&A) | C38: =C14+C36 -> 13764 | D38: =D14+D36 -> 12995 | E38: =E14+E36 -> 12156
B39: EBITDA margin % | C39: =C38/C7 -> 0.18450649 | D39: =D38/D7 -> 0.18143613 | E39: =E38/E7 -> 0.17658851
B41: Per-Share Data (memo — for trading comps / share count cross-check, not used in UFCF)
B42: Basic EPS (EUR) | C42: 8.76 | D42: 8.53 | E42: 8.28
B43: Diluted EPS (EUR) | C43: 8.65 | D43: 8.43 | E43: 8.18
B44: Implied basic shares outstanding (mm) — cross-check | C44: =C34/C42 -> 559.7032 | D44: =D34/D42 -> 570.10551 | E44: =E34/E42 -> 567.8744
B45: Implied diluted shares outstanding (mm) — cross-check | C45: =C34/C43 -> 566.82081 | D45: =D34/D43 -> 576.86833 | E45: =E34/E43 -> 574.81663
B47: 1b. Tax Rate — Methodology & Sourcing
B48: French theoretical CIT rate (excl. exceptional contribution) — per Vinci's own tax note | C48: 0.258
B49: Large-company exceptional surtax — applies? (Vinci turnover vs. threshold) | C49: YES — turnover >EUR 3bn tier
B50: Vinci's own disclosed effective tax rate, FY2025 (incl. exceptional contribution) | C50: 0.348
B51: Confirmed: same elevated rate continues into FY2026 (per Vinci's own guidance) | C51: "around 36%" per Vinci press release
B52: Cross-check: FY2024 vs FY2025 effective rate jump consistent with new surtax? | C52: =C31 -> 0.34848088 | D52: =D31 -> 0.29373952 | E52: =E31 -> 0.27307692
B53: Recommended marginal rate for DCF (near-term forecast years, while surtax is in force) | C53: 0.348
B54: Recommended marginal rate for DCF (terminal/long-run years) | C54: 0.258
B56: 2. Balance Sheet
C57: FY2025 | D57: FY2024 | E57: FY2023
B58: Non-current assets
B59: Concession intangible assets | C59: 29007 | D59: 29672 | E59: 29000
B60: Goodwill | C60: 20177 | D60: 19519 | E60: 17577
B61: Other intangible assets | C61: 11258 | D61: 11786 | E61: 8038
B62: Property, plant and equipment (PP&E) | C62: 16681 | D62: 15300 | E62: 13012
B63: Investments in companies under the equity method | C63: 1995 | D63: 2105 | E63: 1267
B64: Other non-current financial assets | C64: 2909 | D64: 2743 | E64: 2646
B65: Derivative financial instruments (non-current assets) | C65: 151 | D65: 167 | E65: 125
B66: Deferred tax assets | C66: 1333 | D66: 1268 | E66: 1122
B67: Total non-current assets | C67: =SUM(C59:C66) -> 83511 | D67: =SUM(D59:D66) -> 82560 | E67: =SUM(E59:E66) -> 72787
B69: Current assets
B70: Inventories and work in progress | C70: 1700 | D70: 1772 | E70: 1878
B71: Trade and other receivables | C71: 19504 | D71: 19365 | E71: 18698
B72: Other current assets | C72: 8265 | D72: 8333 | E72: 7798
B73: Current tax assets | C73: 419 | D73: 415 | E73: 351
B74: Other current financial assets | C74: 119 | D74: 76 | E74: 79
B75: Derivative financial instruments (current assets) | C75: 188 | D75: 137 | E75: 94
B76: Cash management financial assets | C76: 1244 | D76: 895 | E76: 545
B77: Cash and cash equivalents | C77: 17254 | D77: 15199 | E77: 15627
B78: Total current assets | C78: =SUM(C70:C77) -> 48693 | D78: =SUM(D70:D77) -> 46192 | E78: =SUM(E70:E77) -> 45070
B79: Assets held for sale | C79: 860 | D79: 739 | E79: 702
B80: TOTAL ASSETS | C80: =C67+SUM(C70:C77)+C79 -> 133064 | D80: =D67+SUM(D70:D77)+D79 -> 129491 | E80: =E67+SUM(E70:E77)+E79 -> 118559
B82: Equity
B83: Share capital | C83: 1455 | D83: 1455 | E83: 1473
B84: Share premium | C84: 14811 | D84: 14059 | E84: 13407
B85: Treasury shares | C85: -2796 | D85: -1566 | E85: -1419
B86: Consolidated reserves | C86: 13454 | D86: 11724 | E86: 10422
B87: Currency translation reserves | C87: -906 | D87: -32 | E87: -91
B88: Net income attributable to owners of the parent | C88: 4903 | D88: 4863 | E88: 4702
B89: Amounts recognised directly in equity | C89: -168 | D89: -555 | E89: -382
B90: Equity attributable to owners of the parent | C90: =SUM(C83:C89) -> 30753 | D90: =SUM(D83:D89) -> 29948 | E90: =SUM(E83:E89) -> 28112
B91: Equity attributable to non-controlling interests | C91: 3576 | D91: 4085 | E91: 3928
B92: Total equity | C92: =SUM(C83:C89)+C91 -> 34329 | D92: =SUM(D83:D89)+D91 -> 34033 | E92: =SUM(E83:E89)+E91 -> 32040
B94: Non-current liabilities
B95: Non-current provisions | C95: 1068 | D95: 1011 | E95: 1127
B96: Provisions for employee benefits | C96: 1169 | D96: 1224 | E96: 1176
B97: Bonds | C97: 24787 | D97: 24454 | E97: 22048
B98: Other loans and borrowings | C98: 5185 | D98: 4664 | E98: 3785
B99: Derivative financial instruments (non-current liabilities) | C99: 809 | D99: 1014 | E99: 1257
B100: Non-current lease liabilities | C100: 2112 | D100: 1949 | E100: 1675
B101: Other non-current liabilities | C101: 747 | D101: 1117 | E101: 1076
B102: Deferred tax liabilities | C102: 4764 | D102: 4991 | E102: 4030
B103: Total non-current liabilities | C103: =SUM(C95:C102) -> 40641 | D103: =SUM(D95:D102) -> 40424 | E103: =SUM(E95:E102) -> 36174
B105: Current liabilities
B106: Current provisions | C106: 8353 | D106: 7828 | E106: 7304
B107: Trade payables | C107: 14868 | D107: 14463 | E107: 13572
B108: Other current liabilities | C108: 25612 | D108: 24144 | E108: 22431
B109: Current tax liabilities | C109: 709 | D109: 746 | E109: 594
B110: Current lease liabilities | C110: 737 | D110: 639 | E110: 572
B111: Derivative financial instruments (current liabilities) | C111: 399 | D111: 535 | E111: 476
B112: Current borrowings | C112: 6740 | D112: 6152 | E112: 4956
B113: Total current liabilities | C113: =SUM(C106:C112) -> 57418 | D113: =SUM(D106:D112) -> 54507 | E113: =SUM(E106:E112) -> 49905
...

Sheet WACC
B2: WACC Buildup
B3: =Historicals!B2 -> Vinci SA — Historicals & Sources (all figures EUR millions unless noted)
B4: Cost of capital assumptions
I5: Source
B6: Cost of debt | C6: =Historicals!C205 -> 0.044 | I6: Vinci's own disclosed average cost of long-term gross financial debt (4.4%, FY2025) — see Historicals Sec.7
B7: Tax rate | C7: =Historicals!C54 -> 0.258 | I7: Long-run French statutory rate (25%) — WACC discounts a perpetual stream, so the LONG-RUN rate is used here, not the ~35% near-term rate reflecting France's temporary FY2025-26 large-company surtax (that surtax is instead applied directly in the DCF tab's explicit-forecast tax schedule).
B8: Cost of debt (after tax) | C8: =C6*(1-C7) -> 0.032648 | I8: Cost of debt x (1 - tax rate)
B10: Risk free rate | C10: 0.02988 | I10: ECB euro-area AAA-rated bond yield curve, spot rate, 10yr tenor, 2-Jul-2026
B11: Beta | C11: =Historicals!C199 -> 0.75 | I11: stockanalysis.com, DG.PA, 5Y monthly (proxy for Bloomberg 2Y weekly convention)
B12: Market risk premium | C12: 0.0501 | I12: Damodaran Country Risk Premium dataset, France, rating-based Total ERP, queried 4-Jul-2026
B13: Cost of equity | C13: =C10+C11*C12 -> 0.067455 | I13: RfR + Beta x MRP
B15: Capital weights (capital structure)
C16: Current | D16: % of total
B18: Equity | C18: =Historicals!C197 -> 67790 | D18: =C18/(C18+C19) -> 0.78040638
B19: Debt (net) | C19: =Historicals!C191 -> 19075 | D19: =1-D18 -> 0.21959362 | I19: NET debt (not gross), matching the WSP reference workbook convention (WACC Done!C19 links to net debt).
B21: Cost of capital (WACC) | C21: =C8*D19+C13*D18 -> 0.059811605
B23: WACC sensitivity to MRP and Beta
D24: Beta
C25: =C21 -> 0.059811605 | D25: =$C$11-0.1 -> 0.65 | E25: =$C$11-0.05 -> 0.7 | F25: =$C$11 -> 0.75 | G25: =$C$11+0.05 -> 0.8 | H25: =$C$11+0.1 -> 0.85
C26: =$C$12-0.005 -> 0.0451 | D26: =$C$8*$D$19+($C$10+D$25*$C26)*$D$18 -> 0.053365448 | E26: =$C$8*$D$19+($C$10+E$25*$C26)*$D$18 -> 0.055125264 | F26: =$C$8*$D$19+($C$10+F$25*$C26)*$D$18 -> 0.056885081 | G26: =$C$8*$D$19+($C$10+G$25*$C26)*$D$18 -> 0.058644897 | H26: =$C$8*$D$19+($C$10+H$25*$C26)*$D$18 -> 0.060404714
B27: Market | C27: =$C$12-0.0025 -> 0.0476 | D27: =$C$8*$D$19+($C$10+D$25*$C27)*$D$18 -> 0.054633608 | E27: =$C$8*$D$19+($C$10+E$25*$C27)*$D$18 -> 0.056490976 | F27: =$C$8*$D$19+($C$10+F$25*$C27)*$D$18 -> 0.058348343 | G27: =$C$8*$D$19+($C$10+G$25*$C27)*$D$18 -> 0.06020571 | H27: =$C$8*$D$19+($C$10+H$25*$C27)*$D$18 -> 0.062063077
B28: Risk | C28: =$C$12 -> 0.0501 | D28: =$C$8*$D$19+($C$10+D$25*$C28)*$D$18 -> 0.055901769 | E28: =$C$8*$D$19+($C$10+E$25*$C28)*$D$18 -> 0.057856687 | F28: =$C$8*$D$19+($C$10+F$25*$C28)*$D$18 -> 0.059811605 | G28: =$C$8*$D$19+($C$10+G$25*$C28)*$D$18 -> 0.061766523 | H28: =$C$8*$D$19+($C$10+H$25*$C28)*$D$18 -> 0.063721441
B29: Premium | C29: =$C$12+0.0025 -> 0.0526 | D29: =$C$8*$D$19+($C$10+D$25*$C29)*$D$18 -> 0.057169929 | E29: =$C$8*$D$19+($C$10+E$25*$C29)*$D$18 -> 0.059222398 | F29: =$C$8*$D$19+($C$10+F$25*$C29)*$D$18 -> 0.061274867 | G29: =$C$8*$D$19+($C$10+G$25*$C29)*$D$18 -> 0.063327336 | H29: =$C$8*$D$19+($C$10+H$25*$C29)*$D$18 -> 0.065379804
C30: =$C$12+0.005 -> 0.0551 | D30: =$C$8*$D$19+($C$10+D$25*$C30)*$D$18 -> 0.05843809 | E30: =$C$8*$D$19+($C$10+E$25*$C30)*$D$18 -> 0.060588109 | F30: =$C$8*$D$19+($C$10+F$25*$C30)*$D$18 -> 0.062738129 | G30: =$C$8*$D$19+($C$10+G$25*$C30)*$D$18 -> 0.064888148 | H30: =$C$8*$D$19+($C$10+H$25*$C30)*$D$18 -> 0.067038168

Sheet DCF
B2: Discounted Cash Flow Valuation
B3: =Historicals!B2 -> Vinci SA — Historicals & Sources (all figures EUR millions unless noted)
B4: Most recent fiscal year end | D4: 46022 | F4: Discount rate (WACC) | H4: =WACC!C21 -> 0.059811605
B5: End of first fiscal year | D5: =EOMONTH(D4,12) -> 46387 | F5: Share price (Public Co) | H5: =Historicals!C195 -> 126.9
B6: Most recent quarter end date | D6: 46022 | F6: Share price date | H6: 46207
B7: Valuation date | D7: 46207 | F7: Midyear adjustment? | H7: 1
B8: Portion of year 1 cash flows in forecast | D8: =YEARFRAC(D7,D5) -> 0.49166667
B10: Unlevered Free Cash Flows
D11: Actual | E11: Forecasts
B12: Fiscal year ended | D12: =D4 -> 46022 | E12: =EOMONTH(D12,12) -> 46387 | F12: =EOMONTH(E12,12) -> 46752 | G12: =EOMONTH(F12,12) -> 47118 | H12: =EOMONTH(G12,12) -> 47483 | I12: =EOMONTH(H12,12) -> 47848
B14: Revenue | D14: =Historicals!C7 -> 74599 | E14: =D14*(1+E15) -> 77582.96 | F14: =E14*(1+F15) -> 80686.278 | G14: =F14*(1+G15) -> 83510.298 | H14: =G14*(1+H15) -> 86433.159 | I14: =H14*(1+I15) -> 89026.153
B15: % growth | E15: 0.04 | F15: 0.04 | G15: 0.035 | H15: 0.035 | I15: 0.03
B16: EBITDA | D16: =D18+D25 -> 13764 | E16: =E17*E14 -> 14275.265 | F16: =F17*F14 -> 14846.275 | G16: =G17*G14 -> 15365.895 | H16: =H17*H14 -> 15990.134 | I16: =I17*I14 -> 16469.838
B17: % margin | D17: =D16/D14 -> 0.18450649 | E17: 0.184 | F17: 0.184 | G17: 0.184 | H17: 0.185 | I17: 0.185
B18: EBIT | D18: =Historicals!C14 -> 9558 | E18: =E19*E14 -> 9930.6189 | F18: =F19*F14 -> 10408.53 | G18: =G19*G14 -> 10856.339 | H18: =H19*H14 -> 11236.311 | I18: =I19*I14 -> 11573.4
B19: % margin | D19: =D18/D14 -> 0.12812504 | E19: 0.128 | F19: 0.129 | G19: 0.13 | H19: 0.13 | I19: 0.13
B21: Tax on EBIT | D21: =D22*D18 -> 3326.184 | E21: =E22*E18 -> 3455.8554 | F21: =F22*F18 -> 2685.4007 | G21: =G22*G18 -> 2800.9354 | H21: =H22*H18 -> 2898.9681 | I21: =I22*I18 -> 2985.9372
B22: Tax rate | D22: =Historicals!C50 -> 0.348 | E22: =Historicals!C53 -> 0.348 | F22: =Historicals!C54 -> 0.258 | G22: =Historicals!C54 -> 0.258 | H22: =Historicals!C54 -> 0.258 | I22: =Historicals!C54 -> 0.258
B23: NOPAT (aka EBIAT) | D23: =D18-D21 -> 6231.816 | E23: =E18-E21 -> 6474.7635 | F23: =F18-F21 -> 7723.1292 | G23: =G18-G21 -> 8055.4034 | H23: =H18-H21 -> 8337.3425 | I23: =I18-I21 -> 8587.4628
B25: Depreciation & amortization | D25: =Historicals!C36 -> 4206 | E25: =E16-E18 -> 4344.6458 | F25: =F16-F18 -> 4437.7453 | G25: =G16-G18 -> 4509.5561 | H25: =H16-H18 -> 4753.8237 | I25: =I16-I18 -> 4896.4384
B26: Changes in net working capital | D26: =C32-D32 -> 2399 | E26: =D32-E32 -> 774.56 | F26: =E32-F32 -> 805.5424 | G26: =F32-G32 -> 733.04358 | H26: =G32-H32 -> 758.70011 | I26: =H32-I32 -> 673.07538
B27: Capital expenditures | D27: =Historicals!C149 -> -4005 | E27: =-(E28*E14) -> -4267.0628 | F27: =-(F28*F14) -> -4437.7453 | G27: =-(G28*G14) -> -4509.5561 | H27: =-(H28*H14) -> -4667.3906 | I27: =-(I28*I14) -> -4945.4028
B28: as % of revenue | D28: =-(D27/D14) -> 0.053687047 | E28: 0.055 | F28: 0.055 | G28: 0.054 | H28: 0.054 | I28: =(I25/I14)*(1+C42) -> 0.05555
B30: Unlevered free cash flows (UFCF) | E30: =E23+E25+E26+E27 -> 7326.9065 | F30: =F23+F25+F26+F27 -> 8528.6716 | G30: =G23+G25+G26+G27 -> 8788.4469 | H30: =H23+H25+H26+H27 -> 9182.4757 | I30: =I23+I25+I26+I27 -> 9211.5737
B32: Net working capital (WC Assets - WC liabilities) | C32: =Historicals!D181 -> -16965 | D32: =Historicals!C181 -> -19364 | E32: =E33*E14 -> -20138.56 | F32: =F33*F14 -> -20944.102 | G32: =G33*G14 -> -21677.146 | H32: =H33*H14 -> -22435.846 | I32: =I33*I14 -> -23108.921
B33: as % of revenue | D33: =D32/D14 -> -0.25957453 | E33: =D33 -> -0.25957453 | F33: =E33 -> -0.25957453 | G33: =F33 -> -0.25957453 | H33: =G33 -> -0.25957453 | I33: =H33 -> -0.25957453
B35: Present value of UFCF on valuation date
D36: Val date | E36: Yr 1 - Stub | F36: Year 2 | G36: Year 3 | H36: Year 4 | I36: Year 5
B37: Date for discounting cash flows | D37: =D7 -> 46207 | E37: =IF($H$7=0,E12,AVERAGE(D37,E12)) -> 46297 | F37: =IF($H$7=0,F12,AVERAGE(E37,F12)) -> 46524.5 | G37: =IF($H$7=0,G12,AVERAGE(F37,G12)) -> 46821.25 | H37: =IF($H$7=0,H12,AVERAGE(G37,H12)) -> 47152.125 | I37: =IF($H$7=0,I12,AVERAGE(H37,I12)) -> 47500.062
B38: Unlevered free cash flows (UFCF) stub adjusted | C38: =D8 -> 0.49166667 | E38: =$C$38*E30 -> 3602.3957 | F38: =F30 -> 8528.6716 | G38: =G30 -> 8788.4469 | H38: =H30 -> 9182.4757 | I38: =I30 -> 9211.5737
B39: Present value of unlevered free cash flows | E39: =E38/(1+$H$4)^((E37-$D$37)/365) -> 3551.1633 | F39: =F38/(1+$H$4)^((F37-$D$37)/365) -> 8108.4138 | G39: =G38/(1+$H$4)^((G37-$D$37)/365) -> 7969.9463 | H39: =H38/(1+$H$4)^((H37-$D$37)/365) -> 7900.109 | I39: =I38/(1+$H$4)^((I37-$D$37)/365) -> 7498.2137
B41: Terminal value - growth in perpetuity approach | E41: Terminal value - EBITDA multiple approach
B42: Long term growth rate | C42: 0.01 | E42: Terminal year EBITDA | I42: =I16 -> 16469.838
B43: =YEAR(I12)&" FCF x (1+g)" -> 2030 FCF x (1+g) | C43: =I30*(1+C42) -> 9303.6895 | E43: EBITDA multiple | I43: 10.5
B44: ="Terminal value in "&YEAR(I12) -> Terminal value in 2030 | C44: =C43/(H4-C42) -> 186777.55 | E44: ="Terminal value in "&YEAR(I12) -> Terminal value in 2030 | I44: =I42*I43 -> 172933.3
B45: Present value of terminal value | C45: =C44/(1+H4)^((I37-D37)/365) -> 152036.78 | E45: Present value of terminal value | I45: =I44/(1+H4)^((I37-D37)/365) -> 140767.57
B46: Present value of stage 1 cash flows | C46: =SUM(E39:I39) -> 35027.846 | E46: Present value of stage 1 cash flows | I46: =C46 -> 35027.846
B47: Total enterprise value (TEV) | C47: =SUM(C45:C46) -> 187064.62 | E47: Enterprise value (stage 1 + 2) | I47: =SUM(I45:I46) -> 175795.42
B49: Terminal value as % of TEV | C49: =C45/$C$47 -> 0.81275002 | E49: Terminal value as % of TEV | I49: =I45/$I$47 -> 0.80074653
B50: Stage 1 cash flows as % of TEV | C50: =C46/$C$47 -> 0.18724998 | E50: Stage 1 cash flows as % of TEV | I50: =I46/$I$47 -> 0.19925347
B51: Implied TV exit EBITDA multiple | C51: =C44/I16 -> 11.340582 | E51: Implied terminal growth rate | I51: =(H4-I38/I44)/(1+I38/I44) -> 0.00621398
B53: Net debt | E53: Shares outstanding
B54: Source doc | C54: FY2025 Consolidated Fin. Statements, p.61
B55: Source date | C55: 46207 | G55: Source doc | H55: Date | I55: Shares
B56: Gross debt and equivalents | E56: Diluted shares (stockanalysis.com) | G56: stockanalysis.com | H56: 46207 | I56: =Historicals!C198 -> 530.01
B57: Debt (gross financial debt) | C57: =-Historicals!C186 -> 36712 | E57: Net diluted shares outstanding | I57: =SUM(I56:I56) -> 530.01
B58: Convertible debt | C58: 0
B59: Preferred stock | C59: 0
B60: Noncontrolling (minority) interests | C60: 0
B61: Net derivative financial instruments | C61: =-Historicals!C189 -> 869
B62: Cash | C62: =Historicals!C188 -> 18506
B63: Equity investments | C63: 0
B65: Net debt | C65: =C57+C58+C59+C60+C61-C62-C63 -> 19075
B67: Valuation
C68: Perpetuity | D68: EBITDA
B69: Enterprise value | C69: =C47 -> 187064.62 | D69: =I47 -> 175795.42
B70: Net debt | C70: =C65 -> 19075 | D70: =C70 -> 19075
B71: Equity value | C71: =C69-C70 -> 167989.62 | D71: =D69-D70 -> 156720.42
B72: Shares outstanding | C72: =I57 -> 530.01 | D72: =C72 -> 530.01
B73: Equity value per share | C73: =C71/C72 -> 316.95557 | D73: =D71/D72 -> 295.69332
B74: Implied upside / (downside) vs. current price | C74: =C73/$H$5-1 -> 1.4976798 | D74: =D73/$H$5-1 -> 1.3301286
B75: Year 1 Multiples | C75: Perpetuity | D75: EBITDA
B76: EV / Revenue | C76: =C69/$E$14 -> 2.411156 | D76: =D69/$E$14 -> 2.2659024
B77: EV / EBITDA | C77: =C69/$E$16 -> 13.104109 | D77: =D69/$E$16 -> 12.314687
B78: EV / EBIT | C78: =C69/$E$18 -> 18.837157 | D78: =D69/$E$18 -> 17.702363
B80: Outputs
D82: Equity value per share
E83: Long term growth rate (g):
D84: =C73 -> 316.95557 | E84: =$C$42-0.01 -> 0 | F84: =$C$42-0.005 -> 0.005 | G84: =$C$42 -> 0.01 | H84: =$C$42+0.005 -> 0.015 | I84: =$C$42+0.01 -> 0.02
D85: =$H$4+0.01 -> 0.069811605 | E85: =((($I$30*(1+E$84))/($D85-E$84))/(1+$D85)^(($I$37-$D$37)/365)+$C$46-$C$65)/$C$72 -> 226.11762 | F85: =((($I$30*(1+F$84))/($D85-F$84))/(1+$D85)^(($I$37-$D$37)/365)+$C$46-$C$65)/$C$72 -> 242.29549 | G85: =((($I$30*(1+G$84))/($D85-G$84))/(1+$D85)^(($I$37-$D$37)/365)+$C$46-$C$65)/$C$72 -> 261.17818 | H85: =((($I$30*(1+H$84))/($D85-H$84))/(1+$D85)^(($I$37-$D$37)/365)+$C$46-$C$65)/$C$72 -> 283.50588 | I85: =((($I$30*(1+I$84))/($D85-I$84))/(1+$D85)^(($I$37-$D$37)/365)+$C$46-$C$65)/$C$72 -> 310.316
D86: =$H$4+0.005 -> 0.064811605 | E86: =((($I$30*(1+E$84))/($D86-E$84))/(1+$D86)^(($I$37-$D$37)/365)+$C$46-$C$65)/$C$72 -> 244.77314 | F86: =((($I$30*(1+F$84))/($D86-F$84))/(1+$D86)^(($I$37-$D$37)/365)+$C$46-$C$65)/$C$72 -> 263.88209 | G86: =((($I$30*(1+G$84))/($D86-G$84))/(1+$D86)^(($I$37-$D$37)/365)+$C$46-$C$65)/$C$72 -> 286.47733 | H86: =((($I$30*(1+H$84))/($D86-H$84))/(1+$D86)^(($I$37-$D$37)/365)+$C$46-$C$65)/$C$72 -> 313.60872 | I86: =((($I$30*(1+I$84))/($D86-I$84))/(1+$D86)^(($I$37-$D$37)/365)+$C$46-$C$65)/$C$72 -> 346.79465
C87: WACC: | D87: =$H$4 -> 0.059811605 | E87: =((($I$30*(1+E$84))/($D87-E$84))/(1+$D87)^(($I$37-$D$37)/365)+$C$46-$C$65)/$C$72 -> 266.63026 | F87: =((($I$30*(1+F$84))/($D87-F$84))/(1+$D87)^(($I$37-$D$37)/365)+$C$46-$C$65)/$C$72 -> 289.49754 | G87: =((($I$30*(1+G$84))/($D87-G$84))/(1+$D87)^(($I$37-$D$37)/365)+$C$46-$C$65)/$C$72 -> 316.95557 | H87: =((($I$30*(1+H$84))/($D87-H$84))/(1+$D87)^(($I$37-$D$37)/365)+$C$46-$C$65)/$C$72 -> 350.54104 | I87: =((($I$30*(1+I$84))/($D87-I$84))/(1+$D87)^(($I$37-$D$37)/365)+$C$46-$C$65)/$C$72 -> 392.5626
D88: =$H$4-0.005 -> 0.054811605 | E88: =((($I$30*(1+E$84))/($D88-E$84))/(1+$D88)^(($I$37-$D$37)/365)+$C$46-$C$65)/$C$72 -> 292.56753 | F88: =((($I$30*(1+F$84))/($D88-F$84))/(1+$D88)^(($I$37-$D$37)/365)+$C$46-$C$65)/$C$72 -> 320.35771 | G88: =((($I$30*(1+G$84))/($D88-G$84))/(1+$D88)^(($I$37-$D$37)/365)+$C$46-$C$65)/$C$72 -> 354.34945 | H88: =((($I$30*(1+H$84))/($D88-H$84))/(1+$D88)^(($I$37-$D$37)/365)+$C$46-$C$65)/$C$72 -> 396.87933 | I88: =((($I$30*(1+I$84))/($D88-I$84))/(1+$D88)^(($I$37-$D$37)/365)+$C$46-$C$65)/$C$72 -> 451.62638
D89: =$H$4-0.01 -> 0.049811605 | E89: =((($I$30*(1+E$84))/($D89-E$84))/(1+$D89)^(($I$37-$D$37)/365)+$C$46-$C$65)/$C$72 -> 323.8163 | F89: =((($I$30*(1+F$84))/($D89-F$84))/(1+$D89)^(($I$37-$D$37)/365)+$C$46-$C$65)/$C$72 -> 358.22119 | G89: =((($I$30*(1+G$84))/($D89-G$84))/(1+$D89)^(($I$37-$D$37)/365)+$C$46-$C$65)/$C$72 -> 401.26801 | H89: =((($I$30*(1+H$84))/($D89-H$84))/(1+$D89)^(($I$37-$D$37)/365)+$C$46-$C$65)/$C$72 -> 456.68048 | I89: =((($I$30*(1+I$84))/($D89-I$84))/(1+$D89)^(($I$37-$D$37)/365)+$C$46-$C$65)/$C$72 -> 530.6805
D91: Equity value per share
E92: Exit EBITDA Multiple
D93: =D73 -> 295.69332 | E93: =$I$43-1 -> 9.5 | F93: =$I$43-0.5 -> 10 | G93: =$I$43 -> 10.5 | H93: =$I$43+0.5 -> 11 | I93: =$I$43+1 -> 11.5
D94: =$H$4+0.01 -> 0.069811605 | E94: =((($I$42*E$93))/(1+$D94)^(($I$37-$D$37)/365)+$C$46-$C$65)/$C$72 -> 262.53533 | F94: =((($I$42*F$93))/(1+$D94)^(($I$37-$D$37)/365)+$C$46-$C$65)/$C$72 -> 274.76881 | G94: =((($I$42*G$93))/(1+$D94)^(($I$37-$D$37)/365)+$C$46-$C$65)/$C$72 -> 287.00229 | H94: =((($I$42*H$93))/(1+$D94)^(($I$37-$D$37)/365)+$C$46-$C$65)/$C$72 -> 299.23578 | I94: =((($I$42*I$93))/(1+$D94)^(($I$37-$D$37)/365)+$C$46-$C$65)/$C$72 -> 311.46926
D95: =$H$4+0.005 -> 0.064811605 | E95: =((($I$42*E$93))/(1+$D95)^(($I$37-$D$37)/365)+$C$46-$C$65)/$C$72 -> 266.42505 | F95: =((($I$42*F$93))/(1+$D95)^(($I$37-$D$37)/365)+$C$46-$C$65)/$C$72 -> 278.86326 | G95: =((($I$42*G$93))/(1+$D95)^(($I$37-$D$37)/365)+$C$46-$C$65)/$C$72 -> 291.30146 | H95: =((($I$42*H$93))/(1+$D95)^(($I$37-$D$37)/365)+$C$46-$C$65)/$C$72 -> 303.73967 | I95: =((($I$42*I$93))/(1+$D95)^(($I$37-$D$37)/365)+$C$46-$C$65)/$C$72 -> 316.17787
C96: WACC: | D96: =$H$4 -> 0.059811605 | E96: =((($I$42*E$93))/(1+$D96)^(($I$37-$D$37)/365)+$C$46-$C$65)/$C$72 -> 270.39864 | F96: =((($I$42*F$93))/(1+$D96)^(($I$37-$D$37)/365)+$C$46-$C$65)/$C$72 -> 283.04598 | G96: =((($I$42*G$93))/(1+$D96)^(($I$37-$D$37)/365)+$C$46-$C$65)/$C$72 -> 295.69332 | H96: =((($I$42*H$93))/(1+$D96)^(($I$37-$D$37)/365)+$C$46-$C$65)/$C$72 -> 308.34066 | I96: =((($I$42*I$93))/(1+$D96)^(($I$37-$D$37)/365)+$C$46-$C$65)/$C$72 -> 320.988
D97: =$H$4-0.005 -> 0.054811605 | E97: =((($I$42*E$93))/(1+$D97)^(($I$37-$D$37)/365)+$C$46-$C$65)/$C$72 -> 274.4583 | F97: =((($I$42*F$93))/(1+$D97)^(($I$37-$D$37)/365)+$C$46-$C$65)/$C$72 -> 287.31931 | G97: =((($I$42*G$93))/(1+$D97)^(($I$37-$D$37)/365)+$C$46-$C$65)/$C$72 -> 300.18032 | H97: =((($I$42*H$93))/(1+$D97)^(($I$37-$D$37)/365)+$C$46-$C$65)/$C$72 -> 313.04133 | I97: =((($I$42*I$93))/(1+$D97)^(($I$37-$D$37)/365)+$C$46-$C$65)/$C$72 -> 325.90234
D98: =$H$4-0.01 -> 0.049811605 | E98: =((($I$42*E$93))/(1+$D98)^(($I$37-$D$37)/365)+$C$46-$C$65)/$C$72 -> 278.60633 | F98: =((($I$42*F$93))/(1+$D98)^(($I$37-$D$37)/365)+$C$46-$C$65)/$C$72 -> 291.68566 | G98: =((($I$42*G$93))/(1+$D98)^(($I$37-$D$37)/365)+$C$46-$C$65)/$C$72 -> 304.76498 | H98: =((($I$42*H$93))/(1+$D98)^(($I$37-$D$37)/365)+$C$46-$C$65)/$C$72 -> 317.84431 | I98: =((($I$42*I$93))/(1+$D98)^(($I$37-$D$37)/365)+$C$46-$C$65)/$C$72 -> 330.92364
B100: Equity value range | G100: Football field
C101: Low | D101: Diff. | E101: High
B102: ="DCF Value at "&TEXT(E93,"0.0x")&"-"&TEXT(I93,"0.0x")&" Exit EBITDA Range at "&TEXT(D96,"0.0%")&" WACC" -> DCF Value at 9.5x-11.5x Exit EBITDA Range at 6.0% WACC | C102: =MIN(E96:I96) -> 270.39864 | D102: =MAX(E96:I96)-C102 -> 50.589367 | E102: =MAX(E96:I96) -> 320.988
B103: ="DCF Value at "&TEXT(E84,"0.0%")&"-"&TEXT(I84,"0.0%")&" Perpetuity Growth Range at "&TEXT(D87,"0.0%")&" WACC" -> DCF Value at 0.0%-2.0% Perpetuity Growth Range at 6.0% WACC | C103: =MIN(E87:I87) -> 266.63026 | D103: =MAX(E87:I87)-C103 -> 125.93234 | E103: =MAX(E87:I87) -> 392.5626
B104: 52 Week Market High/Low | C104: 112.4 | D104: =E104-C104 -> 30.75 | E104: 143.15
B105: Current share price (reference) | C105: =H5 -> 126.9
B108: Reverse-DCF: Market-Implied Long-Term Growth Rate
B109: Current market EV (Market Cap + Net Debt) | C109: =Historicals!C197+Historicals!C191 -> 86865
B110: Implied PV of terminal value (Current EV - Stage 1 PV) | C110: =C109-C46 -> 51837.154
B111: Implied (undiscounted) terminal value | C111: =C110*(1+$H$4)^((I37-D37)/365) -> 63682.07
B112: Market-implied long-term growth rate (g) | C112: =($H$4*C111-I30)/(C111+I30) -> -0.074116846
B115: Model Integrity Checks
B116: Check: TV as % of TEV within normal range (60-90%)? | D116: =IF(AND(C49>=0.6,C49<=0.9),"OK","REVIEW") -> OK
B117: Check: implied exit multiple from Growth method reasonable (<15x)? | D117: =IF(C51<15,"OK","REVIEW") -> OK
B118: Check: implied growth rate from Exit Multiple method reasonable (0%-4%)? | D118: =IF(AND(I51>0,I51<0.04),"OK","REVIEW") -> OK
B119: Check: both methods within 15% of each other? | D119: =IF(ABS(C73/D73-1)<0.15,"OK","REVIEW") -> OK
B120: Check: Net debt ties to Historicals net debt reconciliation? | D120: =IF(ABS(C65-Historicals!C191)<=1,"OK","REVIEW") -> OK
